Workbook

Sheet README
A1: AI Infrastructure Stock Scoring System
A3: PURPOSE
A4: Rank AI supply chain stocks on a 0-100 scale to prioritize which names deserve a deep-dive.
A5: The score is NOT a buy/sell signal. It's a triage tool.
A7: HOW IT WORKS
A8: 6 categories, each scored 0-100, then weighted into a single total.
A9: Each category has 3-5 sub-metrics with thresholds defined on the Methodology sheet.
A11: CATEGORIES & DEFAULT WEIGHTS
A12: Value (20%) - Is the price reasonable vs. fundamentals?
A13: Quality (20%) - Is the business well-run and financially sound?
A14: Growth (15%) - Is the company growing meaningfully?
A15: AI Thesis (20%) - How strong is the AI infrastructure exposure?
... A51: Quarterly: re-run the scores, and grade yourself on whether last quarter's picks worked.

Sheet Weights
A1: Category Weights
A3: Category | B3: Weight (%) | C3: Notes
A4: Value | B4: 0.2 | C4: Is the price reasonable?
A5: Quality | B5: 0.2 | C5: Is the business well-run?
A6: Growth | B6: 0.15 | C6: Is it growing?
A7: AI Thesis | B7: 0.2 | C7: How strong is AI exposure?
A8: Momentum | B8: 0.1 | C8: Are estimates and price improving?
A9: Risk | B9: 0.15 | C9: Concentration / geographic / regulatory
A10: TOTAL | B10: =SUM(B4:B9)
A12: ⚠️ Weights must sum to 100%. Adjust the yellow cells above.

Sheet Methodology
A1: Scoring Methodology - Threshold Bands
A3: Each metric is converted to a 0-100 score using the bands below.
A4: Subscores are computed as the average of the metrics within each category.
A5: Edit the threshold cells (blue) if you want to tighten or loosen any standard.
A7: VALUE | J7: Negative-value note
A8: └ Layer 10 carve-out (rule 10, 2026-05-26): col F holds EV/FCF (statement TTM FCF) | B8: Threshold: | C8: ≤20 → 100 | D8: ≤30 → 90 | E8: ≤40 → 75 | F8: ≤55 → 60 | G8: ≤75 → 45 | H8: ≤100 → 30 | I8: >100 → 15 | J8: Negative FCF → 5. Bands were documented in CLAUDE.md 2026-05-26 but only implemented in formulas 2026-06-12 (rebuild_watchlist_formulas.py).
A9: └ Layer 9 capacity carve-out (rule 13, 2026-06-12): col F holds EV / secured gross MW ($M/MW) | B9: Threshold: | C9: ≤2 → 100 | D9: ≤4 → 90 | E9: ≤6 → 75 | F9: ≤9 → 60 | G9: ≤12 → 45 | H9: ≤18 → 30 | I9: >18 → 15 | J9: Cohort: Layer 9 bitcoin-miner pivots + neoclouds (hyperscalers excluded). MW data + provenance: 00-master/capacity-mw.json. Anchor: ~$9-10M/gross-MW AI DC replacement cost at the 45/60 boundary. IT-load-only disclosures converted ×1.25 (flagged in json).
A10: Forward P/E (lower = better) | B10: Threshold: | C10: ≥0 → 100 | D10: ≥15 → 90 | E10: ≥20 → 75 | F10: ≥25 → 60 | G10: ≥30 → 45 | H10: ≥40 → 30 | I10: ≥60 → 15 | J10: If Fwd P/E < 0 (forward EPS estimate negative — losing money), returns 5 (worst band). Patched 2026-05-18.
A11: EV/EBITDA (lower = better) | B11: Threshold: | C11: ≥0 → 100 | D11: ≥10 → 90 | E11: ≥15 → 75 | F11: ≥20 → 60 | G11: ≥25 → 45 | H11: ≥35 → 30 | I11: ≥50 → 15 | J11: If EV/EBITDA < 0 (negative EBITDA — operations unprofitable), returns 5 (worst band). Patched 2026-05-18.
A12: FCF Yield % (higher = better) | B12: Threshold: | C12: ≥8 → 100 | D12: ≥6 → 90 | E12: ≥4 → 75 | F12: ≥2 → 60 | G12: ≥1 → 45 | H12: ≥0 → 30 | I12: ≥-2 → 15
A13: Price / Sales (lower = better) | I13: ≥25 → 15
A14: PEG Ratio (lower = better) | B14: Threshold: | C14: ≤0.5 → 100 | D14: ≤1.0 → 90 | E14: ≤1.5 → 75 | F14: ≤2.0 → 60 | G14: ≤2.5 → 45 | H14: ≤3.0 → 30 | I14: >3.0 → 15 | J14: PEG = Fwd P/E ÷ EPS Growth %. Undefined when EPS growth ≤ 0 (excluded from avg).
A16: QUALITY
A17: ROIC % (higher = better) | B17: Threshold: | C17: ≥25 → 100 | D17: ≥20 → 90 | E17: ≥15 → 75 | F17: ≥10 → 60 | G17: ≥5 → 45 | H17: ≥0 → 30 | I17: ≥-5 → 15
A18: Gross Margin % (higher = better) | B18: Threshold: | C18: ≥60 → 100 | D18: ≥50 → 90 | E18: ≥40 → 75 | F18: ≥30 → 60 | G18: ≥20 → 45 | H18: ≥10 → 30 | I18: ≥0 → 15
A19: FCF Margin % (higher = better) | I19: ≥-10 → 15
A20: Net Debt / EBITDA (lower = better) | B20: Threshold: | C20: ≥0 → 100 | D20: ≥1 → 90 | E20: ≥2 → 75 | F20: ≥3 → 60 | G20: ≥4 → 45 | H20: ≥5 → 30 | I20: ≥7 → 15 | J20: ND/EBITDA can be negative two ways: (a) net cash with positive EBITDA = 100 (correct); (b) negative EBITDA = treated as 100 (WRONG — see batch_score.py guard that excludes when EBITDA<0).
A22: GROWTH
A23: Revenue 3yr CAGR % (higher = better) | B23: Threshold: | C23: ≥40 → 100 | D23: ≥30 → 90 | E23: ≥20 → 75 | F23: ≥15 → 60 | G23: ≥10 → 45 | H23: ≥5 → 30 | I23: ≥0 → 15
A24: Revenue YoY % most recent qtr | I24: ≥-10 → 15
A25: EPS Growth YoY % | B25: Threshold: | C25: ≥40 → 100 | D25: ≥30 → 90 | E25: ≥20 → 75 | F25: ≥10 → 60 | G25: ≥0 → 45 | H25: ≥-10 → 30 | I25: ≥-25 → 15 | J25: Rule 15 (2026-06-12): blank this input when the YoY change is dominated by disclosed non-operating one-time items (divestiture gains, FV swings) — applied on documented evidence per name, not mechanically on magnitude. First application: GEV (Prolec gain).
A27: AI THESIS (subjective 1-5, score = rating × 20)
A28: AI Revenue % of total (1=<5%, 5=>50%)
A29: Supply Chain Position (1=downstream/commodity, 5=upstream/bottleneck)
A30: Moat Strength (1=none, 5=durable)
A31: Capacity Expansion (1=shrinking, 5=major buildout)
A32: Hyperscaler Exposure (1=none, 5=multiple anchor customers)
A34: MOMENTUM (subjective 1-5 except 50DMA %, which is objective and banded)
A35: EPS Revisions last 90d (1=cuts, 5=raises)
A36: Relative Strength vs Sector (1=lagging, 5=leading)
A37: Insider Activity (1=heavy selling, 3=neutral, 5=buying)
A38: % days above 50-DMA, last 120 trading days (higher = better) | B38: Threshold: | C38: ≥85 → 100 | D38: ≥70 → 90 | E38: ≥55 → 75 | F38: ≥40 → 60 | G38: ≥25 → 40 | H38: <25 → 20 | J38: Added 2026-06-09. Share of last 120 trading days with close > 50-day SMA, from yfinance price history (scripts/momentum_50dma.py). Separates consistent uptrends from one-bounce moves. Names with <60 days of valid history are left blank and flagged.
A40: RISK (subjective 1-5; 5 = LOW risk)
A41: Customer Concentration (1=top customer>50%, 5=diversified)
A42: Geographic/Export Risk (1=high China/export, 5=domestic safe)
A43: Balance Sheet Risk (1=stressed, 5=fortress)
A44: Regulatory/Litigation Risk (1=major overhang, 5=clean)
A45: Disruption Risk / business-model durability (1=AI directly produces output+active erosion, 5=no credible disruption; DEFAULT 5 non-Layer-10) [added 2026-06-17, rule 16]
A47: P1 COHORT-RELATIVE SCORING (2026-07-02, rule 20): EV/EBITDA, FCF-Yield, P/S, ROIC, Gross Margin and FCF Margin are percentile-ranked WITHIN each top-level-layer cohort (min 8 non-null, else the absolute band above is the fallback). Live via recalc_watchlist.recalc(mode=percentile); Value Score (J) and Quality Score (O) are recalc-maintained values. See CLAUDE.md rule 20.

Sheet Watchlist
A1: Ticker | B1: Company | C1: Layer | D1: Last Updated | E1: Fwd P/E | F1: EV/EBITDA | G1: FCF Yield % | H1: P/S | I1: PEG | J1: Value Score | K1: ROIC % | L1: Gross Mgn % | M1: FCF Mgn % | N1: ND/EBITDA | O1: Quality Score | P1: Rev 3y CAGR % | Q1: Rev YoY % | R1: EPS YoY % | S1: Growth Score | T1: AI Rev % | U1: Position | V1: Moat | W1: Capacity | X1: Hypersc. | Y1: AI Score | Z1: EPS Rev | AA1: Rel Str | AB1: Insider | AC1: 50DMA % | AD1: Momentum Score | AE1: Cust Conc | AF1: Geo Risk | AG1: BS Risk | AH1: Reg Risk | AI1: Risk Score | AJ1: TOTAL | AK1: Tier | AL1: Disrupt Risk
A2: BE | B2: Bloom Energy | C2: 01 Power - Distributed | D2: 2026-10-11 | E2: 56.757248 | F2: 205.314 | G2: 0.76 | H2: 26.537407 | I2: =IF(OR(E2="",R2="",R2<=0,E2<0),"",E2/R2) | J2: 30.9 | K2: 7.67 | L2: 31.65 | M2: 20.07 | N2: 0.23 | O2: 67.1 | P2: 19.06 | Q2: 165.5 | R2: 60 | S2: =IFERROR(AVERAGE(IFERROR(IF(P2="","",IF(P2>=40,100,IF(P2>=30,90,IF(P2>=20,75,IF(P2>=15,60,IF(P2>=10,45,IF(P2>=5,30,15))))))),""),IFERROR(IF(Q2="","",IF(Q2>=40,100,IF(Q2>=30,90,IF(Q2>=20,75,IF(Q2>=10,60,IF(Q2>=5,45,IF(Q2>=0,30,15))))))),""),IFERROR(IF(R2="","",IF(R2>=40,100,IF(R2>=30,90,IF(R2>=20,75,IF(R2>=10,60,IF(R2>=0,45,IF(R2>=-10,30,15))))))),"")),"") | T2: 5 | U2: 4 | V2: 4 | W2: 5 | X2: 4 | Y2: =IFERROR((AVERAGE(T2,U2,V2,W2,X2)-1)*25,"") | Z2: 5 | AA2: 5 | AB2: 3 | AC2: 62.5 | AD2: =IFERROR(AVERAGE(IFERROR(IF(Z2="","",Z2*20),""),IFERROR(IF(AA2="","",AA2*20),""),IFERROR(IF(AB2="","",AB2*20),""),IFERROR(IF(AC2="","",IF(AC2>=85,100,IF(AC2>=70,90,IF(AC2>=55,75,IF(AC2>=40,60,IF(AC2>=25,40,20)))))),"")),"") | AE2: 3 | AF2: 4 | AG2: 3 | AH2: 4 | AI2: =IFERROR((AVERAGE(AE2,AF2,AG2,AH2,AL2)-1)*25,"") | AJ2: =IFERROR(J2*Weights!$B$4 + O2*Weights!$B$5 + S2*Weights!$B$6 + Y2*Weights!$B$7 + AD2*Weights!$B$8 + AI2*Weights!$B$9,"") | AK2: =IF(AJ2="","",IF(AJ2>=85,"✓✓✓",IF(AJ2>=70,"✓✓",IF(AJ2>=55,"✓",IF(AJ2>=40,"?","✗"))))) | AL2: 5
A3: CRWV | B3: CoreWeave | C3: 09 Cloud - Neocloud | D3: 2026-10-11 | E3: -45.28402 | F3: 22.6 | G3: -30.16 | H3: 5.9644427 | I3: =IF(OR(E3="",R3="",R3<=0,E3<0),"",E3/R3) | J3: 27.5 | K3: -0.32 | L3: 67.42 | M3: -179.91 | N3: 12.16 | O3: 54.4 | P3: 586.92 | Q3: 112.5 | R3: 80 | S3: =IFERROR(AVERAGE(IFERROR(IF(P3="","",IF(P3>=40,100,IF(P3>=30,90,IF(P3>=20,75,IF(P3>=15,60,IF(P3>=10,45,IF(P3>=5,30,15))))))),""),IFERROR(IF(Q3="","",IF(Q3>=40,100,IF(Q3>=30,90,IF(Q3>=20,75,IF(Q3>=10,60,IF(Q3>=5,45,IF(Q3>=0,30,15))))))),""),IFERROR(IF(R3="","",IF(R3>=40,100,IF(R3>=30,90,IF(R3>=20,75,IF(R3>=10,60,IF(R3>=0,45,IF(R3>=-10,30,15))))))),"")),"") | T3: 5 | U3: 4 | V3: 3 | W3: 5 | X3: 5 | Y3: =IFERROR((AVERAGE(T3,U3,V3,W3,X3)-1)*25,"") | Z3: 5 | AA3: 5 | AB3: 2 | AC3: 46.7 | AD3: =IFERROR(AVERAGE(IFERROR(IF(Z3="","",Z3*20),""),IFERROR(IF(AA3="","",AA3*20),""),IFERROR(IF(AB3="","",AB3*20),""),IFERROR(IF(AC3="","",IF(AC3>=85,100,IF(AC3>=70,90,IF(AC3>=55,75,IF(AC3>=40,60,IF(AC3>=25,40,20)))))),"")),"") | AE3: 2 | AF3: 5 | AG3: 1 | AH3: 4 | AI3: =IFERROR((AVERAGE(AE3,AF3,AG3,AH3,AL3)-1)*25,"") | AJ3: =IFERROR(J3*Weights!$B$4 + O3*Weights!$B$5 + S3*Weights!$B$6 + Y3*Weights!$B$7 + AD3*Weights!$B$8 + AI3*Weights!$B$9,"") | AK3: =IF(AJ3="","",IF(AJ3>=85,"✓✓✓",IF(AJ3>=70,"✓✓",IF(AJ3>=55,"✓",IF(AJ3>=40,"?","✗"))))) | AL3: 5
A4: VRT | B4: Vertiv Holdings | C4: 03 DC Infrastructure | D4: 2026-10-11 | E4: 26.450916 | F4: 35.51 | G4: 3.13 | H4: 8.142046 | I4: =IF(OR(E4="",R4="",R4<=0,E4<0),"",E4/R4) | J4: 51.7 | K4: 21.07 | L4: 38.04 | M4: 25.47 | N4: 0.08 | O4: 80.5 | P4: 21.59 | Q4: 24.1 | R4: 53.5 | S4: =IFERROR(AVERAGE(IFERROR(IF(P4="","",IF(P4>=40,100,IF(P4>=30,90,IF(P4>=20,75,IF(P4>=15,60,IF(P4>=10,45,IF(P4>=5,30,15))))))),""),IFERROR(IF(Q4="","",IF(Q4>=40,100,IF(Q4>=30,90,IF(Q4>=20,75,IF(Q4>=10,60,IF(Q4>=5,45,IF(Q4>=0,30,15))))))),""),IFERROR(IF(R4="","",IF(R4>=40,100,IF(R4>=30,90,IF(R4>=20,75,IF(R4>=10,60,IF(R4>=0,45,IF(R4>=-10,30,15))))))),"")),"") | T4: 4 | U4: 4 | V4: 4 | W4: 4 | X4: 5 | Y4: =IFERROR((AVERAGE(T4,U4,V4,W4,X4)-1)*25,"") | Z4: 5 | AA4: 2 | AB4: 2 | AC4: 30.8 | AD4: =IFERROR(AVERAGE(IFERROR(IF(Z4="","",Z4*20),""),IFERROR(IF(AA4="","",AA4*20),""),IFERROR(IF(AB4="","",AB4*20),""),IFERROR(IF(AC4="","",IF(AC4>=85,100,IF(AC4>=70,90,IF(AC4>=55,75,IF(AC4>=40,60,IF(AC4>=25,40,20)))))),"")),"") | AE4: 4 | AF4: 4 | AG4: 4 | AH4: 5 | AI4: =IFERROR((AVERAGE(AE4,AF4,AG4,AH4,AL4)-1)*25,"") | AJ4: =IFERROR(J4*Weights!$B$4 + O4*Weights!$B$5 + S4*Weights!$B$6 + Y4*Weights!$B$7 + AD4*Weights!$B$8 + AI4*Weights!$B$9,"") | AK4: =IF(AJ4="","",IF(AJ4>=85,"✓✓✓",IF(AJ4>=70,"✓✓",IF(AJ4>=55,"✓",IF(AJ4>=40,"?","✗"))))) | AL4: 5
A5: GEV | B5: GE Vernova | C5: 02 Grid Equipment | D5: 2026-10-11 | E5: 39.759323 | F5: 65.627 | G5: 4.65 | H5: 6.4687634 | I5: =IF(OR(E5="",R5="",R5<=0,E5<0),"",E5/R5) | J5: 31.7 | K5: 7.22 | L5: 20.57 | M5: 30.07 | N5: -2.29 | O5: 58 | P5: 8.68 | Q5: 21.9 | S5: =IFERROR(AVERAGE(IFERROR(IF(P5="","",IF(P5>=40,100,IF(P5>=30,90,IF(P5>=20,75,IF(P5>=15,60,IF(P5>=10,45,IF(P5>=5,30,15))))))),""),IFERROR(IF(Q5="","",IF(Q5>=40,100,IF(Q5>=30,90,IF(Q5>=20,75,IF(Q5>=10,60,IF(Q5>=5,45,IF(Q5>=0,30,15))))))),""),IFERROR(IF(R5="","",IF(R5>=40,100,IF(R5>=30,90,IF(R5>=20,75,IF(R5>=10,60,IF(R5>=0,45,IF(R5>=-10,30,15))))))),"")),"") | T5: 2 | U5: 5 | V5: 5 | W5: 4 | X5: 5 | Y5: =IFERROR((AVERAGE(T5,U5,V5,W5,X5)-1)*25,"") | Z5: 4 | AA5: 4 | AB5: 4 | AC5: 49.2 | AD5: =IFERROR(AVERAGE(IFERROR(IF(Z5="","",Z5*20),""),IFERROR(IF(AA5="","",AA5*20),""),IFERROR(IF(AB5="","",AB5*20),""),IFERROR(IF(AC5="","",IF(AC5>=85,100,IF(AC5>=70,90,IF(AC5>=55,75,IF(AC5>=40,60,IF(AC5>=25,40,20)))))),"")),"") | AE5: 4 | AF5: 4 | AG5: 5 | AH5: 4 | AI5: =IFERROR((AVERAGE(AE5,AF5,AG5,AH5,AL5)-1)*25,"") | AJ5: =IFERROR(J5*Weights!$B$4 + O5*Weights!$B$5 + S5*Weights!$B$6 + Y5*Weights!$B$7 + AD5*Weights!$B$8 + AI5*Weights!$B$9,"") | AK5: =IF(AJ5="","",IF(AJ5>=85,"✓✓✓",IF(AJ5>=70,"✓✓",IF(AJ5>=55,"✓",IF(AJ5>=40,"?","✗"))))) | AL5: 5
A6: MU | B6: Micron Technology | C6: 06 Silicon - Memory | D6: 2026-10-11 | E6: 5.5325235 | F6: 10.944 | G6: 2.25 | H6: 8.741286 | I6: =IF(OR(E6="",R6="",R6<=0,E6<0),"",E6/R6) | J6: 60.3 | K6: 44.18 | L6: 80.72 | M6: 19.65 | N6: -0.35 | O6: 86.8 | P6: 6.71 | Q6: 379.3 | R6: 1077.8 | S6: =IFERROR(AVERAGE(IFERROR(IF(P6="","",IF(P6>=40,100,IF(P6>=30,90,IF(P6>=20,75,IF(P6>=15,60,IF(P6>=10,45,IF(P6>=5,30,15))))))),""),IFERROR(IF(Q6="","",IF(Q6>=40,100,IF(Q6>=30,90,IF(Q6>=20,75,IF(Q6>=10,60,IF(Q6>=5,45,IF(Q6>=0,30,15))))))),""),IFERROR(IF(R6="","",IF(R6>=40,100,IF(R6>=30,90,IF(R6>=20,75,IF(R6>=10,60,IF(R6>=0,45,IF(R6>=-10,30,15))))))),"")),"") | T6: 5 | U6: 4 | V6: 5 | W6: 5 | X6: 5 | Y6: =IFERROR((AVERAGE(T6,U6,V6,W6,X6)-1)*25,"") | Z6: 5 | AA6: 5 | AB6: 3 | AC6: 76.7 | AD6: =IFERROR(AVERAGE(IFERROR(IF(Z6="","",Z6*20),""),IFERROR(IF(AA6="","",AA6*20),""),IFERROR(IF(AB6="","",AB6*20),""),IFERROR(IF(AC6="","",IF(AC6>=85,100,IF(AC6>=70,90,IF(AC6>=55,75,IF(AC6>=40,60,IF(AC6>=25,40,20)))))),"")),"") | AE6: 3 | AF6: 2 | AG6: 5 | AH6: 3 | AI6: =IFERROR((AVERAGE(AE6,AF6,AG6,AH6,AL6)-1)*25,"") | AJ6: =IFERROR(J6*Weights!$B$4 + O6*Weights!$B$5 + S6*Weights!$B$6 + Y6*Weights!$B$7 + AD6*Weights!$B$8 + AI6*Weights!$B$9,"") | AK6: =IF(AJ6="","",IF(AJ6>=85,"✓✓✓",IF(AJ6>=70,"✓✓",IF(AJ6>=55,"✓",IF(AJ6>=40,"?","✗"))))) | AL6: 5
A7: CEG | B7: Constellation Energy Corporation | C7: 01 Power - IPP / Nuclear | D7: 2026-10-11 | E7: 22.37736 | F7: 16.41 | G7: 0.29 | H7: 3.3773074 | I7: =IF(OR(E7="",R7="",R7<=0,E7<0),"",E7/R7) | J7: 50.8 | K7: 3.56 | L7: 22.11 | M7: 0.99 | N7: 3.02 | O7: 44.3 | P7: 1.47 | Q7: 23 | S7: =IFERROR(AVERAGE(IFERROR(IF(P7="","",IF(P7>=40,100,IF(P7>=30,90,IF(P7>=20,75,IF(P7>=15,60,IF(P7>=10,45,IF(P7>=5,30,15))))))),""),IFERROR(IF(Q7="","",IF(Q7>=40,100,IF(Q7>=30,90,IF(Q7>=20,75,IF(Q7>=10,60,IF(Q7>=5,45,IF(Q7>=0,30,15))))))),""),IFERROR(IF(R7="","",IF(R7>=40,100,IF(R7>=30,90,IF(R7>=20,75,IF(R7>=10,60,IF(R7>=0,45,IF(R7>=-10,30,15))))))),"")),"") | T7: 2 | U7: 5 | V7: 4 | W7: 5 | X7: 5 | Y7: =IFERROR((AVERAGE(T7,U7,V7,W7,X7)-1)*25,"") | Z7: 3 | AA7: 2 | AB7: 3 | AC7: 40.8 | AD7: =IFERROR(AVERAGE(IFERROR(IF(Z7="","",Z7*20),""),IFERROR(IF(AA7="","",AA7*20),""),IFERROR(IF(AB7="","",AB7*20),""),IFERROR(IF(AC7="","",IF(AC7>=85,100,IF(AC7>=70,90,IF(AC7>=55,75,IF(AC7>=40,60,IF(AC7>=25,40,20)))))),"")),"") | AE7: 4 | AF7: 5 | AG7: 3 | AH7: 4 | AI7: =IFERROR((AVERAGE(AE7,AF7,AG7,AH7,AL7)-1)*25,"") | AJ7: =IFERROR(J7*Weights!$B$4 + O7*Weights!$B$5 + S7*Weights!$B$6 + Y7*Weights!$B$7 + AD7*Weights!$B$8 + AI7*Weights!$B$9,"") | AK7: =IF(AJ7="","",IF(AJ7>=85,"✓✓✓",IF(AJ7>=70,"✓✓",IF(AJ7>=55,"✓",IF(AJ7>=40,"?","✗"))))) | AL7: 5
A8: NVDA | B8: NVIDIA Corporation | C8: 06 AI Compute Silicon / GPUs / merchant accelerators | D8: 2026-10-11 | E8: 14.828233 | F8: 28.318 | G8: 2.29 | H8: 18.273836 | I8: =IF(OR(E8="",R8="",R8<=0,E8<0),"",E8/R8) | J8: 69.9 | K8: 59.83 | L8: 74.67 | M8: 41.92 | N8: -0.12 | O8: 92.5 | P8: 100.05 | Q8: 105.9 | R8: 125.9 | S8: =IFERROR(AVERAGE(IFERROR(IF(P8="","",IF(P8>=40,100,IF(P8>=30,90,IF(P8>=20,75,IF(P8>=15,60,IF(P8>=10,45,IF(P8>=5,30,15))))))),""),IFERROR(IF(Q8="","",IF(Q8>=40,100,IF(Q8>=30,90,IF(Q8>=20,75,IF(Q8>=10,60,IF(Q8>=5,45,IF(Q8>=0,30,15))))))),""),IFERROR(IF(R8="","",IF(R8>=40,100,IF(R8>=30,90,IF(R8>=20,75,IF(R8>=10,60,IF(R8>=0,45,IF(R8>=-10,30,15))))))),"")),"") | T8: 5 | U8: 5 | V8: 5 | W8: 5 | X8: 5 | Y8: =IFERROR((AVERAGE(T8,U8,V8,W8,X8)-1)*25,"") | Z8: 4 | AA8: 1 | AB8: 3 | AC8: 73.3 | AD8: =IFERROR(AVERAGE(IFERROR(IF(Z8="","",Z8*20),""),IFERROR(IF(AA8="","",AA8*20),""),IFERROR(IF(AB8="","",AB8*20),""),IFERROR(IF(AC8="","",IF(AC8>=85,100,IF(AC8>=70,90,IF(AC8>=55,75,IF(AC8>=40,60,IF(AC8>=25,40,20)))))),"")),"") | AE8: 4 | AF8: 2 | AG8: 5 | AH8: 3 | AI8: =IFERROR((AVERAGE(AE8,AF8,AG8,AH8,AL8)-1)*25,"") | AJ8: =IFERROR(J8*Weights!$B$4 + O8*Weights!$B$5 + S8*Weights!$B$6 + Y8*Weights!$B$7 + AD8*Weights!$B$8 + AI8*Weights!$B$9,"") | AK8: =IF(AJ8="","",IF(AJ8>=85,"✓✓✓",IF(AJ8>=70,"✓✓",IF(AJ8>=55,"✓",IF(AJ8>=40,"?","✗"))))) | AL8: 5
A9: AMD | B9: Advanced Micro Devices, Inc. | C9: 06 AI Compute Silicon / GPUs / merchant accelerators | D9: 2026-10-11 | E9: 38.678555 | F9: 109.341 | G9: 0.85 | H9: 24.033602 | I9: =IF(OR(E9="",R9="",R9<=0,E9<0),"",E9/R9) | J9: 34.4 | K9: 7.66 | L9: 55.72 | M9: 20.34 | N9: -0.92 | O9: 57.8 | P9: 13.64 | Q9: 50.1 | R9: 163.4 | S9: =IFERROR(AVERAGE(IFERROR(IF(P9="","",IF(P9>=40,100,IF(P9>=30,90,IF(P9>=20,75,IF(P9>=15,60,IF(P9>=10,45,IF(P9>=5,30,15))))))),""),IFERROR(IF(Q9="","",IF(Q9>=40,100,IF(Q9>=30,90,IF(Q9>=20,75,IF(Q9>=10,60,IF(Q9>=5,45,IF(Q9>=0,30,15))))))),""),IFERROR(IF(R9="","",IF(R9>=40,100,IF(R9>=30,90,IF(R9>=20,75,IF(R9>=10,60,IF(R9>=0,45,IF(R9>=-10,30,15))))))),"")),"") | T9: 4 | U9: 4 | V9: 5 | W9: 5 | X9: 5 | Y9: =IFERROR((AVERAGE(T9,U9,V9,W9,X9)-1)*25,"") | Z9: 5 | AA9: 5 | AB9: 3 | AC9: 75 | AD9: =IFERROR(AVERAGE(IFERROR(IF(Z9="","",Z9*20),""),IFERROR(IF(AA9="","",AA9*20),""),IFERROR(IF(AB9="","",AB9*20),""),IFERROR(IF(AC9="","",IF(AC9>=85,100,IF(AC9>=70,90,IF(AC9>=55,75,IF(AC9>=40,60,IF(AC9>=25,40,20)))))),"")),"") | AE9: 3 | AF9: 3 | AG9: 5 | AH9: 4 | AI9: =IFERROR((AVERAGE(AE9,AF9,AG9,AH9,AL9)-1)*25,"") | AJ9: =IFERROR(J9*Weights!$B$4 + O9*Weights!$B$5 + S9*Weights!$B$6 + Y9*Weights!$B$7 + AD9*Weights!$B$8 + AI9*Weights!$B$9,"") | AK9: =IF(AJ9="","",IF(AJ9>=85,"✓✓✓",IF(AJ9>=70,"✓✓",IF(AJ9>=55,"✓",IF(AJ9>=40,"?","✗"))))) | AL9: 5
A10: D | B10: Dominion Energy, Inc. | C10: 01 Power Generation / Regulated utilities (data-center geographic exposure) | D10: 2026-10-11 | E10: 16.160536 | F10: 13.599 | G10: -13.63 | H10: 2.9921067 | I10: =IF(OR(E10="",R10="",R10<=0,E10<0),"",E10/R10) | J10: 41.3 | K10: 4 | L10: 46.22 | M10: -40.79 | N10: 6.43 | O10: 39.2 | P10: 5.8 | Q10: 17.6 | R10: -55.3 | S10: =IFERROR(AVERAGE(IFERROR(IF(P10="","",IF(P10>=40,100,IF(P10>=30,90,IF(P10>=20,75,IF(P10>=15,60,IF(P10>=10,45,IF(P10>=5,30,15))))))),""),IFERROR(IF(Q10="","",IF(Q10>=40,100,IF(Q10>=30,90,IF(Q10>=20,75,IF(Q10>=10,60,IF(Q10>=5,45,IF(Q10>=0,30,15))))))),""),IFERROR(IF(R10="","",IF(R10>=40,100,IF(R10>=30,90,IF(R10>=20,75,IF(R10>=10,60,IF(R10>=0,45,IF(R10>=-10,30,15))))))),"")),"") | T10: 2 | U10: 3 | V10: 4 | W10: 5 | X10: 3 | Y10: =IFERROR((AVERAGE(T10,U10,V10,W10,X10)-1)*25,"") | Z10: 3 | AA10: 4 | AB10: 3 | AC10: 52.5 | AD10: =IFERROR(AVERAGE(IFERROR(IF(Z10="","",Z10*20),""),IFERROR(IF(AA10="","",AA10*20),""),IFERROR(IF(AB10="","",AB10*20),""),IFERROR(IF(AC10="","",IF(AC10>=85,100,IF(AC10>=70,90,IF(AC10>=55,75,IF(AC10>=40,60,IF(AC10>=25,40,20)))))),"")),"") | AE10: 5 | AF10: 5 | AG10: 3 | AH10: 2 | AI10: =IFERROR((AVERAGE(AE10,AF10,AG10,AH10,AL10)-1)*25,"") | AJ10: =IFERROR(J10*Weights!$B$4 + O10*Weights!$B$5 + S10*Weights!$B$6 + Y10*Weights!$B$7 + AD10*Weights!$B$8 + AI10*Weights!$B$9,"") | AK10: =IF(AJ10="","",IF(AJ10>=85,"✓✓✓",IF(AJ10>=70,"✓✓",IF(AJ10>=55,"✓",IF(AJ10>=40,"?","✗"))))) | AL10: 5
A11: AEP | B11: American Electric Power Company, Inc. | C11: 01 Power Generation / Regulated utilities (data-center geographic exposure) | D11: 2026-10-11 | E11: 17.910582 | F11: 13.356 | G11: -3.65 | H11: 2.9335017 | I11: =IF(OR(E11="",R11="",R11<=0,E11<0),"",E11/R11) | J11: 49.5 | K11: 4.47 | L11: 46.35 | M11: -10.69 | N11: 5.86 | O11: 43.9 | P11: 3.66 | Q11: 7 | R11: -41.8 | S11: =IFERROR(AVERAGE(IFERROR(IF(P11="","",IF(P11>=40,100,IF(P11>=30,90,IF(P11>=20,75,IF(P11>=15,60,IF(P11>=10,45,IF(P11>=5,30,15))))))),""),IFERROR(IF(Q11="","",IF(Q11>=40,100,IF(Q11>=30,90,IF(Q11>=20,75,IF(Q11>=10,60,IF(Q11>=5,45,IF(Q11>=0,30,15))))))),""),IFERROR(IF(R11="","",IF(R11>=40,100,IF(R11>=30,90,IF(R11>=20,75,IF(R11>=10,60,IF(R11>=0,45,IF(R11>=-10,30,15))))))),"")),"") | T11: 1 | U11: 3 | V11: 4 | W11: 5 | X11: 3 | Y11: =IFERROR((AVERAGE(T11,U11,V11,W11,X11)-1)*25,"") | Z11: 5 | AA11: 4 | AB11: 3 | AC11: 30.8 | AD11: =IFERROR(AVERAGE(IFERROR(IF(Z11="","",Z11*20),""),IFERROR(IF(AA11="","",AA11*20),""),IFERROR(IF(AB11="","",AB11*20),""),IFERROR(IF(AC11="","",IF(AC11>=85,100,IF(AC11>=70,90,IF(AC11>=55,75,IF(AC11>=40,60,IF(AC11>=25,40,20)))))),"")),"") | AE11: 5 | AF11: 5 | AG11: 3 | AH11: 4 | AI11: =IFERROR((AVERAGE(AE11,AF11,AG11,AH11,AL11)-1)*25,"") | AJ11: =IFERROR(J11*Weights!$B$4 + O11*Weights!$B$5 + S11*Weights!$B$6 + Y11*Weights!$B$7 + AD11*Weights!$B$8 + AI11*Weights!$B$9,"") | AK11: =IF(AJ11="","",IF(AJ11>=85,"✓✓✓",IF(AJ11>=70,"✓✓",IF(AJ11>=55,"✓",IF(AJ11>=40,"?","✗"))))) | AL11: 5
A12: DUK | B12: Duke Energy Corporation | C12: 01 Power Generation / Regulated utilities (data-center geographic exposure) | D12: 2026-10-11 | E12: 16.265955 | F12: 11.114 | G12: -3.63 | H12: 2.7726812 | I12: =IF(OR(E12="",R12="",R12<=0,E12<0),"",E12/R12) | J12: 60.5 | K12: 4.2 | L12: 51.97 | M12: -10.06 | N12: 5.51 | O12: 47.1 | P12: 3.87 | Q12: 1.1 | R12: 11 | S12: =IFERROR(AVERAGE(IFERROR(IF(P12="","",IF(P12>=40,100,IF(P12>=30,90,IF(P12>=20,75,IF(P12>=15,60,IF(P12>=10,45,IF(P12>=5,30,15))))))),""),IFERROR(IF(Q12="","",IF(Q12>=40,100,IF(Q12>=30,90,IF(Q12>=20,75,IF(Q12>=10,60,IF(Q12>=5,45,IF(Q12>=0,30,15))))))),""),IFERROR(IF(R12="","",IF(R12>=40,100,IF(R12>=30,90,IF(R12>=20,75,IF(R12>=10,60,IF(R12>=0,45,IF(R12>=-10,30,15))))))),"")),"") | T12: 1 | U12: 3 | V12: 4 | W12: 5 | X12: 3 | Y12: =IFERROR((AVERAGE(T12,U12,V12,W12,X12)-1)*25,"") | Z12: 4 | AA12: 3 | AB12: 3 | AC12: 22.5 | AD12: =IFERROR(AVERAGE(IFERROR(IF(Z12="","",Z12*20),""),IFERROR(IF(AA12="","",AA12*20),""),IFERROR(IF(AB12="","",AB12*20),""),IFERROR(IF(AC12="","",IF(AC12>=85,100,IF(AC12>=70,90,IF(AC12>=55,75,IF(AC12>=40,60,IF(AC12>=25,40,20)))))),"")),"") | AE12: 5 | AF12: 5 | AG12: 3 | AH12: 4 | AI12: =IFERROR((AVERAGE(AE12,AF12,AG12,AH12,AL12)-1)*25,"") | AJ12: =IFERROR(J12*Weights!$B$4 + O12*Weights!$B$5 + S12*Weights!$B$6 + Y12*Weights!$B$7 + AD12*Weights!$B$8 + AI12*Weights!$B$9,"") | AK12: =IF(AJ12="","",IF(AJ12>=85,"✓✓✓",IF(AJ12>=70,"✓✓",IF(AJ12>=55,"✓",IF(AJ12>=40,"?","✗"))))) | AL12: 5
A13: SO | B13: The Southern Company | C13: 01 Power Generation / Regulated utilities (data-center geographic exposure) | D13: 2026-10-11 | E13: 17.502808 | F13: 12.285 | G13: -3.3 | H13: 3.2846277 | I13: =IF(OR(E13="",R13="",R13<=0,E13<0),"",E13/R13) | J13: 44.6 | K13: 4.35 | L13: 48.29 | M13: -10.83 | N13: 5.2 | O13: 47.1 | P13: 0.31 | Q13: 0.1 | R13: 33.4 | S13: =IFERROR(AVERAGE(IFERROR(IF(P13="","",IF(P13>=40,100,IF(P13>=30,90,IF(P13>=20,75,IF(P13>=15,60,IF(P13>=10,45,IF(P13>=5,30,15))))))),""),IFERROR(IF(Q13="","",IF(Q13>=40,100,IF(Q13>=30,90,IF(Q13>=20,75,IF(Q13>=10,60,IF(Q13>=5,45,IF(Q13>=0,30,15))))))),""),IFERROR(IF(R13="","",IF(R13>=40,100,IF(R13>=30,90,IF(R13>=20,75,IF(R13>=10,60,IF(R13>=0,45,IF(R13>=-10,30,15))))))),"")),"") | T13: 1 | U13: 3 | V13: 4 | W13: 5 | X13: 3 | Y13: =IFERROR((AVERAGE(T13,U13,V13,W13,X13)-1)*25,"") | Z13: 2 | AA13: 4 | AB13: 3 | AC13: 29.2 | AD13: =IFERROR(AVERAGE(IFERROR(IF(Z13="","",Z13*20),""),IFERROR(IF(AA13="","",AA13*20),""),IFERROR(IF(AB13="","",AB13*20),""),IFERROR(IF(AC13="","",IF(AC13>=85,100,IF(AC13>=70,90,IF(AC13>=55,75,IF(AC13>=40,60,IF(AC13>=25,40,20)))))),"")),"") | AE13: 5 | AF13: 5 | AG13: 3 | AH13: 4 | AI13: =IFERROR((AVERAGE(AE13,AF13,AG13,AH13,AL13)-1)*25,"") | AJ13: =IFERROR(J13*Weights!$B$4 + O13*Weights!$B$5 + S13*Weights!$B$6 + Y13*Weights!$B$7 + AD13*Weights!$B$8 + AI13*Weights!$B$9,"") | AK13: =IF(AJ13="","",IF(AJ13>=85,"✓✓✓",IF(AJ13>=70,"✓✓",IF(AJ13>=55,"✓",IF(AJ13>=40,"?","✗"))))) | AL13: 5
A14: NEE | B14: NextEra Energy, Inc. | C14: 01 Power Generation / Regulated utilities (data-center geographic exposure) | D14: 2026-10-11 | E14: 17.68144 | F14: 19.125 | G14: 1.89 | H14: 5.623141 | I14: =IF(OR(E14="",R14="",R14<=0,E14<0),"",E14/R14) | J14: 46.9 | K14: 3.99 | L14: 61.02 | M14: 10.62 | N14: 7.35 | O14: 54.4 | P14: 9.36 | Q14: 12.4 | R14: 55 | S14: =IFERROR(AVERAGE(IFERROR(IF(P14="","",IF(P14>=40,100,IF(P14>=30,90,IF(P14>=20,75,IF(P14>=15,60,IF(P14>=10,45,IF(P14>=5,30,15))))))),""),IFERROR(IF(Q14="","",IF(Q14>=40,100,IF(Q14>=30,90,IF(Q14>=20,75,IF(Q14>=10,60,IF(Q14>=5,45,IF(Q14>=0,30,15))))))),""),IFERROR(IF(R14="","",IF(R14>=40,100,IF(R14>=30,90,IF(R14>=20,75,IF(R14>=10,60,IF(R14>=0,45,IF(R14>=-10,30,15))))))),"")),"") | T14: 2 | U14: 4 | V14: 5 | W14: 5 | X14: 5 | Y14: =IFERROR((AVERAGE(T14,U14,V14,W14,X14)-1)*25,"") | Z14: 4 | AA14: 3 | AB14: 3 | AC14: 25.8 | AD14: =IFERROR(AVERAGE(IFERROR(IF(Z14="","",Z14*20),""),IFERROR(IF(AA14="","",AA14*20),""),IFERROR(IF(AB14="","",AB14*20),""),IFERROR(IF(AC14="","",IF(AC14>=85,100,IF(AC14>=70,90,IF(AC14>=55,75,IF(AC14>=40,60,IF(AC14>=25,40,20)))))),"")),"") | AE14: 5 | AF14: 5 | AG14: 3 | AH14: 2 | AI14: =IFERROR((AVERAGE(AE14,AF14,AG14,AH14,AL14)-1)*25,"") | AJ14: =IFERROR(J14*Weights!$B$4 + O14*Weights!$B$5 + S14*Weights!$B$6 + Y14*Weights!$B$7 + AD14*Weights!$B$8 + AI14*Weights!$B$9,"") | AK14: =IF(AJ14="","",IF(AJ14>=85,"✓✓✓",IF(AJ14>=70,"✓✓",IF(AJ14>=55,"✓",IF(AJ14>=40,"?","✗"))))) | AL14: 5
A15: ETR | B15: Entergy Corporation | C15: 01 Power Generation / Regulated utilities (data-center geographic exposure) | D15: 2026-10-11 | E15: 20.139488 | F15: 14.274 | G15: -6.42 | H15: 3.6429832 | I15: =IF(OR(E15="",R15="",R15<=0,E15<0),"",E15/R15) | J15: 34.2 | K15: 3.62 | L15: 47 | M15: -23.37 | N15: 5.56 | O15: 35.5 | P15: -2.02 | Q15: 5.9 | R15: 3.1 | S15: =IFERROR(AVERAGE(IFERROR(IF(P15="","",IF(P15>=40,100,IF(P15>=30,90,IF(P15>=20,75,IF(P15>=15,60,IF(P15>=10,45,IF(P15>=5,30,15))))))),""),IFERROR(IF(Q15="","",IF(Q15>=40,100,IF(Q15>=30,90,IF(Q15>=20,75,IF(Q15>=10,60,IF(Q15>=5,45,IF(Q15>=0,30,15))))))),""),IFERROR(IF(R15="","",IF(R15>=40,100,IF(R15>=30,90,IF(R15>=20,75,IF(R15>=10,60,IF(R15>=0,45,IF(R15>=-10,30,15))))))),"")),"") | T15: 1 | U15: 3 | V15: 4 | W15: 5 | X15: 3 | Y15: =IFERROR((AVERAGE(T15,U15,V15,W15,X15)-1)*25,"") | Z15: 5 | AA15: 4 | AB15: 3 | AC15: 40 | AD15: =IFERROR(AVERAGE(IFERROR(IF(Z15="","",Z15*20),""),IFERROR(IF(AA15="","",AA15*20),""),IFERROR(IF(AB15="","",AB15*20),""),IFERROR(IF(AC15="","",IF(AC15>=85,100,IF(AC15>=70,90,IF(AC15>=55,75,IF(AC15>=40,60,IF(AC15>=25,40,20)))))),"")),"") | AE15: 5 | AF15: 5 | AG15: 3 | AH15: 4 | AI15: =IFERROR((AVERAGE(AE15,AF15,AG15,AH15,AL15)-1)*25,"") | AJ15: =IFERROR(J15*Weights!$B$4 + O15*Weights!$B$5 + S15*Weights!$B$6 + Y15*Weights!$B$7 + AD15*Weights!$B$8 + AI15*Weights!$B$9,"") | AK15: =IF(AJ15="","",IF(AJ15>=85,"✓✓✓",IF(AJ15>=70,"✓✓",IF(AJ15>=55,"✓",IF(AJ15>=40,"?","✗"))))) | AL15: 5
A16: PPL | B16: PPL Corporation | C16: 01 Power Generation / Regulated utilities (data-center geographic exposure) | D16: 2026-10-11 | E16: 16.162142 | F16: 12.129 | G16: -7.73 | H16: 2.7425687 | I16: =IF(OR(E16="",R16="",R16<=0,E16<0),"",E16/R16) | J16: 54.5 | K16: 4.26 | L16: 44.09 | M16: -21.2 | N16: 5.33 | O16: 38.6 | P16: 4.59 | Q16: 4.2 | R16: 25.7 | S16: =IFERROR(AVERAGE(IFERROR(IF(P16="","",IF(P16>=40,100,IF(P16>=30,90,IF(P16>=20,75,IF(P16>=15,60,IF(P16>=10,45,IF(P16>=5,30,15))))))),""),IFERROR(IF(Q16="","",IF(Q16>=40,100,IF(Q16>=30,90,IF(Q16>=20,75,IF(Q16>=10,60,IF(Q16>=5,45,IF(Q16>=0,30,15))))))),""),IFERROR(IF(R16="","",IF(R16>=40,100,IF(R16>=30,90,IF(R16>=20,75,IF(R16>=10,60,IF(R16>=0,45,IF(R16>=-10,30,15))))))),"")),"") | T16: 1 | U16: 3 | V16: 4 | W16: 5 | X16: 3 | Y16: =IFERROR((AVERAGE(T16,U16,V16,W16,X16)-1)*25,"") | Z16: 4 | AA16: 3 | AB16: 3 | AC16: 22.5 | AD16: =IFERROR(AVERAGE(IFERROR(IF(Z16="","",Z16*20),""),IFERROR(IF(AA16="","",AA16*20),""),IFERROR(IF(AB16="","",AB16*20),""),IFERROR(IF(AC16="","",IF(AC16>=85,100,IF(AC16>=70,90,IF(AC16>=55,75,IF(AC16>=40,60,IF(AC16>=25,40,20)))))),"")),"") | AE16: 5 | AF16: 5 | AG16: 3 | AH16: 4 | AI16: =IFERROR((AVERAGE(AE16,AF16,AG16,AH16,AL16)-1)*25,"") | AJ16: =IFERROR(J16*Weights!$B$4 + O16*Weights!$B$5 + S16*Weights!$B$6 + Y16*Weights!$B$7 + AD16*Weights!$B$8 + AI16*Weights!$B$9,"") | AK16: =IF(AJ16="","",IF(AJ16>=85,"✓✓✓",IF(AJ16>=70,"✓✓",IF(AJ16>=55,"✓",IF(AJ16>=40,"?","✗"))))) | AL16: 5
A17: XEL | B17: Xcel Energy Inc. | C17: 01 Power Generation / Regulated utilities (data-center geographic exposure) | D17: 2026-10-11 | E17: 16.258345 | F17: 13.861 | G17: -16.69 | H17: 3.1528733 | I17: =IF(OR(E17="",R17="",R17<=0,E17<0),"",E17/R17) | J17: 49.3 | K17: 3.91 | L17: 46.83 | M17: -52.63 | N17: 6.47 | O17: 33.9 | P17: -1.42 | Q17: -5.1 | R17: 32 | S17: =IFERROR(AVERAGE(IFERROR(IF(P17="","",IF(P17>=40,100,IF(P17>=30,90,IF(P17>=20,75,IF(P17>=15,60,IF(P17>=10,45,IF(P17>=5,30,15))))))),""),IFERROR(IF(Q17="","",IF(Q17>=40,100,IF(Q17>=30,90,IF(Q17>=20,75,IF(Q17>=10,60,IF(Q17>=5,45,IF(Q17>=0,30,15))))))),""),IFERROR(IF(R17="","",IF(R17>=40,100,IF(R17>=30,90,IF(R17>=20,75,IF(R17>=10,60,IF(R17>=0,45,IF(R17>=-10,30,15))))))),"")),"") | T17: 1 | U17: 3 | V17: 4 | W17: 4 | X17: 3 | Y17: =IFERROR((AVERAGE(T17,U17,V17,W17,X17)-1)*25,"") | Z17: 4 | AA17: 3 | AB17: 3 | AC17: 27.5 | AD17: =IFERROR(AVERAGE(IFERROR(IF(Z17="","",Z17*20),""),IFERROR(IF(AA17="","",AA17*20),""),IFERROR(IF(AB17="","",AB17*20),""),IFERROR(IF(AC17="","",IF(AC17>=85,100,IF(AC17>=70,90,IF(AC17>=55,75,IF(AC17>=40,60,IF(AC17>=25,40,20)))))),"")),"") | AE17: 5 | AF17: 5 | AG17: 3 | AH17: 4 | AI17: =IFERROR((AVERAGE(AE17,AF17,AG17,AH17,AL17)-1)*25,"") | AJ17: =IFERROR(J17*Weights!$B$4 + O17*Weights!$B$5 + S17*Weights!$B$6 + Y17*Weights!$B$7 + AD17*Weights!$B$8 + AI17*Weights!$B$9,"") | AK17: =IF(AJ17="","",IF(AJ17>=85,"✓✓✓",IF(AJ17>=70,"✓✓",IF(AJ17>=55,"✓",IF(AJ17>=40,"?","✗"))))) | AL17: 5
A18: VST | B18: Vistra Corp. | C18: 01 Power Generation / Independent Power Producers (IPPs) | D18: 2026-10-11 | E18: 15.502566 | F18: 11.814 | G18: 4.16 | H18: 2.8210688 | I18: =IF(OR(E18="",R18="",R18<=0,E18<0),"",E18/R18) | J18: 71.6 | K18: 9.2 | L18: 38.31 | M18: 11.74 | N18: 3.02 | O18: 65.1 | P18: 8.92 | Q18: -5.5 | S18: =IFERROR(AVERAGE(IFERROR(IF(P18="","",IF(P18>=40,100,IF(P18>=30,90,IF(P18>=20,75,IF(P18>=15,60,IF(P18>=10,45,IF(P18>=5,30,15))))))),""),IFERROR(IF(Q18="","",IF(Q18>=40,100,IF(Q18>=30,90,IF(Q18>=20,75,IF(Q18>=10,60,IF(Q18>=5,45,IF(Q18>=0,30,15))))))),""),IFERROR(IF(R18="","",IF(R18>=40,100,IF(R18>=30,90,IF(R18>=20,75,IF(R18>=10,60,IF(R18>=0,45,IF(R18>=-10,30,15))))))),"")),"") | T18: 2 | U18: 5 | V18: 5 | W18: 5 | X18: 5 | Y18: =IFERROR((AVERAGE(T18,U18,V18,W18,X18)-1)*25,"") | Z18: 4 | AA18: 1 | AB18: 3 | AC18: 36.7 | AD18: =IFERROR(AVERAGE(IFERROR(IF(Z18="","",Z18*20),""),IFERROR(IF(AA18="","",AA18*20),""),IFERROR(IF(AB18="","",AB18*20),""),IFERROR(IF(AC18="","",IF(AC18>=85,100,IF(AC18>=70,90,IF(AC18>=55,75,IF(AC18>=40,60,IF(AC18>=25,40,20)))))),"")),"") | AE18: 4 | AF18: 5 | AG18: 4 | AH18: 4 | AI18: =IFERROR((AVERAGE(AE18,AF18,AG18,AH18,AL18)-1)*25,"") | AJ18: =IFERROR(J18*Weights!$B$4 + O18*Weights!$B$5 + S18*Weights!$B$6 + Y18*Weights!$B$7 + AD18*Weights!$B$8 + AI18*Weights!$B$9,"") | AK18: =IF(AJ18="","",IF(AJ18>=85,"✓✓✓",IF(AJ18>=70,"✓✓",IF(AJ18>=55,"✓",IF(AJ18>=40,"?","✗"))))) | AL18: 5
A19: TLN | B19: Talen Energy Corporation | C19: 01 Power Generation / Independent Power Producers (IPPs) | D19: 2026-10-11 | E19: 12.30933 | F19: 47.237 | G19: 2.48 | H19: 4.7865176 | I19: =IF(OR(E19="",R19="",R19<=0,E19<0),"",E19/R19) | J19: 49.5 | K19: 2.69 | L19: 42.1 | M19: 11.87 | N19: 16.05 | O19: 47.1 | P19: 13.95 | Q19: 111.2 | S19: =IFERROR(AVERAGE(IFERROR(IF(P19="","",IF(P19>=40,100,IF(P19>=30,90,IF(P19>=20,75,IF(P19>=15,60,IF(P19>=10,45,IF(P19>=5,30,15))))))),""),IFERROR(IF(Q19="","",IF(Q19>=40,100,IF(Q19>=30,90,IF(Q19>=20,75,IF(Q19>=10,60,IF(Q19>=5,45,IF(Q19>=0,30,15))))))),""),IFERROR(IF(R19="","",IF(R19>=40,100,IF(R19>=30,90,IF(R19>=20,75,IF(R19>=10,60,IF(R19>=0,45,IF(R19>=-10,30,15))))))),"")),"") | T19: 2 | U19: 5 | V19: 5 | W19: 5 | X19: 4 | Y19: =IFERROR((AVERAGE(T19,U19,V19,W19,X19)-1)*25,"") | Z19: 4 | AA19: 2 | AB19: 3 | AC19: 47.5 | AD19: =IFERROR(AVERAGE(IFERROR(IF(Z19="","",Z19*20),""),IFERROR(IF(AA19="","",AA19*20),""),IFERROR(IF(AB19="","",AB19*20),""),IFERROR(IF(AC19="","",IF(AC19>=85,100,IF(AC19>=70,90,IF(AC19>=55,75,IF(AC19>=40,60,IF(AC19>=25,40,20)))))),"")),"") | AE19: 3 | AF19: 5 | AG19: 2 | AH19: 4 | AI19: =IFERROR((AVERAGE(AE19,AF19,AG19,AH19,AL19)-1)*25,"") | AJ19: =IFERROR(J19*Weights!$B$4 + O19*Weights!$B$5 + S19*Weights!$B$6 + Y19*Weights!$B$7 + AD19*Weights!$B$8 + AI19*Weights!$B$9,"") | AK19: =IF(AJ19="","",IF(AJ19>=85,"✓✓✓",IF(AJ19>=70,"✓✓",IF(AJ19>=55,"✓",IF(AJ19>=40,"?","✗"))))) | AL19: 5
A20: NRG | B20: NRG Energy, Inc. | C20: 01 Power Generation / Independent Power Producers (IPPs) | D20: 2026-10-11 | E20: 9.649501 | F20: 14.382 | G20: 1.39 | H20: 0.6851751 | I20: =IF(OR(E20="",R20="",R20<=0,E20<0),"",E20/R20) | J20: 55.4 | K20: 5.62 | L20: 18.8 | M20: 0.95 | N20: 7.16 | O20: 35.9 | P20: -0.88 | Q20: 11 | R20: -83.3 | S20: =IFERROR(AVERAGE(IFERROR(IF(P20="","",IF(P20>=40,100,IF(P20>=30,90,IF(P20>=20,75,IF(P20>=15,60,IF(P20>=10,45,IF(P20>=5,30,15))))))),""),IFERROR(IF(Q20="","",IF(Q20>=40,100,IF(Q20>=30,90,IF(Q20>=20,75,IF(Q20>=10,60,IF(Q20>=5,45,IF(Q20>=0,30,15))))))),""),IFERROR(IF(R20="","",IF(R20>=40,100,IF(R20>=30,90,IF(R20>=20,75,IF(R20>=10,60,IF(R20>=0,45,IF(R20>=-10,30,15))))))),"")),"") | T20: 1 | U20: 3 | V20: 3 | W20: 4 | X20: 2 | Y20: =IFERROR((AVERAGE(T20,U20,V20,W20,X20)-1)*25,"") | Z20: 5 | AA20: 1 | AB20: 3 | AC20: 14.2 | AD20: =IFERROR(AVERAGE(IFERROR(IF(Z20="","",Z20*20),""),IFERROR(IF(AA20="","",AA20*20),""),IFERROR(IF(AB20="","",AB20*20),""),IFERROR(IF(AC20="","",IF(AC20>=85,100,IF(AC20>=70,90,IF(AC20>=55,75,IF(AC20>=40,60,IF(AC20>=25,40,20)))))),"")),"") | AE20: 4 | AF20: 5 | AG20: 3 | AH20: 4 | AI20: =IFERROR((AVERAGE(AE20,AF20,AG20,AH20,AL20)-1)*25,"") | AJ20: =IFERROR(J20*Weights!$B$4 + O20*Weights!$B$5 + S20*Weights!$B$6 + Y20*Weights!$B$7 + AD20*Weights!$B$8 + AI20*Weights!$B$9,"") | AK20: =IF(AJ20="","",IF(AJ20>=85,"✓✓✓",IF(AJ20>=70,"✓✓",IF(AJ20>=55,"✓",IF(AJ20>=40,"?","✗"))))) | AL20: 5
A21: CCJ | B21: Cameco Corporation | C21: 01 Power Generation / Nuclear-specific | D21: 2026-10-11 | E21: 48.468468 | F21: 68.59 | G21: 1.69 | H21: 15.73 | I21: =IF(OR(E21="",R21="",R21<=0,E21<0),"",E21/R21) | J21: 39.6 | K21: 5.16 | L21: 35.11 | M21: 26.53 | N21: 0.14 | O21: 76 | P21: 23.07 | Q21: -7.2 | R21: -92.1 | S21: =IFERROR(AVERAGE(IFERROR(IF(P21="","",IF(P21>=40,100,IF(P21>=30,90,IF(P21>=20,75,IF(P21>=15,60,IF(P21>=10,45,IF(P21>=5,30,15))))))),""),IFERROR(IF(Q21="","",IF(Q21>=40,100,IF(Q21>=30,90,IF(Q21>=20,75,IF(Q21>=10,60,IF(Q21>=5,45,IF(Q21>=0,30,15))))))),""),IFERROR(IF(R21="","",IF(R21>=40,100,IF(R21>=30,90,IF(R21>=20,75,IF(R21>=10,60,IF(R21>=0,45,IF(R21>=-10,30,15))))))),"")),"") | T21: 1 | U21: 4 | V21: 4 | W21: 4 | X21: 2 | Y21: =IFERROR((AVERAGE(T21,U21,V21,W21,X21)-1)*25,"") | Z21: 4 | AA21: 2 | AB21: 3 | AC21: 31.7 | AD21: =IFERROR(AVERAGE(IFERROR(IF(Z21="","",Z21*20),""),IFERROR(IF(AA21="","",AA21*20),""),IFERROR(IF(AB21="","",AB21*20),""),IFERROR(IF(AC21="","",IF(AC21>=85,100,IF(AC21>=70,90,IF(AC21>=55,75,IF(AC21>=40,60,IF(AC21>=25,40,20)))))),"")),"") | AE21: 5 | AF21: 4 | AG21: 5 | AH21: 4 | AI21: =IFERROR((AVERAGE(AE21,AF21,AG21,AH21,AL21)-1)*25,"") | AJ21: =IFERROR(J21*Weights!$B$4 + O21*Weights!$B$5 + S21*Weights!$B$6 + Y21*Weights!$B$7 + AD21*Weights!$B$8 + AI21*Weights!$B$9,"") | AK21: =IF(AJ21="","",IF(AJ21>=85,"✓✓✓",IF(AJ21>=70,"✓✓",IF(AJ21>=55,"✓",IF(AJ21>=40,"?","✗"))))) | AL21: 5
A22: UEC | B22: Uranium Energy Corp. | C22: 01 Power Generation / Nuclear-specific | D22: 2026-10-11 | E22: -124.18918 | F22: -33.279 | G22: -2.64 | H22: 122.26638 | I22: =IF(OR(E22="",R22="",R22<=0,E22<0),"",E22/R22) | J22: 35.7 | K22: -6.61 | L22: -183.96 | M22: -322.78 | O22: 8.7 | P22: 42.37 | Q22: -59.4 | S22: =IFERROR(AVERAGE(IFERROR(IF(P22="","",IF(P22>=40,100,IF(P22>=30,90,IF(P22>=20,75,IF(P22>=15,60,IF(P22>=10,45,IF(P22>=5,30,15))))))),""),IFERROR(IF(Q22="","",IF(Q22>=40,100,IF(Q22>=30,90,IF(Q22>=20,75,IF(Q22>=10,60,IF(Q22>=5,45,IF(Q22>=0,30,15))))))),""),IFERROR(IF(R22="","",IF(R22>=40,100,IF(R22>=30,90,IF(R22>=20,75,IF(R22>=10,60,IF(R22>=0,45,IF(R22>=-10,30,15))))))),"")),"") | T22: 1 | U22: 2 | V22: 4 | W22: 4 | X22: 1 | Y22: =IFERROR((AVERAGE(T22,U22,V22,W22,X22)-1)*25,"") | Z22: 2 | AA22: 1 | AB22: 3 | AC22: 34.2 | AD22: =IFERROR(AVERAGE(IFERROR(IF(Z22="","",Z22*20),""),IFERROR(IF(AA22="","",AA22*20),""),IFERROR(IF(AB22="","",AB22*20),""),IFERROR(IF(AC22="","",IF(AC22>=85,100,IF(AC22>=70,90,IF(AC22>=55,75,IF(AC22>=40,60,IF(AC22>=25,40,20)))))),"")),"") | AE22: 4 | AF22: 5 | AG22: 5 | AH22: 4 | AI22: =IFERROR((AVERAGE(AE22,AF22,AG22,AH22,AL22)-1)*25,"") | AJ22: =IFERROR(J22*Weights!$B$4 + O22*Weights!$B$5 + S22*Weights!$B$6 + Y22*Weights!$B$7 + AD22*Weights!$B$8 + AI22*Weights!$B$9,"") | AK22: =IF(AJ22="","",IF(AJ22>=85,"✓✓✓",IF(AJ22>=70,"✓✓",IF(AJ22>=55,"✓",IF(AJ22>=40,"?","✗"))))) | AL22: 5
A23: LEU | B23: Centrus Energy Corp. | C23: 01 Power Generation / Nuclear-specific | D23: 2026-10-11 | E23: 37.26289 | F23: 222.264 | G23: -5.62 | H23: 6.1475854 | I23: =IF(OR(E23="",R23="",R23<=0,E23<0),"",E23/R23) | J23: 26.1 | K23: 0.35 | L23: 23.66 | M23: -34.56 | N23: -68.42 | O23: 48.6 | P23: 15.16 | Q23: 14 | R23: -41.9 | S23: =IFERROR(AVERAGE(IFERROR(IF(P23="","",IF(P23>=40,100,IF(P23>=30,90,IF(P23>=20,75,IF(P23>=15,60,IF(P23>=10,45,IF(P23>=5,30,15))))))),""),IFERROR(IF(Q23="","",IF(Q23>=40,100,IF(Q23>=30,90,IF(Q23>=20,75,IF(Q23>=10,60,IF(Q23>=5,45,IF(Q23>=0,30,15))))))),""),IFERROR(IF(R23="","",IF(R23>=40,100,IF(R23>=30,90,IF(R23>=20,75,IF(R23>=10,60,IF(R23>=0,45,IF(R23>=-10,30,15))))))),"")),"") | T23: 1 | U23: 4 | V23: 4 | W23: 5 | X23: 3 | Y23: =IFERROR((AVERAGE(T23,U23,V23,W23,X23)-1)*25,"") | Z23: 3 | AA23: 1 | AB23: 3 | AC23: 35 | AD23: =IFERROR(AVERAGE(IFERROR(IF(Z23="","",Z23*20),""),IFERROR(IF(AA23="","",AA23*20),""),IFERROR(IF(AB23="","",AB23*20),""),IFERROR(IF(AC23="","",IF(AC23>=85,100,IF(AC23>=70,90,IF(AC23>=55,75,IF(AC23>=40,60,IF(AC23>=25,40,20)))))),"")),"") | AE23: 4 | AF23: 5 | AG23: 4 | AH23: 4 | AI23: =IFERROR((AVERAGE(AE23,AF23,AG23,AH23,AL23)-1)*25,"") | AJ23: =IFERROR(J23*Weights!$B$4 + O23*Weights!$B$5 + S23*Weights!$B$6 + Y23*Weights!$B$7 + AD23*Weights!$B$8 + AI23*Weights!$B$9,"") | AK23: =IF(AJ23="","",IF(AJ23>=85,"✓✓✓",IF(AJ23>=70,"✓✓",IF(AJ23>=55,"✓",IF(AJ23>=40,"?","✗"))))) | AL23: 5
A24: BWXT | B24: BWX Technologies, Inc. | C24: 01 Power Generation / Nuclear-specific | D24: 2026-10-11 | E24: 27.50027 | F24: 30.178 | G24: 2.4 | H24: 3.7501717 | I24: =IF(OR(E24="",R24="",R24<=0,E24<0),"",E24/R24) | J24: 38.3 | K24: 7.6 | L24: 22.08 | M24: 9.01 | N24: 2.96 | O24: 54.4 | P24: 12.73 | Q24: 18 | R24: 13.6 | S24: =IFERROR(AVERAGE(IFERROR(IF(P24="","",IF(P24>=40,100,IF(P24>=30,90,IF(P24>=20,75,IF(P24>=15,60,IF(P24>=10,45,IF(P24>=5,30,15))))))),""),IFERROR(IF(Q24="","",IF(Q24>=40,100,IF(Q24>=30,90,IF(Q24>=20,75,IF(Q24>=10,60,IF(Q24>=5,45,IF(Q24>=0,30,15))))))),""),IFERROR(IF(R24="","",IF(R24>=40,100,IF(R24>=30,90,IF(R24>=20,75,IF(R24>=10,60,IF(R24>=0,45,IF(R24>=-10,30,15))))))),"")),"") | T24: 2 | U24: 3 | V24: 5 | W24: 5 | X24: 2 | Y24: =IFERROR((AVERAGE(T24,U24,V24,W24,X24)-1)*25,"") | Z24: 4 | AA24: 3 | AB24: 3 | AC24: 10 | AD24: =IFERROR(AVERAGE(IFERROR(IF(Z24="","",Z24*20),""),IFERROR(IF(AA24="","",AA24*20),""),IFERROR(IF(AB24="","",AB24*20),""),IFERROR(IF(AC24="","",IF(AC24>=85,100,IF(AC24>=70,90,IF(AC24>=55,75,IF(AC24>=40,60,IF(AC24>=25,40,20)))))),"")),"") | AE24: 4 | AF24: 5 | AG24: 4 | AH24: 4 | AI24: =IFERROR((AVERAGE(AE24,AF24,AG24,AH24,AL24)-1)*25,"") | AJ24: =IFERROR(J24*Weights!$B$4 + O24*Weights!$B$5 + S24*Weights!$B$6 + Y24*Weights!$B$7 + AD24*Weights!$B$8 + AI24*Weights!$B$9,"") | AK24: =IF(AJ24="","",IF(AJ24>=85,"✓✓✓",IF(AJ24>=70,"✓✓",IF(AJ24>=55,"✓",IF(AJ24>=40,"?","✗"))))) | AL24: 5
A25: SMR | B25: NuScale Power Corporation | C25: 01 Power Generation / Nuclear-specific | D25: 2026-10-11 | E25: -10.907438 | F25: -9.079 | G25: -26.36 | H25: 276.40826 | I25: =IF(OR(E25="",R25="",R25<=0,E25<0),"",E25/R25) | J25: 28.1 | K25: -28.65 | L25: 23.54 | M25: -7284.85 | O25: 11.6 | P25: 38.67 | Q25: -99.1 | S25: =IFERROR(AVERAGE(IFERROR(IF(P25="","",IF(P25>=40,100,IF(P25>=30,90,IF(P25>=20,75,IF(P25>=15,60,IF(P25>=10,45,IF(P25>=5,30,15))))))),""),IFERROR(IF(Q25="","",IF(Q25>=40,100,IF(Q25>=30,90,IF(Q25>=20,75,IF(Q25>=10,60,IF(Q25>=5,45,IF(Q25>=0,30,15))))))),""),IFERROR(IF(R25="","",IF(R25>=40,100,IF(R25>=30,90,IF(R25>=20,75,IF(R25>=10,60,IF(R25>=0,45,IF(R25>=-10,30,15))))))),"")),"") | T25: 1 | U25: 3 | V25: 3 | W25: 2 | X25: 2 | Y25: =IFERROR((AVERAGE(T25,U25,V25,W25,X25)-1)*25,"") | Z25: 1 | AA25: 1 | AB25: 1 | AC25: 34.2 | AD25: =IFERROR(AVERAGE(IFERROR(IF(Z25="","",Z25*20),""),IFERROR(IF(AA25="","",AA25*20),""),IFERROR(IF(AB25="","",AB25*20),""),IFERROR(IF(AC25="","",IF(AC25>=85,100,IF(AC25>=70,90,IF(AC25>=55,75,IF(AC25>=40,60,IF(AC25>=25,40,20)))))),"")),"") | AE25: 3 | AF25: 5 | AG25: 2 | AH25: 1 | AI25: =IFERROR((AVERAGE(AE25,AF25,AG25,AH25,AL25)-1)*25,"") | AJ25: =IFERROR(J25*Weights!$B$4 + O25*Weights!$B$5 + S25*Weights!$B$6 + Y25*Weights!$B$7 + AD25*Weights!$B$8 + AI25*Weights!$B$9,"") | AK25: =IF(AJ25="","",IF(AJ25>=85,"✓✓✓",IF(AJ25>=70,"✓✓",IF(AJ25>=55,"✓",IF(AJ25>=40,"?","✗"))))) | AL25: 5
A26: OKLO | B26: Oklo Inc. | C26: 01 Power Generation / Nuclear-specific | D26: 2026-10-11 | E26: -32.21464 | F26: -20.241 | G26: -4.27 | H26: 5334.556 | I26: =IF(OR(E26="",R26="",R26<=0,E26<0),"",E26/R26) | J26: 47.5 | K26: -5.21 | L26: 40.41 | M26: -22794.71 | O26: 12.1 | S26: =IFERROR(AVERAGE(IFERROR(IF(P26="","",IF(P26>=40,100,IF(P26>=30,90,IF(P26>=20,75,IF(P26>=15,60,IF(P26>=10,45,IF(P26>=5,30,15))))))),""),IFERROR(IF(Q26="","",IF(Q26>=40,100,IF(Q26>=30,90,IF(Q26>=20,75,IF(Q26>=10,60,IF(Q26>=5,45,IF(Q26>=0,30,15))))))),""),IFERROR(IF(R26="","",IF(R26>=40,100,IF(R26>=30,90,IF(R26>=20,75,IF(R26>=10,60,IF(R26>=0,45,IF(R26>=-10,30,15))))))),"")),"") | T26: 1 | U26: 3 | V26: 3 | W26: 5 | X26: 3 | Y26: =IFERROR((AVERAGE(T26,U26,V26,W26,X26)-1)*25,"") | Z26: 3 | AA26: 1 | AB26: 3 | AC26: 25 | AD26: =IFERROR(AVERAGE(IFERROR(IF(Z26="","",Z26*20),""),IFERROR(IF(AA26="","",AA26*20),""),IFERROR(IF(AB26="","",AB26*20),""),IFERROR(IF(AC26="","",IF(AC26>=85,100,IF(AC26>=70,90,IF(AC26>=55,75,IF(AC26>=40,60,IF(AC26>=25,40,20)))))),"")),"") | AE26: 3 | AF26: 5 | AG26: 3 | AH26: 4 | AI26: =IFERROR((AVERAGE(AE26,AF26,AG26,AH26,AL26)-1)*25,"") | AJ26: =IFERROR(J26*Weights!$B$4 + O26*Weights!$B$5 + S26*Weights!$B$6 + Y26*Weights!$B$7 + AD26*Weights!$B$8 + AI26*Weights!$B$9,"") | AK26: =IF(AJ26="","",IF(AJ26>=85,"✓✓✓",IF(AJ26>=70,"✓✓",IF(AJ26>=55,"✓",IF(AJ26>=40,"?","✗"))))) | AL26: 5
A27: NNE | B27: NANO Nuclear Energy Inc. | C27: 01 Power Generation / Nuclear-specific | D27: 2026-10-11 | E27: -15.225806 | F27: -5.449 | G27: -4.62 | H27: 3848.4482 | I27: =IF(OR(E27="",R27="",R27<=0,E27<0),"",E27/R27) | J27: 37.9 | K27: -6.66 | L27: 29.07 | M27: -17776.09 | O27: 9.1 | S27: =IFERROR(AVERAGE(IFERROR(IF(P27="","",IF(P27>=40,100,IF(P27>=30,90,IF(P27>=20,75,IF(P27>=15,60,IF(P27>=10,45,IF(P27>=5,30,15))))))),""),IFERROR(IF(Q27="","",IF(Q27>=40,100,IF(Q27>=30,90,IF(Q27>=20,75,IF(Q27>=10,60,IF(Q27>=5,45,IF(Q27>=0,30,15))))))),""),IFERROR(IF(R27="","",IF(R27>=40,100,IF(R27>=30,90,IF(R27>=20,75,IF(R27>=10,60,IF(R27>=0,45,IF(R27>=-10,30,15))))))),"")),"") | T27: 1 | U27: 3 | V27: 3 | W27: 4 | X27: 2 | Y27: =IFERROR((AVERAGE(T27,U27,V27,W27,X27)-1)*25,"") | Z27: 4 | AA27: 1 | AB27: 3 | AC27: 29.2 | AD27: =IFERROR(AVERAGE(IFERROR(IF(Z27="","",Z27*20),""),IFERROR(IF(AA27="","",AA27*20),""),IFERROR(IF(AB27="","",AB27*20),""),IFERROR(IF(AC27="","",IF(AC27>=85,100,IF(AC27>=70,90,IF(AC27>=55,75,IF(AC27>=40,60,IF(AC27>=25,40,20)))))),"")),"") | AE27: 3 | AF27: 5 | AG27: 3 | AH27: 4 | AI27: =IFERROR((AVERAGE(AE27,AF27,AG27,AH27,AL27)-1)*25,"") | AJ27: =IFERROR(J27*Weights!$B$4 + O27*Weights!$B$5 + S27*Weights!$B$6 + Y27*Weights!$B$7 + AD27*Weights!$B$8 + AI27*Weights!$B$9,"") | AK27: =IF(AJ27="","",IF(AJ27>=85,"✓✓✓",IF(AJ27>=70,"✓✓",IF(AJ27>=55,"✓",IF(AJ27>=40,"?","✗"))))) | AL27: 5
A28: EQT | B28: EQT Corporation | C28: 01 Power Generation / Natural gas E&P (powering gas turbines for data centers) | D28: 2026-10-11 | E28: 14.009398 | F28: 5.985 | G28: 11.37 | H28: 3.5556598 | I28: =IF(OR(E28="",R28="",R28<=0,E28<0),"",E28/R28) | J28: 78.2 | K28: 7.96 | L28: 80.75 | M28: 40.44 | N28: 0.79 | O28: 91.8 | P28: -11.72 | Q28: -3.9 | R28: -73 | S28: =IFERROR(AVERAGE(IFERROR(IF(P28="","",IF(P28>=40,100,IF(P28>=30,90,IF(P28>=20,75,IF(P28>=15,60,IF(P28>=10,45,IF(P28>=5,30,15))))))),""),IFERROR(IF(Q28="","",IF(Q28>=40,100,IF(Q28>=30,90,IF(Q28>=20,75,IF(Q28>=10,60,IF(Q28>=5,45,IF(Q28>=0,30,15))))))),""),IFERROR(IF(R28="","",IF(R28>=40,100,IF(R28>=30,90,IF(R28>=20,75,IF(R28>=10,60,IF(R28>=0,45,IF(R28>=-10,30,15))))))),"")),"") | T28: 1 | U28: 2 | V28: 3 | W28: 5 | X28: 2 | Y28: =IFERROR((AVERAGE(T28,U28,V28,W28,X28)-1)*25,"") | Z28: 2 | AA28: 1 | AB28: 3 | AC28: 29.2 | AD28: =IFERROR(AVERAGE(IFERROR(IF(Z28="","",Z28*20),""),IFERROR(IF(AA28="","",AA28*20),""),IFERROR(IF(AB28="","",AB28*20),""),IFERROR(IF(AC28="","",IF(AC28>=85,100,IF(AC28>=70,90,IF(AC28>=55,75,IF(AC28>=40,60,IF(AC28>=25,40,20)))))),"")),"") | AE28: 4 | AF28: 5 | AG28: 5 | AH28: 4 | AI28: =IFERROR((AVERAGE(AE28,AF28,AG28,AH28,AL28)-1)*25,"") | AJ28: =IFERROR(J28*Weights!$B$4 + O28*Weights!$B$5 + S28*Weights!$B$6 + Y28*Weights!$B$7 + AD28*Weights!$B$8 + AI28*Weights!$B$9,"") | AK28: =IF(AJ28="","",IF(AJ28>=85,"✓✓✓",IF(AJ28>=70,"✓✓",IF(AJ28>=55,"✓",IF(AJ28>=40,"?","✗"))))) | AL28: 5
A29: RRC | B29: Range Resources Corporation | C29: 01 Power Generation / Natural gas E&P (powering gas turbines for data centers) | D29: 2026-10-11 | E29: 10.368882 | F29: 6.356 | G29: 7.22 | H29: 2.921856 | I29: =IF(OR(E29="",R29="",R29<=0,E29<0),"",E29/R29) | J29: 77.9 | K29: 12.19 | L29: 52.12 | M29: 21.1 | N29: 0.63 | O29: 88.6 | P29: -17.55 | Q29: 8.6 | R29: -17.8 | S29: =IFERROR(AVERAGE(IFERROR(IF(P29="","",IF(P29>=40,100,IF(P29>=30,90,IF(P29>=20,75,IF(P29>=15,60,IF(P29>=10,45,IF(P29>=5,30,15))))))),""),IFERROR(IF(Q29="","",IF(Q29>=40,100,IF(Q29>=30,90,IF(Q29>=20,75,IF(Q29>=10,60,IF(Q29>=5,45,IF(Q29>=0,30,15))))))),""),IFERROR(IF(R29="","",IF(R29>=40,100,IF(R29>=30,90,IF(R29>=20,75,IF(R29>=10,60,IF(R29>=0,45,IF(R29>=-10,30,15))))))),"")),"") | T29: 1 | U29: 2 | V29: 2 | W29: 4 | X29: 1 | Y29: =IFERROR((AVERAGE(T29,U29,V29,W29,X29)-1)*25,"") | Z29: 4 | AA29: 1 | AB29: 3 | AC29: 40.8 | AD29: =IFERROR(AVERAGE(IFERROR(IF(Z29="","",Z29*20),""),IFERROR(IF(AA29="","",AA29*20),""),IFERROR(IF(AB29="","",AB29*20),""),IFERROR(IF(AC29="","",IF(AC29>=85,100,IF(AC29>=70,90,IF(AC29>=55,75,IF(AC29>=40,60,IF(AC29>=25,40,20)))))),"")),"") | AE29: 4 | AF29: 5 | AG29: 5 | AH29: 4 | AI29: =IFERROR((AVERAGE(AE29,AF29,AG29,AH29,AL29)-1)*25,"") | AJ29: =IFERROR(J29*Weights!$B$4 + O29*Weights!$B$5 + S29*Weights!$B$6 + Y29*Weights!$B$7 + AD29*Weights!$B$8 + AI29*Weights!$B$9,"") | AK29: =IF(AJ29="","",IF(AJ29>=85,"✓✓✓",IF(AJ29>=70,"✓✓",IF(AJ29>=55,"✓",IF(AJ29>=40,"?","✗"))))) | AL29: 5
A30: AR | B30: Antero Resources Corporation | C30: 01 Power Generation / Natural gas E&P (powering gas turbines for data centers) | D30: 2026-10-11 | E30: 8.182038 | G30: 14.45 | H30: 1.9091189 | I30: =IF(OR(E30="",R30="",R30<=0,E30<0),"",E30/R30) | J30: 86.8 | K30: 6.71 | L30: 67.15 | M30: 27.58 | O30: 86.3 | P30: -15.47 | Q30: 12.6 | R30: 78 | S30: =IFERROR(AVERAGE(IFERROR(IF(P30="","",IF(P30>=40,100,IF(P30>=30,90,IF(P30>=20,75,IF(P30>=15,60,IF(P30>=10,45,IF(P30>=5,30,15))))))),""),IFERROR(IF(Q30="","",IF(Q30>=40,100,IF(Q30>=30,90,IF(Q30>=20,75,IF(Q30>=10,60,IF(Q30>=5,45,IF(Q30>=0,30,15))))))),""),IFERROR(IF(R30="","",IF(R30>=40,100,IF(R30>=30,90,IF(R30>=20,75,IF(R30>=10,60,IF(R30>=0,45,IF(R30>=-10,30,15))))))),"")),"") | T30: 1 | U30: 2 | V30: 2 | W30: 5 | X30: 1 | Y30: =IFERROR((AVERAGE(T30,U30,V30,W30,X30)-1)*25,"") | Z30: 5 | AA30: 1 | AB30: 3 | AC30: 30.8 | AD30: =IFERROR(AVERAGE(IFERROR(IF(Z30="","",Z30*20),""),IFERROR(IF(AA30="","",AA30*20),""),IFERROR(IF(AB30="","",AB30*20),""),IFERROR(IF(AC30="","",IF(AC30>=85,100,IF(AC30>=70,90,IF(AC30>=55,75,IF(AC30>=40,60,IF(AC30>=25,40,20)))))),"")),"") | AE30: 4 | AF30: 5 | AG30: 4 | AH30: 4 | AI30: =IFERROR((AVERAGE(AE30,AF30,AG30,AH30,AL30)-1)*25,"") | AJ30: =IFERROR(J30*Weights!$B$4 + O30*Weights!$B$5 + S30*Weights!$B$6 + Y30*Weights!$B$7 + AD30*Weights!$B$8 + AI30*Weights!$B$9,"") | AK30: =IF(AJ30="","",IF(AJ30>=85,"✓✓✓",IF(AJ30>=70,"✓✓",IF(AJ30>=55,"✓",IF(AJ30>=40,"?","✗"))))) | AL30: 5
A31: EXE | B31: Expand Energy Corporation | C31: 01 Power Generation / Natural gas E&P (powering gas turbines for data centers) | D31: 2026-10-11 | E31: 10.623668 | F31: 3.491 | G31: 11.74 | H31: 1.6673068 | I31: =IF(OR(E31="",R31="",R31<=0,E31<0),"",E31/R31) | J31: 82.8 | K31: 12.56 | L31: 47.07 | M31: 19.57 | N31: 0.46 | O31: 86.2 | P31: 2.13 | Q31: -10.6 | S31: =IFERROR(AVERAGE(IFERROR(IF(P31="","",IF(P31>=40,100,IF(P31>=30,90,IF(P31>=20,75,IF(P31>=15,60,IF(P31>=10,45,IF(P31>=5,30,15))))))),""),IFERROR(IF(Q31="","",IF(Q31>=40,100,IF(Q31>=30,90,IF(Q31>=20,75,IF(Q31>=10,60,IF(Q31>=5,45,IF(Q31>=0,30,15))))))),""),IFERROR(IF(R31="","",IF(R31>=40,100,IF(R31>=30,90,IF(R31>=20,75,IF(R31>=10,60,IF(R31>=0,45,IF(R31>=-10,30,15))))))),"")),"") | T31: 1 | U31: 2 | V31: 2 | W31: 5 | X31: 1 | Y31: =IFERROR((AVERAGE(T31,U31,V31,W31,X31)-1)*25,"") | Z31: 5 | AA31: 1 | AB31: 3 | AC31: 30.8 | AD31: =IFERROR(AVERAGE(IFERROR(IF(Z31="","",Z31*20),""),IFERROR(IF(AA31="","",AA31*20),""),IFERROR(IF(AB31="","",AB31*20),""),IFERROR(IF(AC31="","",IF(AC31>=85,100,IF(AC31>=70,90,IF(AC31>=55,75,IF(AC31>=40,60,IF(AC31>=25,40,20)))))),"")),"") | AE31: 4 | AF31: 5 | AG31: 5 | AH31: 4 | AI31: =IFERROR((AVERAGE(AE31,AF31,AG31,AH31,AL31)-1)*25,"") | AJ31: =IFERROR(J31*Weights!$B$4 + O31*Weights!$B$5 + S31*Weights!$B$6 + Y31*Weights!$B$7 + AD31*Weights!$B$8 + AI31*Weights!$B$9,"") | AK31: =IF(AJ31="","",IF(AJ31>=85,"✓✓✓",IF(AJ31>=70,"✓✓",IF(AJ31>=55,"✓",IF(AJ31>=40,"?","✗"))))) | AL31: 5
A32: PLUG | B32: Plug Power Inc. | C32: 01 Power Generation / Distributed / on-site power | D32: 2026-10-11 | E32: -11.326097 | F32: -6.556 | G32: -23.88 | H32: 3.1545882 | I32: =IF(OR(E32="",R32="",R32<=0,E32<0),"",E32/R32) | J32: 31.6 | K32: -23.36 | L32: -24.75 | M32: -75.33 | O32: 4.7 | P32: 0.4 | Q32: 2.5 | S32: =IFERROR(AVERAGE(IFERROR(IF(P32="","",IF(P32>=40,100,IF(P32>=30,90,IF(P32>=20,75,IF(P32>=15,60,IF(P32>=10,45,IF(P32>=5,30,15))))))),""),IFERROR(IF(Q32="","",IF(Q32>=40,100,IF(Q32>=30,90,IF(Q32>=20,75,IF(Q32>=10,60,IF(Q32>=5,45,IF(Q32>=0,30,15))))))),""),IFERROR(IF(R32="","",IF(R32>=40,100,IF(R32>=30,90,IF(R32>=20,75,IF(R32>=10,60,IF(R32>=0,45,IF(R32>=-10,30,15))))))),"")),"") | T32: 1 | U32: 2 | V32: 2 | W32: 3 | X32: 2 | Y32: =IFERROR((AVERAGE(T32,U32,V32,W32,X32)-1)*25,"") | Z32: 3 | AA32: 5 | AB32: 3 | AC32: 28.3 | AD32: =IFERROR(AVERAGE(IFERROR(IF(Z32="","",Z32*20),""),IFERROR(IF(AA32="","",AA32*20),""),IFERROR(IF(AB32="","",AB32*20),""),IFERROR(IF(AC32="","",IF(AC32>=85,100,IF(AC32>=70,90,IF(AC32>=55,75,IF(AC32>=40,60,IF(AC32>=25,40,20)))))),"")),"") | AE32: 3 | AF32: 4 | AG32: 2 | AH32: 4 | AI32: =IFERROR((AVERAGE(AE32,AF32,AG32,AH32,AL32)-1)*25,"") | AJ32: =IFERROR(J32*Weights!$B$4 + O32*Weights!$B$5 + S32*Weights!$B$6 + Y32*Weights!$B$7 + AD32*Weights!$B$8 + AI32*Weights!$B$9,"") | AK32: =IF(AJ32="","",IF(AJ32>=85,"✓✓✓",IF(AJ32>=70,"✓✓",IF(AJ32>=55,"✓",IF(AJ32>=40,"?","✗"))))) | AL32: 5
A33: CMI | B33: Cummins Inc. | C33: 01 Power Generation / Distributed / on-site power | D33: 2026-10-11 | E33: 15.038128 | F33: 15.266 | G33: 3.7 | H33: 2.080849 | I33: =IF(OR(E33="",R33="",R33<=0,E33<0),"",E33/R33) | J33: 57.6 | K33: 11.7 | L33: 25.77 | M33: 7.7 | N33: 0.87 | O33: 67.1 | P33: 6.25 | Q33: 9.4 | R33: 4.7 | S33: =IFERROR(AVERAGE(IFERROR(IF(P33="","",IF(P33>=40,100,IF(P33>=30,90,IF(P33>=20,75,IF(P33>=15,60,IF(P33>=10,45,IF(P33>=5,30,15))))))),""),IFERROR(IF(Q33="","",IF(Q33>=40,100,IF(Q33>=30,90,IF(Q33>=20,75,IF(Q33>=10,60,IF(Q33>=5,45,IF(Q33>=0,30,15))))))),""),IFERROR(IF(R33="","",IF(R33>=40,100,IF(R33>=30,90,IF(R33>=20,75,IF(R33>=10,60,IF(R33>=0,45,IF(R33>=-10,30,15))))))),"")),"") | T33: 2 | U33: 4 | V33: 4 | W33: 5 | X33: 2 | Y33: =IFERROR((AVERAGE(T33,U33,V33,W33,X33)-1)*25,"") | Z33: 5 | AA33: 5 | AB33: 3 | AC33: 41.7 | AD33: =IFERROR(AVERAGE(IFERROR(IF(Z33="","",Z33*20),""),IFERROR(IF(AA33="","",AA33*20),""),IFERROR(IF(AB33="","",AB33*20),""),IFERROR(IF(AC33="","",IF(AC33>=85,100,IF(AC33>=70,90,IF(AC33>=55,75,IF(AC33>=40,60,IF(AC33>=25,40,20)))))),"")),"") | AE33: 5 | AF33: 4 | AG33: 4 | AH33: 4 | AI33: =IFERROR((AVERAGE(AE33,AF33,AG33,AH33,AL33)-1)*25,"") | AJ33: =IFERROR(J33*Weights!$B$4 + O33*Weights!$B$5 + S33*Weights!$B$6 + Y33*Weights!$B$7 + AD33*Weights!$B$8 + AI33*Weights!$B$9,"") | AK33: =IF(AJ33="","",IF(AJ33>=85,"✓✓✓",IF(AJ33>=70,"✓✓",IF(AJ33>=55,"✓",IF(AJ33>=40,"?","✗"))))) | AL33: 5
A34: GNRC | B34: Generac Holdings Inc. | C34: 01 Power Generation / Distributed / on-site power | D34: 2026-10-11 | E34: 17.343113 | F34: 22.318 | G34: 2.85 | H34: 2.9931617 | I34: =IF(OR(E34="",R34="",R34<=0,E34<0),"",E34/R34) | J34: 57.9 | K34: 7.06 | L34: 39.54 | M34: 8.54 | N34: 1.79 | O34: 61 | P34: -2.67 | Q34: 10.6 | R34: 93.5 | S34: =IFERROR(AVERAGE(IFERROR(IF(P34="","",IF(P34>=40,100,IF(P34>=30,90,IF(P34>=20,75,IF(P34>=15,60,IF(P34>=10,45,IF(P34>=5,30,15))))))),""),IFERROR(IF(Q34="","",IF(Q34>=40,100,IF(Q34>=30,90,IF(Q34>=20,75,IF(Q34>=10,60,IF(Q34>=5,45,IF(Q34>=0,30,15))))))),""),IFERROR(IF(R34="","",IF(R34>=40,100,IF(R34>=30,90,IF(R34>=20,75,IF(R34>=10,60,IF(R34>=0,45,IF(R34>=-10,30,15))))))),"")),"") | T34: 2 | U34: 3 | V34: 3 | W34: 5 | X34: 3 | Y34: =IFERROR((AVERAGE(T34,U34,V34,W34,X34)-1)*25,"") | Z34: 5 | AA34: 5 | AB34: 3 | AC34: 53.3 | AD34: =IFERROR(AVERAGE(IFERROR(IF(Z34="","",Z34*20),""),IFERROR(IF(AA34="","",AA34*20),""),IFERROR(IF(AB34="","",AB34*20),""),IFERROR(IF(AC34="","",IF(AC34>=85,100,IF(AC34>=70,90,IF(AC34>=55,75,IF(AC34>=40,60,IF(AC34>=25,40,20)))))),"")),"") | AE34: 4 | AF34: 4 | AG34: 4 | AH34: 4 | AI34: =IFERROR((AVERAGE(AE34,AF34,AG34,AH34,AL34)-1)*25,"") | AJ34: =IFERROR(J34*Weights!$B$4 + O34*Weights!$B$5 + S34*Weights!$B$6 + Y34*Weights!$B$7 + AD34*Weights!$B$8 + AI34*Weights!$B$9,"") | AK34: =IF(AJ34="","",IF(AJ34>=85,"✓✓✓",IF(AJ34>=70,"✓✓",IF(AJ34>=55,"✓",IF(AJ34>=40,"?","✗"))))) | AL34: 5
A35: ETN | B35: Eaton Corporation plc | C35: 02 Grid & Power Equipment | D35: 2026-10-11 | E35: 26.446348 | F35: 28.348 | G35: 2.26 | H35: 5.556288 | I35: =IF(OR(E35="",R35="",R35<=0,E35<0),"",E35/R35) | J35: 33.4 | K35: 9.82 | L35: 36.02 | M35: 12.58 | N35: 3.11 | O35: 55.6 | P35: 9.77 | Q35: 21.4 | R35: -16.4 | S35: =IFERROR(AVERAGE(IFERROR(IF(P35="","",IF(P35>=40,100,IF(P35>=30,90,IF(P35>=20,75,IF(P35>=15,60,IF(P35>=10,45,IF(P35>=5,30,15))))))),""),IFERROR(IF(Q35="","",IF(Q35>=40,100,IF(Q35>=30,90,IF(Q35>=20,75,IF(Q35>=10,60,IF(Q35>=5,45,IF(Q35>=0,30,15))))))),""),IFERROR(IF(R35="","",IF(R35>=40,100,IF(R35>=30,90,IF(R35>=20,75,IF(R35>=10,60,IF(R35>=0,45,IF(R35>=-10,30,15))))))),"")),"") | T35: 4 | U35: 4 | V35: 4 | W35: 5 | X35: 5 | Y35: =IFERROR((AVERAGE(T35,U35,V35,W35,X35)-1)*25,"") | Z35: 5 | AA35: 3 | AB35: 3 | AC35: 67.5 | AD35: =IFERROR(AVERAGE(IFERROR(IF(Z35="","",Z35*20),""),IFERROR(IF(AA35="","",AA35*20),""),IFERROR(IF(AB35="","",AB35*20),""),IFERROR(IF(AC35="","",IF(AC35>=85,100,IF(AC35>=70,90,IF(AC35>=55,75,IF(AC35>=40,60,IF(AC35>=25,40,20)))))),"")),"") | AE35: 5 | AF35: 4 | AG35: 4 | AH35: 4 | AI35: =IFERROR((AVERAGE(AE35,AF35,AG35,AH35,AL35)-1)*25,"") | AJ35: =IFERROR(J35*Weights!$B$4 + O35*Weights!$B$5 + S35*Weights!$B$6 + Y35*Weights!$B$7 + AD35*Weights!$B$8 + AI35*Weights!$B$9,"") | AK35: =IF(AJ35="","",IF(AJ35>=85,"✓✓✓",IF(AJ35>=70,"✓✓",IF(AJ35>=55,"✓",IF(AJ35>=40,"?","✗"))))) | AL35: 5
A36: SBGSY | B36: Schneider Electric S.E. | C36: 02 Grid & Power Equipment | D36: 2026-10-11 | E36: 21.28942 | F36: 19.52 | G36: 3.58 | H36: 3.57 | I36: =IF(OR(E36="",R36="",R36<=0,E36<0),"",E36/R36) | J36: 69.8 | K36: 12.2 | L36: 42.12 | M36: 12.78 | N36: 1.91 | O36: 79 | P36: 5.52 | Q36: 9.8 | R36: 30.1 | S36: =IFERROR(AVERAGE(IFERROR(IF(P36="","",IF(P36>=40,100,IF(P36>=30,90,IF(P36>=20,75,IF(P36>=15,60,IF(P36>=10,45,IF(P36>=5,30,15))))))),""),IFERROR(IF(Q36="","",IF(Q36>=40,100,IF(Q36>=30,90,IF(Q36>=20,75,IF(Q36>=10,60,IF(Q36>=5,45,IF(Q36>=0,30,15))))))),""),IFERROR(IF(R36="","",IF(R36>=40,100,IF(R36>=30,90,IF(R36>=20,75,IF(R36>=10,60,IF(R36>=0,45,IF(R36>=-10,30,15))))))),"")),"") | T36: 4 | U36: 4 | V36: 4 | W36: 5 | X36: 4 | Y36: =IFERROR((AVERAGE(T36,U36,V36,W36,X36)-1)*25,"") | Z36: 4 | AA36: 4 | AB36: 3 | AC36: 68.3 | AD36: =IFERROR(AVERAGE(IFERROR(IF(Z36="","",Z36*20),""),IFERROR(IF(AA36="","",AA36*20),""),IFERROR(IF(AB36="","",AB36*20),""),IFERROR(IF(AC36="","",IF(AC36>=85,100,IF(AC36>=70,90,IF(AC36>=55,75,IF(AC36>=40,60,IF(AC36>=25,40,20)))))),"")),"") | AE36: 5 | AF36: 4 | AG36: 3 | AH36: 4 | AI36: =IFERROR((AVERAGE(AE36,AF36,AG36,AH36,AL36)-1)*25,"") | AJ36: =IFERROR(J36*Weights!$B$4 + O36*Weights!$B$5 + S36*Weights!$B$6 + Y36*Weights!$B$7 + AD36*Weights!$B$8 + AI36*Weights!$B$9,"") | AK36: =IF(AJ36="","",IF(AJ36>=85,"✓✓✓",IF(AJ36>=70,"✓✓",IF(AJ36>=55,"✓",IF(AJ36>=40,"?","✗"))))) | AL36: 5
A37: ABBNY | B37: ABB Ltd | C37: 02 Grid & Power Equipment | D37: 2026-10-11 | E37: 26.253393 | F37: 98.238 | G37: 2.39 | H37: 4.857817 | I37: =IF(OR(E37="",R37="",R37<=0,E37<0),"",E37/R37) | J37: 32.2 | K37: 16.73 | L37: 40.25 | M37: 11.63 | N37: 0.46 | O37: 78.2 | P37: 4.1 | Q37: 14.2 | R37: 7 | S37: =IFERROR(AVERAGE(IFERROR(IF(P37="","",IF(P37>=40,100,IF(P37>=30,90,IF(P37>=20,75,IF(P37>=15,60,IF(P37>=10,45,IF(P37>=5,30,15))))))),""),IFERROR(IF(Q37="","",IF(Q37>=40,100,IF(Q37>=30,90,IF(Q37>=20,75,IF(Q37>=10,60,IF(Q37>=5,45,IF(Q37>=0,30,15))))))),""),IFERROR(IF(R37="","",IF(R37>=40,100,IF(R37>=30,90,IF(R37>=20,75,IF(R37>=10,60,IF(R37>=0,45,IF(R37>=-10,30,15))))))),"")),"") | T37: 4 | U37: 4 | V37: 4 | W37: 5 | X37: 4 | Y37: =IFERROR((AVERAGE(T37,U37,V37,W37,X37)-1)*25,"") | Z37: 5 | AA37: 5 | AB37: 3 | AC37: 50 | AD37: =IFERROR(AVERAGE(IFERROR(IF(Z37="","",Z37*20),""),IFERROR(IF(AA37="","",AA37*20),""),IFERROR(IF(AB37="","",AB37*20),""),IFERROR(IF(AC37="","",IF(AC37>=85,100,IF(AC37>=70,90,IF(AC37>=55,75,IF(AC37>=40,60,IF(AC37>=25,40,20)))))),"")),"") | AE37: 5 | AF37: 4 | AG37: 4 | AH37: 4 | AI37: =IFERROR((AVERAGE(AE37,AF37,AG37,AH37,AL37)-1)*25,"") | AJ37: =IFERROR(J37*Weights!$B$4 + O37*Weights!$B$5 + S37*Weights!$B$6 + Y37*Weights!$B$7 + AD37*Weights!$B$8 + AI37*Weights!$B$9,"") | AK37: =IF(AJ37="","",IF(AJ37>=85,"✓✓✓",IF(AJ37>=70,"✓✓",IF(AJ37>=55,"✓",IF(AJ37>=40,"?","✗"))))) | AL37: 5
A38: HTHIY | B38: Hitachi, Ltd. | C38: 02 Grid & Power Equipment | D38: 2026-10-11 | E38: 15.071524 | F38: 14.02 | H38: 2.3 | I38: =IF(OR(E38="",R38="",R38<=0,E38<0),"",E38/R38) | J38: 84.1 | K38: 9.8 | L38: 30.15 | M38: 11.46 | N38: -0.47 | O38: 58 | P38: -0.91 | Q38: 20 | R38: -1.4 | S38: =IFERROR(AVERAGE(IFERROR(IF(P38="","",IF(P38>=40,100,IF(P38>=30,90,IF(P38>=20,75,IF(P38>=15,60,IF(P38>=10,45,IF(P38>=5,30,15))))))),""),IFERROR(IF(Q38="","",IF(Q38>=40,100,IF(Q38>=30,90,IF(Q38>=20,75,IF(Q38>=10,60,IF(Q38>=5,45,IF(Q38>=0,30,15))))))),""),IFERROR(IF(R38="","",IF(R38>=40,100,IF(R38>=30,90,IF(R38>=20,75,IF(R38>=10,60,IF(R38>=0,45,IF(R38>=-10,30,15))))))),"")),"") | T38: 4 | U38: 5 | V38: 4 | W38: 5 | X38: 4 | Y38: =IFERROR((AVERAGE(T38,U38,V38,W38,X38)-1)*25,"") | Z38: 4 | AA38: 2 | AB38: 3 | AC38: 65.8 | AD38: =IFERROR(AVERAGE(IFERROR(IF(Z38="","",Z38*20),""),IFERROR(IF(AA38="","",AA38*20),""),IFERROR(IF(AB38="","",AB38*20),""),IFERROR(IF(AC38="","",IF(AC38>=85,100,IF(AC38>=70,90,IF(AC38>=55,75,IF(AC38>=40,60,IF(AC38>=25,40,20)))))),"")),"") | AE38: 5 | AF38: 4 | AG38: 4 | AH38: 4 | AI38: =IFERROR((AVERAGE(AE38,AF38,AG38,AH38,AL38)-1)*25,"") | AJ38: =IFERROR(J38*Weights!$B$4 + O38*Weights!$B$5 + S38*Weights!$B$6 + Y38*Weights!$B$7 + AD38*Weights!$B$8 + AI38*Weights!$B$9,"") | AK38: =IF(AJ38="","",IF(AJ38>=85,"✓✓✓",IF(AJ38>=70,"✓✓",IF(AJ38>=55,"✓",IF(AJ38>=40,"?","✗"))))) | AL38: 5
A39: HUBB | B39: Hubbell Incorporated | C39: 02 Grid & Power Equipment | D39: 2026-10-11 | E39: 20.645487 | F39: 19.987 | G39: 3.6 | H39: 4.0254536 | I39: =IF(OR(E39="",R39="",R39<=0,E39<0),"",E39/R39) | J39: 63 | K39: 10.07 | L39: 35.34 | M39: 14.48 | N39: 3.41 | O39: 60.1 | P39: 5.71 | Q39: 15.3 | R39: -1.6 | S39: =IFERROR(AVERAGE(IFERROR(IF(P39="","",IF(P39>=40,100,IF(P39>=30,90,IF(P39>=20,75,IF(P39>=15,60,IF(P39>=10,45,IF(P39>=5,30,15))))))),""),IFERROR(IF(Q39="","",IF(Q39>=40,100,IF(Q39>=30,90,IF(Q39>=20,75,IF(Q39>=10,60,IF(Q39>=5,45,IF(Q39>=0,30,15))))))),""),IFERROR(IF(R39="","",IF(R39>=40,100,IF(R39>=30,90,IF(R39>=20,75,IF(R39>=10,60,IF(R39>=0,45,IF(R39>=-10,30,15))))))),"")),"") | T39: 3 | U39: 3 | V39: 3 | W39: 4 | X39: 3 | Y39: =IFERROR((AVERAGE(T39,U39,V39,W39,X39)-1)*25,"") | Z39: 4 | AA39: 2 | AB39: 3 | AC39: 30.8 | AD39: =IFERROR(AVERAGE(IFERROR(IF(Z39="","",Z39*20),""),IFERROR(IF(AA39="","",AA39*20),""),IFERROR(IF(AB39="","",AB39*20),""),IFERROR(IF(AC39="","",IF(AC39>=85,100,IF(AC39>=70,90,IF(AC39>=55,75,IF(AC39>=40,60,IF(AC39>=25,40,20)))))),"")),"") | AE39: 5 | AF39: 4 | AG39: 3 | AH39: 4 | AI39: =IFERROR((AVERAGE(AE39,AF39,AG39,AH39,AL39)-1)*25,"") | AJ39: =IFERROR(J39*Weights!$B$4 + O39*Weights!$B$5 + S39*Weights!$B$6 + Y39*Weights!$B$7 + AD39*Weights!$B$8 + AI39*Weights!$B$9,"") | AK39: =IF(AJ39="","",IF(AJ39>=85,"✓✓✓",IF(AJ39>=70,"✓✓",IF(AJ39>=55,"✓",IF(AJ39>=40,"?","✗"))))) | AL39: 5
A40: PWR | B40: Quanta Services, Inc. | C40: 02 Grid & Power Equipment | D40: 2026-10-11 | E40: 35.700523 | F40: 36.651 | G40: 2.25 | H40: 3.2254357 | I40: =IF(OR(E40="",R40="",R40<=0,E40<0),"",E40/R40) | J40: 56.4 | K40: 8.86 | L40: 15.46 | M40: 7.27 | N40: 2 | O40: 33.5 | P40: 18.6 | Q40: 41.1 | R40: 96.9 | S40: =IFERROR(AVERAGE(IFERROR(IF(P40="","",IF(P40>=40,100,IF(P40>=30,90,IF(P40>=20,75,IF(P40>=15,60,IF(P40>=10,45,IF(P40>=5,30,15))))))),""),IFERROR(IF(Q40="","",IF(Q40>=40,100,IF(Q40>=30,90,IF(Q40>=20,75,IF(Q40>=10,60,IF(Q40>=5,45,IF(Q40>=0,30,15))))))),""),IFERROR(IF(R40="","",IF(R40>=40,100,IF(R40>=30,90,IF(R40>=20,75,IF(R40>=10,60,IF(R40>=0,45,IF(R40>=-10,30,15))))))),"")),"") | T40: 4 | U40: 4 | V40: 4 | W40: 5 | X40: 4 | Y40: =IFERROR((AVERAGE(T40,U40,V40,W40,X40)-1)*25,"") | Z40: 5 | AA40: 5 | AB40: 3 | AC40: 57.5 | AD40: =IFERROR(AVERAGE(IFERROR(IF(Z40="","",Z40*20),""),IFERROR(IF(AA40="","",AA40*20),""),IFERROR(IF(AB40="","",AB40*20),""),IFERROR(IF(AC40="","",IF(AC40>=85,100,IF(AC40>=70,90,IF(AC40>=55,75,IF(AC40>=40,60,IF(AC40>=25,40,20)))))),"")),"") | AE40: 5 | AF40: 5 | AG40: 4 | AH40: 4 | AI40: =IFERROR((AVERAGE(AE40,AF40,AG40,AH40,AL40)-1)*25,"") | AJ40: =IFERROR(J40*Weights!$B$4 + O40*Weights!$B$5 + S40*Weights!$B$6 + Y40*Weights!$B$7 + AD40*Weights!$B$8 + AI40*Weights!$B$9,"") | AK40: =IF(AJ40="","",IF(AJ40>=85,"✓✓✓",IF(AJ40>=70,"✓✓",IF(AJ40>=55,"✓",IF(AJ40>=40,"?","✗"))))) | AL40: 5
A41: MTZ | B41: MasTec, Inc. | C41: 02 Grid & Power Equipment | D41: 2026-10-11 | E41: 17.149788 | F41: 15.859 | G41: 1.43 | H41: 1.0600742 | I41: =IF(OR(E41="",R41="",R41<=0,E41<0),"",E41/R41) | J41: 48.6 | K41: 8.93 | L41: 12.91 | M41: 1.52 | N41: 2.23 | O41: 25.2 | P41: 13.51 | Q41: 23.4 | R41: 51.7 | S41: =IFERROR(AVERAGE(IFERROR(IF(P41="","",IF(P41>=40,100,IF(P41>=30,90,IF(P41>=20,75,IF(P41>=15,60,IF(P41>=10,45,IF(P41>=5,30,15))))))),""),IFERROR(IF(Q41="","",IF(Q41>=40,100,IF(Q41>=30,90,IF(Q41>=20,75,IF(Q41>=10,60,IF(Q41>=5,45,IF(Q41>=0,30,15))))))),""),IFERROR(IF(R41="","",IF(R41>=40,100,IF(R41>=30,90,IF(R41>=20,75,IF(R41>=10,60,IF(R41>=0,45,IF(R41>=-10,30,15))))))),"")),"") | T41: 3 | U41: 3 | V41: 3 | W41: 5 | X41: 3 | Y41: =IFERROR((AVERAGE(T41,U41,V41,W41,X41)-1)*25,"") | Z41: 5 | AA41: 5 | AB41: 3 | AC41: 30 | AD41: =IFERROR(AVERAGE(IFERROR(IF(Z41="","",Z41*20),""),IFERROR(IF(AA41="","",AA41*20),""),IFERROR(IF(AB41="","",AB41*20),""),IFERROR(IF(AC41="","",IF(AC41>=85,100,IF(AC41>=70,90,IF(AC41>=55,75,IF(AC41>=40,60,IF(AC41>=25,40,20)))))),"")),"") | AE41: 5 | AF41: 5 | AG41: 4 | AH41: 4 | AI41: =IFERROR((AVERAGE(AE41,AF41,AG41,AH41,AL41)-1)*25,"") | AJ41: =IFERROR(J41*Weights!$B$4 + O41*Weights!$B$5 + S41*Weights!$B$6 + Y41*Weights!$B$7 + AD41*Weights!$B$8 + AI41*Weights!$B$9,"") | AK41: =IF(AJ41="","",IF(AJ41>=85,"✓✓✓",IF(AJ41>=70,"✓✓",IF(AJ41>=55,"✓",IF(AJ41>=40,"?","✗"))))) | AL41: 5
A42: POWL | B42: Powell Industries, Inc. | C42: 02 Grid & Power Equipment | D42: 2026-10-11 | E42: 27.458424 | F42: 27.826 | G42: 3.49 | H42: 6.0407715 | I42: =IF(OR(E42="",R42="",R42<=0,E42<0),"",E42/R42) | J42: 36.9 | K42: 22.63 | L42: 30.08 | M42: 21.08 | N42: -2.67 | O42: 80.7 | P42: 27.52 | Q42: 8.9 | R42: 8.1 | S42: =IFERROR(AVERAGE(IFERROR(IF(P42="","",IF(P42>=40,100,IF(P42>=30,90,IF(P42>=20,75,IF(P42>=15,60,IF(P42>=10,45,IF(P42>=5,30,15))))))),""),IFERROR(IF(Q42="","",IF(Q42>=40,100,IF(Q42>=30,90,IF(Q42>=20,75,IF(Q42>=10,60,IF(Q42>=5,45,IF(Q42>=0,30,15))))))),""),IFERROR(IF(R42="","",IF(R42>=40,100,IF(R42>=30,90,IF(R42>=20,75,IF(R42>=10,60,IF(R42>=0,45,IF(R42>=-10,30,15))))))),"")),"") | T42: 4 | U42: 4 | V42: 3 | W42: 5 | X42: 4 | Y42: =IFERROR((AVERAGE(T42,U42,V42,W42,X42)-1)*25,"") | Z42: 4 | AA42: 5 | AB42: 3 | AC42: 41.7 | AD42: =IFERROR(AVERAGE(IFERROR(IF(Z42="","",Z42*20),""),IFERROR(IF(AA42="","",AA42*20),""),IFERROR(IF(AB42="","",AB42*20),""),IFERROR(IF(AC42="","",IF(AC42>=85,100,IF(AC42>=70,90,IF(AC42>=55,75,IF(AC42>=40,60,IF(AC42>=25,40,20)))))),"")),"") | AE42: 4 | AF42: 4 | AG42: 4 | AH42: 4 | AI42: =IFERROR((AVERAGE(AE42,AF42,AG42,AH42,AL42)-1)*25,"") | AJ42: =IFERROR(J42*Weights!$B$4 + O42*Weights!$B$5 + S42*Weights!$B$6 + Y42*Weights!$B$7 + AD42*Weights!$B$8 + AI42*Weights!$B$9,"") | AK42: =IF(AJ42="","",IF(AJ42>=85,"✓✓✓",IF(AJ42>=70,"✓✓",IF(AJ42>=55,"✓",IF(AJ42>=40,"?","✗"))))) | AL42: 5
A43: NVT | B43: nVent Electric plc | C43: 02 Grid & Power Equipment | D43: 2026-10-11 | E43: 25.72648 | F43: 27.191 | G43: 2.13 | H43: 5.606097 | I43: =IF(OR(E43="",R43="",R43<=0,E43<0),"",E43/R43) | J43: 37.5 | K43: 10.66 | L43: 36.45 | M43: 11.95 | N43: 1.31 | O43: 63.1 | P43: 19.26 | Q43: 52.8 | R43: 97.2 | S43: =IFERROR(AVERAGE(IFERROR(IF(P43="","",IF(P43>=40,100,IF(P43>=30,90,IF(P43>=20,75,IF(P43>=15,60,IF(P43>=10,45,IF(P43>=5,30,15))))))),""),IFERROR(IF(Q43="","",IF(Q43>=40,100,IF(Q43>=30,90,IF(Q43>=20,75,IF(Q43>=10,60,IF(Q43>=5,45,IF(Q43>=0,30,15))))))),""),IFERROR(IF(R43="","",IF(R43>=40,100,IF(R43>=30,90,IF(R43>=20,75,IF(R43>=10,60,IF(R43>=0,45,IF(R43>=-10,30,15))))))),"")),"") | T43: 4 | U43: 4 | V43: 4 | W43: 5 | X43: 4 | Y43: =IFERROR((AVERAGE(T43,U43,V43,W43,X43)-1)*25,"") | Z43: 5 | AA43: 5 | AB43: 3 | AC43: 65.8 | AD43: =IFERROR(AVERAGE(IFERROR(IF(Z43="","",Z43*20),""),IFERROR(IF(AA43="","",AA43*20),""),IFERROR(IF(AB43="","",AB43*20),""),IFERROR(IF(AC43="","",IF(AC43>=85,100,IF(AC43>=70,90,IF(AC43>=55,75,IF(AC43>=40,60,IF(AC43>=25,40,20)))))),"")),"") | AE43: 4 | AF43: 4 | AG43: 4 | AH43: 4 | AI43: =IFERROR((AVERAGE(AE43,AF43,AG43,AH43,AL43)-1)*25,"") | AJ43: =IFERROR(J43*Weights!$B$4 + O43*Weights!$B$5 + S43*Weights!$B$6 + Y43*Weights!$B$7 + AD43*Weights!$B$8 + AI43*Weights!$B$9,"") | AK43: =IF(AJ43="","",IF(AJ43>=85,"✓✓✓",IF(AJ43>=70,"✓✓",IF(AJ43>=55,"✓",IF(AJ43>=40,"?","✗"))))) | AL43: 5
A44: ATKR | B44: Atkore Inc. | C44: 02 Grid & Power Equipment | D44: 2026-10-11 | E44: 14.831449 | F44: 12.878 | G44: 1.79 | H44: 1.091795 | I44: =IF(OR(E44="",R44="",R44<=0,E44<0),"",E44/R44) | J44: 78.1 | K44: 4.92 | L44: 20.59 | M44: 1.96 | N44: 1.94 | O44: 31.2 | P44: -10.03 | Q44: 8.1 | S44: =IFERROR(AVERAGE(IFERROR(IF(P44="","",IF(P44>=40,100,IF(P44>=30,90,IF(P44>=20,75,IF(P44>=15,60,IF(P44>=10,45,IF(P44>=5,30,15))))))),""),IFERROR(IF(Q44="","",IF(Q44>=40,100,IF(Q44>=30,90,IF(Q44>=20,75,IF(Q44>=10,60,IF(Q44>=5,45,IF(Q44>=0,30,15))))))),""),IFERROR(IF(R44="","",IF(R44>=40,100,IF(R44>=30,90,IF(R44>=20,75,IF(R44>=10,60,IF(R44>=0,45,IF(R44>=-10,30,15))))))),"")),"") | T44: 3 | U44: 3 | V44: 3 | W44: 4 | X44: 3 | Y44: =IFERROR((AVERAGE(T44,U44,V44,W44,X44)-1)*25,"") | Z44: 4 | AA44: 3 | AB44: 3 | AC44: 80.8 | AD44: =IFERROR(AVERAGE(IFERROR(IF(Z44="","",Z44*20),""),IFERROR(IF(AA44="","",AA44*20),""),IFERROR(IF(AB44="","",AB44*20),""),IFERROR(IF(AC44="","",IF(AC44>=85,100,IF(AC44>=70,90,IF(AC44>=55,75,IF(AC44>=40,60,IF(AC44>=25,40,20)))))),"")),"") | AE44: 4 | AF44: 4 | AG44: 4 | AH44: 4 | AI44: =IFERROR((AVERAGE(AE44,AF44,AG44,AH44,AL44)-1)*25,"") | AJ44: =IFERROR(J44*Weights!$B$4 + O44*Weights!$B$5 + S44*Weights!$B$6 + Y44*Weights!$B$7 + AD44*Weights!$B$8 + AI44*Weights!$B$9,"") | AK44: =IF(AJ44="","",IF(AJ44>=85,"✓✓✓",IF(AJ44>=70,"✓✓",IF(AJ44>=55,"✓",IF(AJ44>=40,"?","✗"))))) | AL44: 5
A45: DLR | B45: Digital Realty Trust, Inc. | C45: 03 Data Center Construction, REITs & Cooling | D45: 2026-10-11 | E45: 64.71934 | F45: 27.347 | G45: 5.58 | H45: 9.99124 | I45: =IF(OR(E45="",R45="",R45<=0,E45<0),"",E45/R45) | J45: 46 | K45: 2.11 | L45: 56.99 | M45: 55.77 | N45: 5.66 | O45: 52.6 | P45: 9.22 | Q45: 29.9 | R45: -56.1 | S45: =IFERROR(AVERAGE(IFERROR(IF(P45="","",IF(P45>=40,100,IF(P45>=30,90,IF(P45>=20,75,IF(P45>=15,60,IF(P45>=10,45,IF(P45>=5,30,15))))))),""),IFERROR(IF(Q45="","",IF(Q45>=40,100,IF(Q45>=30,90,IF(Q45>=20,75,IF(Q45>=10,60,IF(Q45>=5,45,IF(Q45>=0,30,15))))))),""),IFERROR(IF(R45="","",IF(R45>=40,100,IF(R45>=30,90,IF(R45>=20,75,IF(R45>=10,60,IF(R45>=0,45,IF(R45>=-10,30,15))))))),"")),"") | T45: 5 | U45: 5 | V45: 4 | W45: 5 | X45: 5 | Y45: =IFERROR((AVERAGE(T45,U45,V45,W45,X45)-1)*25,"") | Z45: 2 | AA45: 4 | AB45: 3 | AC45: 50 | AD45: =IFERROR(AVERAGE(IFERROR(IF(Z45="","",Z45*20),""),IFERROR(IF(AA45="","",AA45*20),""),IFERROR(IF(AB45="","",AB45*20),""),IFERROR(IF(AC45="","",IF(AC45>=85,100,IF(AC45>=70,90,IF(AC45>=55,75,IF(AC45>=40,60,IF(AC45>=25,40,20)))))),"")),"") | AE45: 4 | AF45: 4 | AG45: 3 | AH45: 4 | AI45: =IFERROR((AVERAGE(AE45,AF45,AG45,AH45,AL45)-1)*25,"") | AJ45: =IFERROR(J45*Weights!$B$4 + O45*Weights!$B$5 + S45*Weights!$B$6 + Y45*Weights!$B$7 + AD45*Weights!$B$8 + AI45*Weights!$B$9,"") | AK45: =IF(AJ45="","",IF(AJ45>=85,"✓✓✓",IF(AJ45>=70,"✓✓",IF(AJ45>=55,"✓",IF(AJ45>=40,"?","✗"))))) | AL45: 5
A46: EQIX | B46: Equinix, Inc. | C46: 03 Data Center Construction, REITs & Cooling | D46: 2026-10-11 | E46: 55.380383 | F46: 27.357 | G46: -1.45 | H46: 10.222444 | I46: =IF(OR(E46="",R46="",R46<=0,E46<0),"",E46/R46) | J46: 23.8 | K46: 5.44 | L46: 51.98 | M46: -14.78 | N46: 4.93 | O46: 32.2 | P46: 8.27 | Q46: 16.7 | R46: 30.2 | S46: =IFERROR(AVERAGE(IFERROR(IF(P46="","",IF(P46>=40,100,IF(P46>=30,90,IF(P46>=20,75,IF(P46>=15,60,IF(P46>=10,45,IF(P46>=5,30,15))))))),""),IFERROR(IF(Q46="","",IF(Q46>=40,100,IF(Q46>=30,90,IF(Q46>=20,75,IF(Q46>=10,60,IF(Q46>=5,45,IF(Q46>=0,30,15))))))),""),IFERROR(IF(R46="","",IF(R46>=40,100,IF(R46>=30,90,IF(R46>=20,75,IF(R46>=10,60,IF(R46>=0,45,IF(R46>=-10,30,15))))))),"")),"") | T46: 4 | U46: 5 | V46: 5 | W46: 5 | X46: 5 | Y46: =IFERROR((AVERAGE(T46,U46,V46,W46,X46)-1)*25,"") | Z46: 4 | AA46: 5 | AB46: 3 | AC46: 52.5 | AD46: =IFERROR(AVERAGE(IFERROR(IF(Z46="","",Z46*20),""),IFERROR(IF(AA46="","",AA46*20),""),IFERROR(IF(AB46="","",AB46*20),""),IFERROR(IF(AC46="","",IF(AC46>=85,100,IF(AC46>=70,90,IF(AC46>=55,75,IF(AC46>=40,60,IF(AC46>=25,40,20)))))),"")),"") | AE46: 4 | AF46: 4 | AG46: 3 | AH46: 4 | AI46: =IFERROR((AVERAGE(AE46,AF46,AG46,AH46,AL46)-1)*25,"") | AJ46: =IFERROR(J46*Weights!$B$4 + O46*Weights!$B$5 + S46*Weights!$B$6 + Y46*Weights!$B$7 + AD46*Weights!$B$8 + AI46*Weights!$B$9,"") | AK46: =IF(AJ46="","",IF(AJ46>=85,"✓✓✓",IF(AJ46>=70,"✓✓",IF(AJ46>=55,"✓",IF(AJ46>=40,"?","✗"))))) | AL46: 5
A47: IRM | B47: Iron Mountain Incorporated | C47: 03 Data Center Construction, REITs & Cooling | D47: 2026-10-11 | E47: 41.993664 | F47: 21.4 | G47: -1.75 | H47: 4.507779 | I47: =IF(OR(E47="",R47="",R47<=0,E47<0),"",E47/R47) | J47: 49.4 | K47: 7.06 | L47: 54.21 | M47: -7.89 | N47: 7.74 | O47: 39 | P47: 10.58 | Q47: 18.5 | R47: 800.6 | S47: =IFERROR(AVERAGE(IFERROR(IF(P47="","",IF(P47>=40,100,IF(P47>=30,90,IF(P47>=20,75,IF(P47>=15,60,IF(P47>=10,45,IF(P47>=5,30,15))))))),""),IFERROR(IF(Q47="","",IF(Q47>=40,100,IF(Q47>=30,90,IF(Q47>=20,75,IF(Q47>=10,60,IF(Q47>=5,45,IF(Q47>=0,30,15))))))),""),IFERROR(IF(R47="","",IF(R47>=40,100,IF(R47>=30,90,IF(R47>=20,75,IF(R47>=10,60,IF(R47>=0,45,IF(R47>=-10,30,15))))))),"")),"") | T47: 4 | U47: 3 | V47: 3 | W47: 5 | X47: 4 | Y47: =IFERROR((AVERAGE(T47,U47,V47,W47,X47)-1)*25,"") | Z47: 4 | AA47: 5 | AB47: 3 | AC47: 49.2 | AD47: =IFERROR(AVERAGE(IFERROR(IF(Z47="","",Z47*20),""),IFERROR(IF(AA47="","",AA47*20),""),IFERROR(IF(AB47="","",AB47*20),""),IFERROR(IF(AC47="","",IF(AC47>=85,100,IF(AC47>=70,90,IF(AC47>=55,75,IF(AC47>=40,60,IF(AC47>=25,40,20)))))),"")),"") | AE47: 4 | AF47: 4 | AG47: 2 | AH47: 4 | AI47: =IFERROR((AVERAGE(AE47,AF47,AG47,AH47,AL47)-1)*25,"") | AJ47: =IFERROR(J47*Weights!$B$4 + O47*Weights!$B$5 + S47*Weights!$B$6 + Y47*Weights!$B$7 + AD47*Weights!$B$8 + AI47*Weights!$B$9,"") | AK47: =IF(AJ47="","",IF(AJ47>=85,"✓✓✓",IF(AJ47>=70,"✓✓",IF(AJ47>=55,"✓",IF(AJ47>=40,"?","✗"))))) | AL47: 5
A48: FIX | B48: Comfort Systems USA, Inc. | C48: 03 Data Center Construction, REITs & Cooling | D48: 2026-10-11 | E48: 28.510025 | F48: 29.784 | G48: 3.58 | H48: 5.3778434 | I48: =IF(OR(E48="",R48="",R48<=0,E48<0),"",E48/R48) | J48: 65.8 | K48: 38.78 | L48: 25.66 | M48: 19.24 | N48: -0.77 | O48: 73.6 | P48: 30.03 | Q48: 50.3 | R48: 91.3 | S48: =IFERROR(AVERAGE(IFERROR(IF(P48="","",IF(P48>=40,100,IF(P48>=30,90,IF(P48>=20,75,IF(P48>=15,60,IF(P48>=10,45,IF(P48>=5,30,15))))))),""),IFERROR(IF(Q48="","",IF(Q48>=40,100,IF(Q48>=30,90,IF(Q48>=20,75,IF(Q48>=10,60,IF(Q48>=5,45,IF(Q48>=0,30,15))))))),""),IFERROR(IF(R48="","",IF(R48>=40,100,IF(R48>=30,90,IF(R48>=20,75,IF(R48>=10,60,IF(R48>=0,45,IF(R48>=-10,30,15))))))),"")),"") | T48: 5 | U48: 4 | V48: 4 | W48: 5 | X48: 5 | Y48: =IFERROR((AVERAGE(T48,U48,V48,W48,X48)-1)*25,"") | Z48: 5 | AA48: 4 | AB48: 3 | AC48: 47.5 | AD48: =IFERROR(AVERAGE(IFERROR(IF(Z48="","",Z48*20),""),IFERROR(IF(AA48="","",AA48*20),""),IFERROR(IF(AB48="","",AB48*20),""),IFERROR(IF(AC48="","",IF(AC48>=85,100,IF(AC48>=70,90,IF(AC48>=55,75,IF(AC48>=40,60,IF(AC48>=25,40,20)))))),"")),"") | AE48: 4 | AF48: 5 | AG48: 5 | AH48: 4 | AI48: =IFERROR((AVERAGE(AE48,AF48,AG48,AH48,AL48)-1)*25,"") | AJ48: =IFERROR(J48*Weights!$B$4 + O48*Weights!$B$5 + S48*Weights!$B$6 + Y48*Weights!$B$7 + AD48*Weights!$B$8 + AI48*Weights!$B$9,"") | AK48: =IF(AJ48="","",IF(AJ48>=85,"✓✓✓",IF(AJ48>=70,"✓✓",IF(AJ48>=55,"✓",IF(AJ48>=40,"?","✗"))))) | AL48: 5
A49: EME | B49: EMCOR Group, Inc. | C49: 03 Data Center Construction, REITs & Cooling | D49: 2026-10-11 | E49: 21.479156 | F49: 17.199 | G49: 3.36 | H49: 1.8724047 | I49: =IF(OR(E49="",R49="",R49<=0,E49<0),"",E49/R49) | J49: 79.7 | K49: 26.76 | L49: 19.43 | M49: 6.3 | N49: -0.19 | O49: 60.2 | P49: 15.32 | Q49: 19.8 | R49: 33.6 | S49: =IFERROR(AVERAGE(IFERROR(IF(P49="","",IF(P49>=40,100,IF(P49>=30,90,IF(P49>=20,75,IF(P49>=15,60,IF(P49>=10,45,IF(P49>=5,30,15))))))),""),IFERROR(IF(Q49="","",IF(Q49>=40,100,IF(Q49>=30,90,IF(Q49>=20,75,IF(Q49>=10,60,IF(Q49>=5,45,IF(Q49>=0,30,15))))))),""),IFERROR(IF(R49="","",IF(R49>=40,100,IF(R49>=30,90,IF(R49>=20,75,IF(R49>=10,60,IF(R49>=0,45,IF(R49>=-10,30,15))))))),"")),"") | T49: 4 | U49: 4 | V49: 4 | W49: 4 | X49: 4 | Y49: =IFERROR((AVERAGE(T49,U49,V49,W49,X49)-1)*25,"") | Z49: 5 | AA49: 3 | AB49: 3 | AC49: 42.5 | AD49: =IFERROR(AVERAGE(IFERROR(IF(Z49="","",Z49*20),""),IFERROR(IF(AA49="","",AA49*20),""),IFERROR(IF(AB49="","",AB49*20),""),IFERROR(IF(AC49="","",IF(AC49>=85,100,IF(AC49>=70,90,IF(AC49>=55,75,IF(AC49>=40,60,IF(AC49>=25,40,20)))))),"")),"") | AE49: 5 | AF49: 5 | AG49: 5 | AH49: 4 | AI49: =IFERROR((AVERAGE(AE49,AF49,AG49,AH49,AL49)-1)*25,"") | AJ49: =IFERROR(J49*Weights!$B$4 + O49*Weights!$B$5 + S49*Weights!$B$6 + Y49*Weights!$B$7 + AD49*Weights!$B$8 + AI49*Weights!$B$9,"") | AK49: =IF(AJ49="","",IF(AJ49>=85,"✓✓✓",IF(AJ49>=70,"✓✓",IF(AJ49>=55,"✓",IF(AJ49>=40,"?","✗"))))) | AL49: 5
A50: MOD | B50: Modine Manufacturing Company | C50: 03 Data Center Construction, REITs & Cooling | D50: 2026-10-11 | E50: 19.621046 | F50: 23.674 | G50: 1.04 | H50: 2.8594303 | I50: =IF(OR(E50="",R50="",R50<=0,E50<0),"",E50/R50) | J50: 56.7 | K50: 13.9 | L50: 22.21 | M50: 2.97 | N50: 1.28 | O50: 44.9 | P50: 11.45 | Q50: 28 | R50: 44.3 | S50: =IFERROR(AVERAGE(IFERROR(IF(P50="","",IF(P50>=40,100,IF(P50>=30,90,IF(P50>=20,75,IF(P50>=15,60,IF(P50>=10,45,IF(P50>=5,30,15))))))),""),IFERROR(IF(Q50="","",IF(Q50>=40,100,IF(Q50>=30,90,IF(Q50>=20,75,IF(Q50>=10,60,IF(Q50>=5,45,IF(Q50>=0,30,15))))))),""),IFERROR(IF(R50="","",IF(R50>=40,100,IF(R50>=30,90,IF(R50>=20,75,IF(R50>=10,60,IF(R50>=0,45,IF(R50>=-10,30,15))))))),"")),"") | T50: 4 | U50: 4 | V50: 4 | W50: 5 | X50: 5 | Y50: =IFERROR((AVERAGE(T50,U50,V50,W50,X50)-1)*25,"") | Z50: 4 | AA50: 5 | AB50: 3 | AC50: 37.5 | AD50: =IFERROR(AVERAGE(IFERROR(IF(Z50="","",Z50*20),""),IFERROR(IF(AA50="","",AA50*20),""),IFERROR(IF(AB50="","",AB50*20),""),IFERROR(IF(AC50="","",IF(AC50>=85,100,IF(AC50>=70,90,IF(AC50>=55,75,IF(AC50>=40,60,IF(AC50>=25,40,20)))))),"")),"") | AE50: 2 | AF50: 4 | AG50: 3 | AH50: 4 | AI50: =IFERROR((AVERAGE(AE50,AF50,AG50,AH50,AL50)-1)*25,"") | AJ50: =IFERROR(J50*Weights!$B$4 + O50*Weights!$B$5 + S50*Weights!$B$6 + Y50*Weights!$B$7 + AD50*Weights!$B$8 + AI50*Weights!$B$9,"") | AK50: =IF(AJ50="","",IF(AJ50>=85,"✓✓✓",IF(AJ50>=70,"✓✓",IF(AJ50>=55,"✓",IF(AJ50>=40,"?","✗"))))) | AL50: 5
A51: CARR | B51: Carrier Global Corporation | C51: 03 Data Center Construction, REITs & Cooling | D51: 2026-10-11 | E51: 16.849077 | F51: 18.336 | G51: 4.18 | H51: 2.087346 | I51: =IF(OR(E51="",R51="",R51<=0,E51<0),"",E51/R51) | J51: 60.7 | K51: 5.33 | L51: 24.69 | M51: 8.72 | N51: 3.57 | O51: 35.1 | P51: 7.95 | Q51: 3.9 | R51: -15.2 | S51: =IFERROR(AVERAGE(IFERROR(IF(P51="","",IF(P51>=40,100,IF(P51>=30,90,IF(P51>=20,75,IF(P51>=15,60,IF(P51>=10,45,IF(P51>=5,30,15))))))),""),IFERROR(IF(Q51="","",IF(Q51>=40,100,IF(Q51>=30,90,IF(Q51>=20,75,IF(Q51>=10,60,IF(Q51>=5,45,IF(Q51>=0,30,15))))))),""),IFERROR(IF(R51="","",IF(R51>=40,100,IF(R51>=30,90,IF(R51>=20,75,IF(R51>=10,60,IF(R51>=0,45,IF(R51>=-10,30,15))))))),"")),"") | T51: 3 | U51: 4 | V51: 3 | W51: 4 | X51: 4 | Y51: =IFERROR((AVERAGE(T51,U51,V51,W51,X51)-1)*25,"") | Z51: 3 | AA51: 4 | AB51: 3 | AC51: 53.3 | AD51: =IFERROR(AVERAGE(IFERROR(IF(Z51="","",Z51*20),""),IFERROR(IF(AA51="","",AA51*20),""),IFERROR(IF(AB51="","",AB51*20),""),IFERROR(IF(AC51="","",IF(AC51>=85,100,IF(AC51>=70,90,IF(AC51>=55,75,IF(AC51>=40,60,IF(AC51>=25,40,20)))))),"")),"") | AE51: 5 | AF51: 4 | AG51: 3 | AH51: 4 | AI51: =IFERROR((AVERAGE(AE51,AF51,AG51,AH51,AL51)-1)*25,"") | AJ51: =IFERROR(J51*Weights!$B$4 + O51*Weights!$B$5 + S51*Weights!$B$6 + Y51*Weights!$B$7 + AD51*Weights!$B$8 + AI51*Weights!$B$9,"") | AK51: =IF(AJ51="","",IF(AJ51>=85,"✓✓✓",IF(AJ51>=70,"✓✓",IF(AJ51>=55,"✓",IF(AJ51>=40,"?","✗"))))) | AL51: 5
A52: TT | B52: Trane Technologies plc | C52: 03 Data Center Construction, REITs & Cooling | D52: 2026-10-11 | E52: 27.09564 | F52: 24.633 | G52: 3.38 | H52: 4.7252197 | I52: =IF(OR(E52="",R52="",R52<=0,E52<0),"",E52/R52) | J52: 54.4 | K52: 20.78 | L52: 35.39 | M52: 15.97 | N52: 0.77 | O52: 69.1 | P52: 10.06 | Q52: 10.6 | R52: 5.8 | S52: =IFERROR(AVERAGE(IFERROR(IF(P52="","",IF(P52>=40,100,IF(P52>=30,90,IF(P52>=20,75,IF(P52>=15,60,IF(P52>=10,45,IF(P52>=5,30,15))))))),""),IFERROR(IF(Q52="","",IF(Q52>=40,100,IF(Q52>=30,90,IF(Q52>=20,75,IF(Q52>=10,60,IF(Q52>=5,45,IF(Q52>=0,30,15))))))),""),IFERROR(IF(R52="","",IF(R52>=40,100,IF(R52>=30,90,IF(R52>=20,75,IF(R52>=10,60,IF(R52>=0,45,IF(R52>=-10,30,15))))))),"")),"") | T52: 3 | U52: 4 | V52: 4 | W52: 5 | X52: 4 | Y52: =IFERROR((AVERAGE(T52,U52,V52,W52,X52)-1)*25,"") | Z52: 5 | AA52: 3 | AB52: 3 | AC52: 60.8 | AD52: =IFERROR(AVERAGE(IFERROR(IF(Z52="","",Z52*20),""),IFERROR(IF(AA52="","",AA52*20),""),IFERROR(IF(AB52="","",AB52*20),""),IFERROR(IF(AC52="","",IF(AC52>=85,100,IF(AC52>=70,90,IF(AC52>=55,75,IF(AC52>=40,60,IF(AC52>=25,40,20)))))),"")),"") | AE52: 5 | AF52: 4 | AG52: 4 | AH52: 4 | AI52: =IFERROR((AVERAGE(AE52,AF52,AG52,AH52,AL52)-1)*25,"") | AJ52: =IFERROR(J52*Weights!$B$4 + O52*Weights!$B$5 + S52*Weights!$B$6 + Y52*Weights!$B$7 + AD52*Weights!$B$8 + AI52*Weights!$B$9,"") | AK52: =IF(AJ52="","",IF(AJ52>=85,"✓✓✓",IF(AJ52>=70,"✓✓",IF(AJ52>=55,"✓",IF(AJ52>=40,"?","✗"))))) | AL52: 5
A53: JCI | B53: Johnson Controls International plc | C53: 03 Data Center Construction, REITs & Cooling | D53: 2026-10-11 | E53: 25.793896 | F53: 23.889 | G53: 1.74 | H53: 3.8154802 | I53: =IF(OR(E53="",R53="",R53<=0,E53<0),"",E53/R53) | J53: 61.6 | K53: 10.59 | L53: 36.65 | M53: 6.64 | N53: 2.04 | O53: 50.2 | P53: 4.57 | Q53: 9.3 | R53: 6.8 | S53: =IFERROR(AVERAGE(IFERROR(IF(P53="","",IF(P53>=40,100,IF(P53>=30,90,IF(P53>=20,75,IF(P53>=15,60,IF(P53>=10,45,IF(P53>=5,30,15))))))),""),IFERROR(IF(Q53="","",IF(Q53>=40,100,IF(Q53>=30,90,IF(Q53>=20,75,IF(Q53>=10,60,IF(Q53>=5,45,IF(Q53>=0,30,15))))))),""),IFERROR(IF(R53="","",IF(R53>=40,100,IF(R53>=30,90,IF(R53>=20,75,IF(R53>=10,60,IF(R53>=0,45,IF(R53>=-10,30,15))))))),"")),"") | T53: 3 | U53: 4 | V53: 4 | W53: 4 | X53: 4 | Y53: =IFERROR((AVERAGE(T53,U53,V53,W53,X53)-1)*25,"") | Z53: 5 | AA53: 4 | AB53: 3 | AC53: 67.5 | AD53: =IFERROR(AVERAGE(IFERROR(IF(Z53="","",Z53*20),""),IFERROR(IF(AA53="","",AA53*20),""),IFERROR(IF(AB53="","",AB53*20),""),IFERROR(IF(AC53="","",IF(AC53>=85,100,IF(AC53>=70,90,IF(AC53>=55,75,IF(AC53>=40,60,IF(AC53>=25,40,20)))))),"")),"") | AE53: 5 | AF53: 4 | AG53: 4 | AH53: 4 | AI53: =IFERROR((AVERAGE(AE53,AF53,AG53,AH53,AL53)-1)*25,"") | AJ53: =IFERROR(J53*Weights!$B$4 + O53*Weights!$B$5 + S53*Weights!$B$6 + Y53*Weights!$B$7 + AD53*Weights!$B$8 + AI53*Weights!$B$9,"") | AK53: =IF(AJ53="","",IF(AJ53>=85,"✓✓✓",IF(AJ53>=70,"✓✓",IF(AJ53>=55,"✓",IF(AJ53>=40,"?","✗"))))) | AL53: 5
A54: ASML | B54: ASML Holding N.V. | C54: 04 Semiconductor Equipment & Materials / Equipment | D54: 2026-10-11 | E54: 30.446087 | F54: 44.83 | G54: 1.46 | H54: 17.27 | I54: =IF(OR(E54="",R54="",R54<=0,E54<0),"",E54/R54) | J54: 45.3 | K54: 36.76 | L54: 52.73 | M54: 25.18 | N54: -0.41 | O54: 59.9 | P54: 15.55 | Q54: 21.3 | R54: 27.4 | S54: =IFERROR(AVERAGE(IFERROR(IF(P54="","",IF(P54>=40,100,IF(P54>=30,90,IF(P54>=20,75,IF(P54>=15,60,IF(P54>=10,45,IF(P54>=5,30,15))))))),""),IFERROR(IF(Q54="","",IF(Q54>=40,100,IF(Q54>=30,90,IF(Q54>=20,75,IF(Q54>=10,60,IF(Q54>=5,45,IF(Q54>=0,30,15))))))),""),IFERROR(IF(R54="","",IF(R54>=40,100,IF(R54>=30,90,IF(R54>=20,75,IF(R54>=10,60,IF(R54>=0,45,IF(R54>=-10,30,15))))))),"")),"") | T54: 3 | U54: 5 | V54: 5 | W54: 4 | X54: 2 | Y54: =IFERROR((AVERAGE(T54,U54,V54,W54,X54)-1)*25,"") | Z54: 4 | AA54: 2 | AB54: 3 | AC54: 70 | AD54: =IFERROR(AVERAGE(IFERROR(IF(Z54="","",Z54*20),""),IFERROR(IF(AA54="","",AA54*20),""),IFERROR(IF(AB54="","",AB54*20),""),IFERROR(IF(AC54="","",IF(AC54>=85,100,IF(AC54>=70,90,IF(AC54>=55,75,IF(AC54>=40,60,IF(AC54>=25,40,20)))))),"")),"") | AE54: 4 | AF54: 3 | AG54: 5 | AH54: 3 | AI54: =IFERROR((AVERAGE(AE54,AF54,AG54,AH54,AL54)-1)*25,"") | AJ54: =IFERROR(J54*Weights!$B$4 + O54*Weights!$B$5 + S54*Weights!$B$6 + Y54*Weights!$B$7 + AD54*Weights!$B$8 + AI54*Weights!$B$9,"") | AK54: =IF(AJ54="","",IF(AJ54>=85,"✓✓✓",IF(AJ54>=70,"✓✓",IF(AJ54>=55,"✓",IF(AJ54>=40,"?","✗"))))) | AL54: 5
A55: AMAT | B55: Applied Materials, Inc. | C55: 04 Semiconductor Equipment & Materials / Equipment | D55: 2026-10-11 | E55: 27.438263 | F55: 40.502 | G55: 1.4 | H55: 13.048536 | I55: =IF(OR(E55="",R55="",R55<=0,E55<0),"",E55/R55) | J55: 37.6 | K55: 24.97 | L55: 49.4 | M55: 18.23 | N55: -0.19 | O55: 75 | P55: 3.23 | Q55: 24.8 | R55: 42.7 | S55: =IFERROR(AVERAGE(IFERROR(IF(P55="","",IF(P55>=40,100,IF(P55>=30,90,IF(P55>=20,75,IF(P55>=15,60,IF(P55>=10,45,IF(P55>=5,30,15))))))),""),IFERROR(IF(Q55="","",IF(Q55>=40,100,IF(Q55>=30,90,IF(Q55>=20,75,IF(Q55>=10,60,IF(Q55>=5,45,IF(Q55>=0,30,15))))))),""),IFERROR(IF(R55="","",IF(R55>=40,100,IF(R55>=30,90,IF(R55>=20,75,IF(R55>=10,60,IF(R55>=0,45,IF(R55>=-10,30,15))))))),"")),"") | T55: 3 | U55: 4 | V55: 4 | W55: 5 | X55: 2 | Y55: =IFERROR((AVERAGE(T55,U55,V55,W55,X55)-1)*25,"") | Z55: 4 | AA55: 3 | AB55: 3 | AC55: 60.8 | AD55: =IFERROR(AVERAGE(IFERROR(IF(Z55="","",Z55*20),""),IFERROR(IF(AA55="","",AA55*20),""),IFERROR(IF(AB55="","",AB55*20),""),IFERROR(IF(AC55="","",IF(AC55>=85,100,IF(AC55>=70,90,IF(AC55>=55,75,IF(AC55>=40,60,IF(AC55>=25,40,20)))))),"")),"") | AE55: 4 | AF55: 3 | AG55: 5 | AH55: 4 | AI55: =IFERROR((AVERAGE(AE55,AF55,AG55,AH55,AL55)-1)*25,"") | AJ55: =IFERROR(J55*Weights!$B$4 + O55*Weights!$B$5 + S55*Weights!$B$6 + Y55*Weights!$B$7 + AD55*Weights!$B$8 + AI55*Weights!$B$9,"") | AK55: =IF(AJ55="","",IF(AJ55>=85,"✓✓✓",IF(AJ55>=70,"✓✓",IF(AJ55>=55,"✓",IF(AJ55>=40,"?","✗"))))) | AL55: 5
A56: LRCX | B56: Lam Research Corporation | C56: 04 Semiconductor Equipment & Materials / Equipment | D56: 2026-10-11 | E56: 29.962131 | F56: 47.547 | G56: 1.23 | H56: 17.174255 | I56: =IF(OR(E56="",R56="",R56<=0,E56<0),"",E56/R56) | J56: 37 | K56: 40.98 | L56: 50.47 | M56: 21.05 | N56: -0.17 | O56: 87 | P56: 10.06 | Q56: 30 | R56: 32.4 | S56: =IFERROR(AVERAGE(IFERROR(IF(P56="","",IF(P56>=40,100,IF(P56>=30,90,IF(P56>=20,75,IF(P56>=15,60,IF(P56>=10,45,IF(P56>=5,30,15))))))),""),IFERROR(IF(Q56="","",IF(Q56>=40,100,IF(Q56>=30,90,IF(Q56>=20,75,IF(Q56>=10,60,IF(Q56>=5,45,IF(Q56>=0,30,15))))))),""),IFERROR(IF(R56="","",IF(R56>=40,100,IF(R56>=30,90,IF(R56>=20,75,IF(R56>=10,60,IF(R56>=0,45,IF(R56>=-10,30,15))))))),"")),"") | T56: 3 | U56: 4 | V56: 4 | W56: 5 | X56: 2 | Y56: =IFERROR((AVERAGE(T56,U56,V56,W56,X56)-1)*25,"") | Z56: 5 | AA56: 4 | AB56: 3 | AC56: 60.8 | AD56: =IFERROR(AVERAGE(IFERROR(IF(Z56="","",Z56*20),""),IFERROR(IF(AA56="","",AA56*20),""),IFERROR(IF(AB56="","",AB56*20),""),IFERROR(IF(AC56="","",IF(AC56>=85,100,IF(AC56>=70,90,IF(AC56>=55,75,IF(AC56>=40,60,IF(AC56>=25,40,20)))))),"")),"") | AE56: 4 | AF56: 3 | AG56: 5 | AH56: 4 | AI56: =IFERROR((AVERAGE(AE56,AF56,AG56,AH56,AL56)-1)*25,"") | AJ56: =IFERROR(J56*Weights!$B$4 + O56*Weights!$B$5 + S56*Weights!$B$6 + Y56*Weights!$B$7 + AD56*Weights!$B$8 + AI56*Weights!$B$9,"") | AK56: =IF(AJ56="","",IF(AJ56>=85,"✓✓✓",IF(AJ56>=70,"✓✓",IF(AJ56>=55,"✓",IF(AJ56>=40,"?","✗"))))) | AL56: 5
A57: KLAC | B57: KLA Corporation | C57: 04 Semiconductor Equipment & Materials / Equipment | D57: 2026-10-11 | E57: 32.090569 | F57: 42.68 | G57: 1.48 | H57: 18.794548 | I57: =IF(OR(E57="",R57="",R57<=0,E57<0),"",E57/R57) | J57: 23.2 | K57: 35.75 | L57: 61.3 | M57: 27.74 | N57: 0.21 | O57: 88 | P57: 8.96 | Q57: 15.2 | R57: 13.3 | S57: =IFERROR(AVERAGE(IFERROR(IF(P57="","",IF(P57>=40,100,IF(P57>=30,90,IF(P57>=20,75,IF(P57>=15,60,IF(P57>=10,45,IF(P57>=5,30,15))))))),""),IFERROR(IF(Q57="","",IF(Q57>=40,100,IF(Q57>=30,90,IF(Q57>=20,75,IF(Q57>=10,60,IF(Q57>=5,45,IF(Q57>=0,30,15))))))),""),IFERROR(IF(R57="","",IF(R57>=40,100,IF(R57>=30,90,IF(R57>=20,75,IF(R57>=10,60,IF(R57>=0,45,IF(R57>=-10,30,15))))))),"")),"") | T57: 4 | U57: 5 | V57: 5 | W57: 4 | X57: 4 | Y57: =IFERROR((AVERAGE(T57,U57,V57,W57,X57)-1)*25,"") | Z57: 5 | AA57: 2 | AB57: 3 | AC57: 58.3 | AD57: =IFERROR(AVERAGE(IFERROR(IF(Z57="","",Z57*20),""),IFERROR(IF(AA57="","",AA57*20),""),IFERROR(IF(AB57="","",AB57*20),""),IFERROR(IF(AC57="","",IF(AC57>=85,100,IF(AC57>=70,90,IF(AC57>=55,75,IF(AC57>=40,60,IF(AC57>=25,40,20)))))),"")),"") | AE57: 4 | AF57: 3 | AG57: 5 | AH57: 4 | AI57: =IFERROR((AVERAGE(AE57,AF57,AG57,AH57,AL57)-1)*25,"") | AJ57: =IFERROR(J57*Weights!$B$4 + O57*Weights!$B$5 + S57*Weights!$B$6 + Y57*Weights!$B$7 + AD57*Weights!$B$8 + AI57*Weights!$B$9,"") | AK57: =IF(AJ57="","",IF(AJ57>=85,"✓✓✓",IF(AJ57>=70,"✓✓",IF(AJ57>=55,"✓",IF(AJ57>=40,"?","✗"))))) | AL57: 5
A58: TOELY | B58: Tokyo Electron Limited | C58: 04 Semiconductor Equipment & Materials / Equipment | D58: 2026-10-11 | F58: 31.27 | G58: 1.2 | H58: 9.42 | I58: =IF(OR(E58="",R58="",R58<=0,E58<0),"",E58/R58) | J58: 38.9 | L58: 45.56 | M58: 11.32 | N58: -0.53 | O58: 61.2 | P58: 3.42 | Q58: 33.3 | R58: 39.5 | S58: =IFERROR(AVERAGE(IFERROR(IF(P58="","",IF(P58>=40,100,IF(P58>=30,90,IF(P58>=20,75,IF(P58>=15,60,IF(P58>=10,45,IF(P58>=5,30,15))))))),""),IFERROR(IF(Q58="","",IF(Q58>=40,100,IF(Q58>=30,90,IF(Q58>=20,75,IF(Q58>=10,60,IF(Q58>=5,45,IF(Q58>=0,30,15))))))),""),IFERROR(IF(R58="","",IF(R58>=40,100,IF(R58>=30,90,IF(R58>=20,75,IF(R58>=10,60,IF(R58>=0,45,IF(R58>=-10,30,15))))))),"")),"") | T58: 3 | U58: 4 | V58: 4 | W58: 4 | X58: 3 | Y58: =IFERROR((AVERAGE(T58,U58,V58,W58,X58)-1)*25,"") | Z58: 3 | AA58: 2 | AB58: 3 | AC58: 81.7 | AD58: =IFERROR(AVERAGE(IFERROR(IF(Z58="","",Z58*20),""),IFERROR(IF(AA58="","",AA58*20),""),IFERROR(IF(AB58="","",AB58*20),""),IFERROR(IF(AC58="","",IF(AC58>=85,100,IF(AC58>=70,90,IF(AC58>=55,75,IF(AC58>=40,60,IF(AC58>=25,40,20)))))),"")),"") | AE58: 4 | AF58: 3 | AG58: 5 | AH58: 4 | AI58: =IFERROR((AVERAGE(AE58,AF58,AG58,AH58,AL58)-1)*25,"") | AJ58: =IFERROR(J58*Weights!$B$4 + O58*Weights!$B$5 + S58*Weights!$B$6 + Y58*Weights!$B$7 + AD58*Weights!$B$8 + AI58*Weights!$B$9,"") | AK58: =IF(AJ58="","",IF(AJ58>=85,"✓✓✓",IF(AJ58>=70,"✓✓",IF(AJ58>=55,"✓",IF(AJ58>=40,"?","✗"))))) | AL58: 5
A59: TER | B59: Teradyne, Inc. | C59: 04 Semiconductor Equipment & Materials / Equipment | D59: 2026-10-11 | E59: 34.55748 | F59: 42.634 | G59: 1.27 | H59: 14.10279 | I59: =IF(OR(E59="",R59="",R59<=0,E59<0),"",E59/R59) | J59: 48.5 | K59: 31.27 | L59: 59.24 | M59: 17.92 | N59: -0.17 | O59: 79.4 | P59: 0.37 | Q59: 103.9 | R59: 377.9 | S59: =IFERROR(AVERAGE(IFERROR(IF(P59="","",IF(P59>=40,100,IF(P59>=30,90,IF(P59>=20,75,IF(P59>=15,60,IF(P59>=10,45,IF(P59>=5,30,15))))))),""),IFERROR(IF(Q59="","",IF(Q59>=40,100,IF(Q59>=30,90,IF(Q59>=20,75,IF(Q59>=10,60,IF(Q59>=5,45,IF(Q59>=0,30,15))))))),""),IFERROR(IF(R59="","",IF(R59>=40,100,IF(R59>=30,90,IF(R59>=20,75,IF(R59>=10,60,IF(R59>=0,45,IF(R59>=-10,30,15))))))),"")),"") | T59: 5 | U59: 4 | V59: 4 | W59: 4 | X59: 3 | Y59: =IFERROR((AVERAGE(T59,U59,V59,W59,X59)-1)*25,"") | Z59: 5 | AA59: 1 | AB59: 3 | AC59: 61.7 | AD59: =IFERROR(AVERAGE(IFERROR(IF(Z59="","",Z59*20),""),IFERROR(IF(AA59="","",AA59*20),""),IFERROR(IF(AB59="","",AB59*20),""),IFERROR(IF(AC59="","",IF(AC59>=85,100,IF(AC59>=70,90,IF(AC59>=55,75,IF(AC59>=40,60,IF(AC59>=25,40,20)))))),"")),"") | AE59: 4 | AF59: 4 | AG59: 5 | AH59: 4 | AI59: =IFERROR((AVERAGE(AE59,AF59,AG59,AH59,AL59)-1)*25,"") | AJ59: =IFERROR(J59*Weights!$B$4 + O59*Weights!$B$5 + S59*Weights!$B$6 + Y59*Weights!$B$7 + AD59*Weights!$B$8 + AI59*Weights!$B$9,"") | AK59: =IF(AJ59="","",IF(AJ59>=85,"✓✓✓",IF(AJ59>=70,"✓✓",IF(AJ59>=55,"✓",IF(AJ59>=40,"?","✗"))))) | AL59: 5
A60: ONTO | B60: Onto Innovation Inc. | C60: 04 Semiconductor Equipment & Materials / Equipment | D60: 2026-10-11 | E60: 25.243868 | F60: 47.014 | G60: 1.75 | H60: 12.903634 | I60: =IF(OR(E60="",R60="",R60<=0,E60<0),"",E60/R60) | J60: 38.3 | K60: 3.79 | L60: 55.49 | M60: 22.54 | N60: -1.33 | O60: 65.6 | P60: 0 | Q60: 35.3 | R60: 77.2 | S60: =IFERROR(AVERAGE(IFERROR(IF(P60="","",IF(P60>=40,100,IF(P60>=30,90,IF(P60>=20,75,IF(P60>=15,60,IF(P60>=10,45,IF(P60>=5,30,15))))))),""),IFERROR(IF(Q60="","",IF(Q60>=40,100,IF(Q60>=30,90,IF(Q60>=20,75,IF(Q60>=10,60,IF(Q60>=5,45,IF(Q60>=0,30,15))))))),""),IFERROR(IF(R60="","",IF(R60>=40,100,IF(R60>=30,90,IF(R60>=20,75,IF(R60>=10,60,IF(R60>=0,45,IF(R60>=-10,30,15))))))),"")),"") | T60: 5 | U60: 4 | V60: 4 | W60: 5 | X60: 4 | Y60: =IFERROR((AVERAGE(T60,U60,V60,W60,X60)-1)*25,"") | Z60: 5 | AA60: 2 | AB60: 3 | AC60: 62.5 | AD60: =IFERROR(AVERAGE(IFERROR(IF(Z60="","",Z60*20),""),IFERROR(IF(AA60="","",AA60*20),""),IFERROR(IF(AB60="","",AB60*20),""),IFERROR(IF(AC60="","",IF(AC60>=85,100,IF(AC60>=70,90,IF(AC60>=55,75,IF(AC60>=40,60,IF(AC60>=25,40,20)))))),"")),"") | AE60: 4 | AF60: 4 | AG60: 5 | AH60: 4 | AI60: =IFERROR((AVERAGE(AE60,AF60,AG60,AH60,AL60)-1)*25,"") | AJ60: =IFERROR(J60*Weights!$B$4 + O60*Weights!$B$5 + S60*Weights!$B$6 + Y60*Weights!$B$7 + AD60*Weights!$B$8 + AI60*Weights!$B$9,"") | AK60: =IF(AJ60="","",IF(AJ60>=85,"✓✓✓",IF(AJ60>=70,"✓✓",IF(AJ60>=55,"✓",IF(AJ60>=40,"?","✗"))))) | AL60: 5
A61: CAMT | B61: Camtek Ltd. | C61: 04 Semiconductor Equipment & Materials / Equipment | D61: 2026-10-11 | E61: 31.907806 | F61: 50.318 | H61: 14.288648 | I61: =IF(OR(E61="",R61="",R61<=0,E61<0),"",E61/R61) | J61: 32.2 | K61: 7.81 | L61: 50.97 | N61: -1.32 | O61: 68.4 | P61: 15.63 | Q61: 2.5 | R61: -7.8 | S61: =IFERROR(AVERAGE(IFERROR(IF(P61="","",IF(P61>=40,100,IF(P61>=30,90,IF(P61>=20,75,IF(P61>=15,60,IF(P61>=10,45,IF(P61>=5,30,15))))))),""),IFERROR(IF(Q61="","",IF(Q61>=40,100,IF(Q61>=30,90,IF(Q61>=20,75,IF(Q61>=10,60,IF(Q61>=5,45,IF(Q61>=0,30,15))))))),""),IFERROR(IF(R61="","",IF(R61>=40,100,IF(R61>=30,90,IF(R61>=20,75,IF(R61>=10,60,IF(R61>=0,45,IF(R61>=-10,30,15))))))),"")),"") | T61: 5 | U61: 3 | V61: 3 | W61: 4 | X61: 4 | Y61: =IFERROR((AVERAGE(T61,U61,V61,W61,X61)-1)*25,"") | Z61: 3 | AA61: 2 | AB61: 3 | AC61: 36.7 | AD61: =IFERROR(AVERAGE(IFERROR(IF(Z61="","",Z61*20),""),IFERROR(IF(AA61="","",AA61*20),""),IFERROR(IF(AB61="","",AB61*20),""),IFERROR(IF(AC61="","",IF(AC61>=85,100,IF(AC61>=70,90,IF(AC61>=55,75,IF(AC61>=40,60,IF(AC61>=25,40,20)))))),"")),"") | AE61: 4 | AF61: 4 | AG61: 4 | AH61: 4 | AI61: =IFERROR((AVERAGE(AE61,AF61,AG61,AH61,AL61)-1)*25,"") | AJ61: =IFERROR(J61*Weights!$B$4 + O61*Weights!$B$5 + S61*Weights!$B$6 + Y61*Weights!$B$7 + AD61*Weights!$B$8 + AI61*Weights!$B$9,"") | AK61: =IF(AJ61="","",IF(AJ61>=85,"✓✓✓",IF(AJ61>=70,"✓✓",IF(AJ61>=55,"✓",IF(AJ61>=40,"?","✗"))))) | AL61: 5
A62: KLIC | B62: Kulicke and Soffa Industries, Inc. | C62: 04 Semiconductor Equipment & Materials / Equipment | D62: 2026-10-11 | E62: 15.586119 | F62: 23.396 | G62: 0.83 | H62: 5.0670767 | I62: =IF(OR(E62="",R62="",R62<=0,E62<0),"",E62/R62) | J62: 33.1 | K62: 10.07 | L62: 52.64 | M62: 4.21 | N62: -2.49 | O62: 59.2 | P62: -24.23 | Q62: 122.6 | S62: =IFERROR(AVERAGE(IFERROR(IF(P62="","",IF(P62>=40,100,IF(P62>=30,90,IF(P62>=20,75,IF(P62>=15,60,IF(P62>=10,45,IF(P62>=5,30,15))))))),""),IFERROR(IF(Q62="","",IF(Q62>=40,100,IF(Q62>=30,90,IF(Q62>=20,75,IF(Q62>=10,60,IF(Q62>=5,45,IF(Q62>=0,30,15))))))),""),IFERROR(IF(R62="","",IF(R62>=40,100,IF(R62>=30,90,IF(R62>=20,75,IF(R62>=10,60,IF(R62>=0,45,IF(R62>=-10,30,15))))))),"")),"") | T62: 4 | U62: 3 | V62: 3 | W62: 5 | X62: 4 | Y62: =IFERROR((AVERAGE(T62,U62,V62,W62,X62)-1)*25,"") | Z62: 3 | AA62: 5 | AB62: 3 | AC62: 55.8 | AD62: =IFERROR(AVERAGE(IFERROR(IF(Z62="","",Z62*20),""),IFERROR(IF(AA62="","",AA62*20),""),IFERROR(IF(AB62="","",AB62*20),""),IFERROR(IF(AC62="","",IF(AC62>=85,100,IF(AC62>=70,90,IF(AC62>=55,75,IF(AC62>=40,60,IF(AC62>=25,40,20)))))),"")),"") | AE62: 4 | AF62: 4 | AG62: 4 | AH62: 4 | AI62: =IFERROR((AVERAGE(AE62,AF62,AG62,AH62,AL62)-1)*25,"") | AJ62: =IFERROR(J62*Weights!$B$4 + O62*Weights!$B$5 + S62*Weights!$B$6 + Y62*Weights!$B$7 + AD62*Weights!$B$8 + AI62*Weights!$B$9,"") | AK62: =IF(AJ62="","",IF(AJ62>=85,"✓✓✓",IF(AJ62>=70,"✓✓",IF(AJ62>=55,"✓",IF(AJ62>=40,"?","✗"))))) | AL62: 5
A63: ENTG | B63: Entegris, Inc. | C63: 04 Semiconductor Equipment & Materials / Materials & consumables | D63: 2026-10-11 | E63: 32.961285 | F63: 31.289 | G63: 2 | H63: 7.5914183 | I63: =IF(OR(E63="",R63="",R63<=0,E63<0),"",E63/R63) | J63: 61.7 | K63: 11.41 | L63: 45.56 | M63: 15.19 | N63: 3.51 | O63: 51.2 | P63: -0.88 | Q63: 11.5 | R63: 77.3 | S63: =IFERROR(AVERAGE(IFERROR(IF(P63="","",IF(P63>=40,100,IF(P63>=30,90,IF(P63>=20,75,IF(P63>=15,60,IF(P63>=10,45,IF(P63>=5,30,15))))))),""),IFERROR(IF(Q63="","",IF(Q63>=40,100,IF(Q63>=30,90,IF(Q63>=20,75,IF(Q63>=10,60,IF(Q63>=5,45,IF(Q63>=0,30,15))))))),""),IFERROR(IF(R63="","",IF(R63>=40,100,IF(R63>=30,90,IF(R63>=20,75,IF(R63>=10,60,IF(R63>=0,45,IF(R63>=-10,30,15))))))),"")),"") | T63: 4 | U63: 4 | V63: 4 | W63: 4 | X63: 4 | Y63: =IFERROR((AVERAGE(T63,U63,V63,W63,X63)-1)*25,"") | Z63: 4 | AA63: 3 | AB63: 3 | AC63: 58.3 | AD63: =IFERROR(AVERAGE(IFERROR(IF(Z63="","",Z63*20),""),IFERROR(IF(AA63="","",AA63*20),""),IFERROR(IF(AB63="","",AB63*20),""),IFERROR(IF(AC63="","",IF(AC63>=85,100,IF(AC63>=70,90,IF(AC63>=55,75,IF(AC63>=40,60,IF(AC63>=25,40,20)))))),"")),"") | AE63: 4 | AF63: 4 | AG63: 4 | AH63: 4 | AI63: =IFERROR((AVERAGE(AE63,AF63,AG63,AH63,AL63)-1)*25,"") | AJ63: =IFERROR(J63*Weights!$B$4 + O63*Weights!$B$5 + S63*Weights!$B$6 + Y63*Weights!$B$7 + AD63*Weights!$B$8 + AI63*Weights!$B$9,"") | AK63: =IF(AJ63="","",IF(AJ63>=85,"✓✓✓",IF(AJ63>=70,"✓✓",IF(AJ63>=55,"✓",IF(AJ63>=40,"?","✗"))))) | AL63: 5
A64: MKSI | B64: MKS Inc. | C64: 04 Semiconductor Equipment & Materials / Materials & consumables | D64: 2026-10-11 | E64: 15.073424 | F64: 20.856 | G64: 2.54 | H64: 4.114296 | I64: =IF(OR(E64="",R64="",R64<=0,E64<0),"",E64/R64) | J64: 64.7 | K64: 10.04 | L64: 46.95 | M64: 10.47 | N64: 3.38 | O64: 48.3 | P64: 3.49 | Q64: 28.3 | R64: 182.3 | S64: =IFERROR(AVERAGE(IFERROR(IF(P64="","",IF(P64>=40,100,IF(P64>=30,90,IF(P64>=20,75,IF(P64>=15,60,IF(P64>=10,45,IF(P64>=5,30,15))))))),""),IFERROR(IF(Q64="","",IF(Q64>=40,100,IF(Q64>=30,90,IF(Q64>=20,75,IF(Q64>=10,60,IF(Q64>=5,45,IF(Q64>=0,30,15))))))),""),IFERROR(IF(R64="","",IF(R64>=40,100,IF(R64>=30,90,IF(R64>=20,75,IF(R64>=10,60,IF(R64>=0,45,IF(R64>=-10,30,15))))))),"")),"") | T64: 4 | U64: 3 | V64: 3 | W64: 4 | X64: 4 | Y64: =IFERROR((AVERAGE(T64,U64,V64,W64,X64)-1)*25,"") | Z64: 5 | AA64: 5 | AB64: 3 | AC64: 51.7 | AD64: =IFERROR(AVERAGE(IFERROR(IF(Z64="","",Z64*20),""),IFERROR(IF(AA64="","",AA64*20),""),IFERROR(IF(AB64="","",AB64*20),""),IFERROR(IF(AC64="","",IF(AC64>=85,100,IF(AC64>=70,90,IF(AC64>=55,75,IF(AC64>=40,60,IF(AC64>=25,40,20)))))),"")),"") | AE64: 4 | AF64: 4 | AG64: 4 | AH64: 4 | AI64: =IFERROR((AVERAGE(AE64,AF64,AG64,AH64,AL64)-1)*25,"") | AJ64: =IFERROR(J64*Weights!$B$4 + O64*Weights!$B$5 + S64*Weights!$B$6 + Y64*Weights!$B$7 + AD64*Weights!$B$8 + AI64*Weights!$B$9,"") | AK64: =IF(AJ64="","",IF(AJ64>=85,"✓✓✓",IF(AJ64>=70,"✓✓",IF(AJ64>=55,"✓",IF(AJ64>=40,"?","✗"))))) | AL64: 5
A65: PLAB | B65: Photronics, Inc. | C65: 04 Semiconductor Equipment & Materials / Materials & consumables | D65: 2026-10-11 | E65: 14.263221 | F65: 5.735 | G65: 6.32 | H65: 2.0159757 | I65: =IF(OR(E65="",R65="",R65<=0,E65<0),"",E65/R65) | J65: 86.4 | K65: 9.46 | L65: 33.66 | M65: 12.73 | N65: -2.44 | O65: 55.8 | P65: 0.99 | Q65: 2.7 | R65: 26.3 | S65: =IFERROR(AVERAGE(IFERROR(IF(P65="","",IF(P65>=40,100,IF(P65>=30,90,IF(P65>=20,75,IF(P65>=15,60,IF(P65>=10,45,IF(P65>=5,30,15))))))),""),IFERROR(IF(Q65="","",IF(Q65>=40,100,IF(Q65>=30,90,IF(Q65>=20,75,IF(Q65>=10,60,IF(Q65>=5,45,IF(Q65>=0,30,15))))))),""),IFERROR(IF(R65="","",IF(R65>=40,100,IF(R65>=30,90,IF(R65>=20,75,IF(R65>=10,60,IF(R65>=0,45,IF(R65>=-10,30,15))))))),"")),"") | T65: 3 | U65: 3 | V65: 3 | W65: 4 | X65: 3 | Y65: =IFERROR((AVERAGE(T65,U65,V65,W65,X65)-1)*25,"") | Z65: 3 | AA65: 5 | AB65: 3 | AC65: 39.2 | AD65: =IFERROR(AVERAGE(IFERROR(IF(Z65="","",Z65*20),""),IFERROR(IF(AA65="","",AA65*20),""),IFERROR(IF(AB65="","",AB65*20),""),IFERROR(IF(AC65="","",IF(AC65>=85,100,IF(AC65>=70,90,IF(AC65>=55,75,IF(AC65>=40,60,IF(AC65>=25,40,20)))))),"")),"") | AE65: 4 | AF65: 4 | AG65: 5 | AH65: 4 | AI65: =IFERROR((AVERAGE(AE65,AF65,AG65,AH65,AL65)-1)*25,"") | AJ65: =IFERROR(J65*Weights!$B$4 + O65*Weights!$B$5 + S65*Weights!$B$6 + Y65*Weights!$B$7 + AD65*Weights!$B$8 + AI65*Weights!$B$9,"") | AK65: =IF(AJ65="","",IF(AJ65>=85,"✓✓✓",IF(AJ65>=70,"✓✓",IF(AJ65>=55,"✓",IF(AJ65>=40,"?","✗"))))) | AL65: 5
A66: UCTT | B66: Ultra Clean Holdings, Inc. | C66: 04 Semiconductor Equipment & Materials / Materials & consumables | D66: 2026-10-11 | E66: 10.9844 | F66: 27.541 | G66: -3.68 | H66: 1.4006817 | I66: =IF(OR(E66="",R66="",R66<=0,E66<0),"",E66/R66) | J66: 50.6 | K66: 2.72 | L66: 15.83 | M66: -5.15 | N66: 3.74 | O66: 20.9 | P66: -4.72 | Q66: 24.3 | S66: =IFERROR(AVERAGE(IFERROR(IF(P66="","",IF(P66>=40,100,IF(P66>=30,90,IF(P66>=20,75,IF(P66>=15,60,IF(P66>=10,45,IF(P66>=5,30,15))))))),""),IFERROR(IF(Q66="","",IF(Q66>=40,100,IF(Q66>=30,90,IF(Q66>=20,75,IF(Q66>=10,60,IF(Q66>=5,45,IF(Q66>=0,30,15))))))),""),IFERROR(IF(R66="","",IF(R66>=40,100,IF(R66>=30,90,IF(R66>=20,75,IF(R66>=10,60,IF(R66>=0,45,IF(R66>=-10,30,15))))))),"")),"") | T66: 4 | U66: 3 | V66: 3 | W66: 4 | X66: 4 | Y66: =IFERROR((AVERAGE(T66,U66,V66,W66,X66)-1)*25,"") | Z66: 4 | AA66: 5 | AB66: 3 | AC66: 53.3 | AD66: =IFERROR(AVERAGE(IFERROR(IF(Z66="","",Z66*20),""),IFERROR(IF(AA66="","",AA66*20),""),IFERROR(IF(AB66="","",AB66*20),""),IFERROR(IF(AC66="","",IF(AC66>=85,100,IF(AC66>=70,90,IF(AC66>=55,75,IF(AC66>=40,60,IF(AC66>=25,40,20)))))),"")),"") | AE66: 4 | AF66: 4 | AG66: 4 | AH66: 4 | AI66: =IFERROR((AVERAGE(AE66,AF66,AG66,AH66,AL66)-1)*25,"") | AJ66: =IFERROR(J66*Weights!$B$4 + O66*Weights!$B$5 + S66*Weights!$B$6 + Y66*Weights!$B$7 + AD66*Weights!$B$8 + AI66*Weights!$B$9,"") | AK66: =IF(AJ66="","",IF(AJ66>=85,"✓✓✓",IF(AJ66>=70,"✓✓",IF(AJ66>=55,"✓",IF(AJ66>=40,"?","✗"))))) | AL66: 5
A67: CDNS | B67: Cadence Design Systems, Inc. | C67: 04 Semiconductor Equipment & Materials / EDA & IP | D67: 2026-10-11 | E67: 36.878246 | F67: 46.009 | G67: 1.72 | H67: 16.670984 | I67: =IF(OR(E67="",R67="",R67<=0,E67<0),"",E67/R67) | J67: 37 | K67: 13.29 | L67: 85.87 | M67: 28.64 | N67: 0.52 | O67: 83.3 | P67: 14.14 | Q67: 24.2 | R67: 129.3 | S67: =IFERROR(AVERAGE(IFERROR(IF(P67="","",IF(P67>=40,100,IF(P67>=30,90,IF(P67>=20,75,IF(P67>=15,60,IF(P67>=10,45,IF(P67>=5,30,15))))))),""),IFERROR(IF(Q67="","",IF(Q67>=40,100,IF(Q67>=30,90,IF(Q67>=20,75,IF(Q67>=10,60,IF(Q67>=5,45,IF(Q67>=0,30,15))))))),""),IFERROR(IF(R67="","",IF(R67>=40,100,IF(R67>=30,90,IF(R67>=20,75,IF(R67>=10,60,IF(R67>=0,45,IF(R67>=-10,30,15))))))),"")),"") | T67: 4 | U67: 4 | V67: 5 | W67: 4 | X67: 4 | Y67: =IFERROR((AVERAGE(T67,U67,V67,W67,X67)-1)*25,"") | Z67: 3 | AA67: 1 | AB67: 3 | AC67: 58.3 | AD67: =IFERROR(AVERAGE(IFERROR(IF(Z67="","",Z67*20),""),IFERROR(IF(AA67="","",AA67*20),""),IFERROR(IF(AB67="","",AB67*20),""),IFERROR(IF(AC67="","",IF(AC67>=85,100,IF(AC67>=70,90,IF(AC67>=55,75,IF(AC67>=40,60,IF(AC67>=25,40,20)))))),"")),"") | AE67: 5 | AF67: 4 | AG67: 4 | AH67: 4 | AI67: =IFERROR((AVERAGE(AE67,AF67,AG67,AH67,AL67)-1)*25,"") | AJ67: =IFERROR(J67*Weights!$B$4 + O67*Weights!$B$5 + S67*Weights!$B$6 + Y67*Weights!$B$7 + AD67*Weights!$B$8 + AI67*Weights!$B$9,"") | AK67: =IF(AJ67="","",IF(AJ67>=85,"✓✓✓",IF(AJ67>=70,"✓✓",IF(AJ67>=55,"✓",IF(AJ67>=40,"?","✗"))))) | AL67: 5
A68: SNPS | B68: Synopsys, Inc. | C68: 04 Semiconductor Equipment & Materials / EDA & IP | D68: 2026-10-11 | E68: 27.443886 | F68: 49.898 | G68: 2.81 | H68: 10.378923 | I68: =IF(OR(E68="",R68="",R68<=0,E68<0),"",E68/R68) | J68: 56.2 | K68: 2.01 | L68: 82.92 | M68: 29.18 | N68: 3.49 | O68: 55.3 | P68: 15.19 | Q68: 42.4 | R68: 125.1 | S68: =IFERROR(AVERAGE(IFERROR(IF(P68="","",IF(P68>=40,100,IF(P68>=30,90,IF(P68>=20,75,IF(P68>=15,60,IF(P68>=10,45,IF(P68>=5,30,15))))))),""),IFERROR(IF(Q68="","",IF(Q68>=40,100,IF(Q68>=30,90,IF(Q68>=20,75,IF(Q68>=10,60,IF(Q68>=5,45,IF(Q68>=0,30,15))))))),""),IFERROR(IF(R68="","",IF(R68>=40,100,IF(R68>=30,90,IF(R68>=20,75,IF(R68>=10,60,IF(R68>=0,45,IF(R68>=-10,30,15))))))),"")),"") | T68: 4 | U68: 4 | V68: 5 | W68: 5 | X68: 4 | Y68: =IFERROR((AVERAGE(T68,U68,V68,W68,X68)-1)*25,"") | Z68: 4 | AA68: 1 | AB68: 3 | AC68: 44.2 | AD68: =IFERROR(AVERAGE(IFERROR(IF(Z68="","",Z68*20),""),IFERROR(IF(AA68="","",AA68*20),""),IFERROR(IF(AB68="","",AB68*20),""),IFERROR(IF(AC68="","",IF(AC68>=85,100,IF(AC68>=70,90,IF(AC68>=55,75,IF(AC68>=40,60,IF(AC68>=25,40,20)))))),"")),"") | AE68: 5 | AF68: 4 | AG68: 4 | AH68: 4 | AI68: =IFERROR((AVERAGE(AE68,AF68,AG68,AH68,AL68)-1)*25,"") | AJ68: =IFERROR(J68*Weights!$B$4 + O68*Weights!$B$5 + S68*Weights!$B$6 + Y68*Weights!$B$7 + AD68*Weights!$B$8 + AI68*Weights!$B$9,"") | AK68: =IF(AJ68="","",IF(AJ68>=85,"✓✓✓",IF(AJ68>=70,"✓✓",IF(AJ68>=55,"✓",IF(AJ68>=40,"?","✗"))))) | AL68: 5
A69: ARM | B69: Arm Holdings plc | C69: 04 Semiconductor Equipment & Materials / EDA & IP | D69: 2026-10-11 | E69: 93.203611 | F69: 292.361 | G69: 0.52 | H69: 55.156452 | I69: =IF(OR(E69="",R69="",R69<=0,E69<0),"",E69/R69) | J69: 18 | K69: 7.38 | L69: 97.54 | M69: 28.55 | N69: -3.2 | O69: 74.6 | P69: 22.46 | Q69: 22.4 | R69: 107.7 | S69: =IFERROR(AVERAGE(IFERROR(IF(P69="","",IF(P69>=40,100,IF(P69>=30,90,IF(P69>=20,75,IF(P69>=15,60,IF(P69>=10,45,IF(P69>=5,30,15))))))),""),IFERROR(IF(Q69="","",IF(Q69>=40,100,IF(Q69>=30,90,IF(Q69>=20,75,IF(Q69>=10,60,IF(Q69>=5,45,IF(Q69>=0,30,15))))))),""),IFERROR(IF(R69="","",IF(R69>=40,100,IF(R69>=30,90,IF(R69>=20,75,IF(R69>=10,60,IF(R69>=0,45,IF(R69>=-10,30,15))))))),"")),"") | T69: 4 | U69: 5 | V69: 5 | W69: 4 | X69: 4 | Y69: =IFERROR((AVERAGE(T69,U69,V69,W69,X69)-1)*25,"") | Z69: 4 | AA69: 2 | AB69: 3 | AC69: 58.3 | AD69: =IFERROR(AVERAGE(IFERROR(IF(Z69="","",Z69*20),""),IFERROR(IF(AA69="","",AA69*20),""),IFERROR(IF(AB69="","",AB69*20),""),IFERROR(IF(AC69="","",IF(AC69>=85,100,IF(AC69>=70,90,IF(AC69>=55,75,IF(AC69>=40,60,IF(AC69>=25,40,20)))))),"")),"") | AE69: 5 | AF69: 4 | AG69: 5 | AH69: 3 | AI69: =IFERROR((AVERAGE(AE69,AF69,AG69,AH69,AL69)-1)*25,"") | AJ69: =IFERROR(J69*Weights!$B$4 + O69*Weights!$B$5 + S69*Weights!$B$6 + Y69*Weights!$B$7 + AD69*Weights!$B$8 + AI69*Weights!$B$9,"") | AK69: =IF(AJ69="","",IF(AJ69>=85,"✓✓✓",IF(AJ69>=70,"✓✓",IF(AJ69>=55,"✓",IF(AJ69>=40,"?","✗"))))) | AL69: 5
A70: TSM | B70: Taiwan Semiconductor Manufacturing Company Limited | C70: 05 Fabs & Foundries | D70: 2026-10-11 | E70: 20.67539 | F70: 20.117 | G70: 1.7 | H70: 14.891939 | I70: =IF(OR(E70="",R70="",R70<=0,E70<0),"",E70/R70) | J70: 60.6 | K70: 27.53 | L70: 64.23 | M70: 25.33 | N70: -0.77 | O70: 96.9 | P70: 18.94 | Q70: 36 | R70: 77.4 | S70: =IFERROR(AVERAGE(IFERROR(IF(P70="","",IF(P70>=40,100,IF(P70>=30,90,IF(P70>=20,75,IF(P70>=15,60,IF(P70>=10,45,IF(P70>=5,30,15))))))),""),IFERROR(IF(Q70="","",IF(Q70>=40,100,IF(Q70>=30,90,IF(Q70>=20,75,IF(Q70>=10,60,IF(Q70>=5,45,IF(Q70>=0,30,15))))))),""),IFERROR(IF(R70="","",IF(R70>=40,100,IF(R70>=30,90,IF(R70>=20,75,IF(R70>=10,60,IF(R70>=0,45,IF(R70>=-10,30,15))))))),"")),"") | T70: 5 | U70: 5 | V70: 5 | W70: 5 | X70: 5 | Y70: =IFERROR((AVERAGE(T70,U70,V70,W70,X70)-1)*25,"") | Z70: 5 | AA70: 2 | AB70: 5 | AC70: 70 | AD70: =IFERROR(AVERAGE(IFERROR(IF(Z70="","",Z70*20),""),IFERROR(IF(AA70="","",AA70*20),""),IFERROR(IF(AB70="","",AB70*20),""),IFERROR(IF(AC70="","",IF(AC70>=85,100,IF(AC70>=70,90,IF(AC70>=55,75,IF(AC70>=40,60,IF(AC70>=25,40,20)))))),"")),"") | AE70: 3 | AF70: 2 | AG70: 5 | AH70: 4 | AI70: =IFERROR((AVERAGE(AE70,AF70,AG70,AH70,AL70)-1)*25,"") | AJ70: =IFERROR(J70*Weights!$B$4 + O70*Weights!$B$5 + S70*Weights!$B$6 + Y70*Weights!$B$7 + AD70*Weights!$B$8 + AI70*Weights!$B$9,"") | AK70: =IF(AJ70="","",IF(AJ70>=85,"✓✓✓",IF(AJ70>=70,"✓✓",IF(AJ70>=55,"✓",IF(AJ70>=40,"?","✗"))))) | AL70: 5
A71: INTC | B71: Intel Corporation | C71: 05 Fabs & Foundries | D71: 2026-10-11 | E71: 50.272007 | F71: 36.044 | G71: 0.51 | H71: 9.704292 | I71: =IF(OR(E71="",R71="",R71<=0,E71<0),"",E71/R71) | J71: 27.8 | K71: 2.04 | L71: 38.87 | M71: 4.96 | N71: 1.24 | O71: 61.2 | P71: -5.71 | Q71: 25.4 | S71: =IFERROR(AVERAGE(IFERROR(IF(P71="","",IF(P71>=40,100,IF(P71>=30,90,IF(P71>=20,75,IF(P71>=15,60,IF(P71>=10,45,IF(P71>=5,30,15))))))),""),IFERROR(IF(Q71="","",IF(Q71>=40,100,IF(Q71>=30,90,IF(Q71>=20,75,IF(Q71>=10,60,IF(Q71>=5,45,IF(Q71>=0,30,15))))))),""),IFERROR(IF(R71="","",IF(R71>=40,100,IF(R71>=30,90,IF(R71>=20,75,IF(R71>=10,60,IF(R71>=0,45,IF(R71>=-10,30,15))))))),"")),"") | T71: 3 | U71: 3 | V71: 3 | W71: 4 | X71: 4 | Y71: =IFERROR((AVERAGE(T71,U71,V71,W71,X71)-1)*25,"") | Z71: 5 | AA71: 5 | AB71: 3 | AC71: 61.7 | AD71: =IFERROR(AVERAGE(IFERROR(IF(Z71="","",Z71*20),""),IFERROR(IF(AA71="","",AA71*20),""),IFERROR(IF(AB71="","",AB71*20),""),IFERROR(IF(AC71="","",IF(AC71>=85,100,IF(AC71>=70,90,IF(AC71>=55,75,IF(AC71>=40,60,IF(AC71>=25,40,20)))))),"")),"") | AE71: 5 | AF71: 3 | AG71: 2 | AH71: 3 | AI71: =IFERROR((AVERAGE(AE71,AF71,AG71,AH71,AL71)-1)*25,"") | AJ71: =IFERROR(J71*Weights!$B$4 + O71*Weights!$B$5 + S71*Weights!$B$6 + Y71*Weights!$B$7 + AD71*Weights!$B$8 + AI71*Weights!$B$9,"") | AK71: =IF(AJ71="","",IF(AJ71>=85,"✓✓✓",IF(AJ71>=70,"✓✓",IF(AJ71>=55,"✓",IF(AJ71>=40,"?","✗"))))) | AL71: 5
A72: GFS | B72: GLOBALFOUNDRIES Inc. | C72: 05 Fabs & Foundries | D72: 2026-10-11 | E72: 18.329521 | F72: 13.001 | G72: 2.96 | H72: 3.8757389 | I72: =IF(OR(E72="",R72="",R72<=0,E72<0),"",E72/R72) | J72: 71.2 | K72: 4.5 | L72: 27.14 | M72: 11.47 | N72: -0.34 | O72: 57.5 | P72: -5.74 | Q72: 5.8 | R72: -27.2 | S72: =IFERROR(AVERAGE(IFERROR(IF(P72="","",IF(P72>=40,100,IF(P72>=30,90,IF(P72>=20,75,IF(P72>=15,60,IF(P72>=10,45,IF(P72>=5,30,15))))))),""),IFERROR(IF(Q72="","",IF(Q72>=40,100,IF(Q72>=30,90,IF(Q72>=20,75,IF(Q72>=10,60,IF(Q72>=5,45,IF(Q72>=0,30,15))))))),""),IFERROR(IF(R72="","",IF(R72>=40,100,IF(R72>=30,90,IF(R72>=20,75,IF(R72>=10,60,IF(R72>=0,45,IF(R72>=-10,30,15))))))),"")),"") | T72: 3 | U72: 3 | V72: 4 | W72: 4 | X72: 3 | Y72: =IFERROR((AVERAGE(T72,U72,V72,W72,X72)-1)*25,"") | Z72: 4 | AA72: 5 | AB72: 3 | AC72: 48.3 | AD72: =IFERROR(AVERAGE(IFERROR(IF(Z72="","",Z72*20),""),IFERROR(IF(AA72="","",AA72*20),""),IFERROR(IF(AB72="","",AB72*20),""),IFERROR(IF(AC72="","",IF(AC72>=85,100,IF(AC72>=70,90,IF(AC72>=55,75,IF(AC72>=40,60,IF(AC72>=25,40,20)))))),"")),"") | AE72: 4 | AF72: 4 | AG72: 4 | AH72: 4 | AI72: =IFERROR((AVERAGE(AE72,AF72,AG72,AH72,AL72)-1)*25,"") | AJ72: =IFERROR(J72*Weights!$B$4 + O72*Weights!$B$5 + S72*Weights!$B$6 + Y72*Weights!$B$7 + AD72*Weights!$B$8 + AI72*Weights!$B$9,"") | AK72: =IF(AJ72="","",IF(AJ72>=85,"✓✓✓",IF(AJ72>=70,"✓✓",IF(AJ72>=55,"✓",IF(AJ72>=40,"?","✗"))))) | AL72: 5
A73: TSEM | B73: Tower Semiconductor Ltd. | C73: 05 Fabs & Foundries | D73: 2026-10-11 | E73: 34.080784 | F73: 44.732 | G73: 1.16 | H73: 15.121451 | I73: =IF(OR(E73="",R73="",R73<=0,E73<0),"",E73/R73) | J73: 33.5 | K73: 7.41 | L73: 26.87 | M73: 17.58 | N73: -2.24 | O73: 61.2 | P73: -2.27 | Q73: 23.7 | R73: 95 | S73: =IFERROR(AVERAGE(IFERROR(IF(P73="","",IF(P73>=40,100,IF(P73>=30,90,IF(P73>=20,75,IF(P73>=15,60,IF(P73>=10,45,IF(P73>=5,30,15))))))),""),IFERROR(IF(Q73="","",IF(Q73>=40,100,IF(Q73>=30,90,IF(Q73>=20,75,IF(Q73>=10,60,IF(Q73>=5,45,IF(Q73>=0,30,15))))))),""),IFERROR(IF(R73="","",IF(R73>=40,100,IF(R73>=30,90,IF(R73>=20,75,IF(R73>=10,60,IF(R73>=0,45,IF(R73>=-10,30,15))))))),"")),"") | T73: 4 | U73: 4 | V73: 4 | W73: 5 | X73: 4 | Y73: =IFERROR((AVERAGE(T73,U73,V73,W73,X73)-1)*25,"") | Z73: 4 | AA73: 5 | AB73: 3 | AC73: 59.2 | AD73: =IFERROR(AVERAGE(IFERROR(IF(Z73="","",Z73*20),""),IFERROR(IF(AA73="","",AA73*20),""),IFERROR(IF(AB73="","",AB73*20),""),IFERROR(IF(AC73="","",IF(AC73>=85,100,IF(AC73>=70,90,IF(AC73>=55,75,IF(AC73>=40,60,IF(AC73>=25,40,20)))))),"")),"") | AE73: 4 | AF73: 4 | AG73: 4 | AH73: 4 | AI73: =IFERROR((AVERAGE(AE73,AF73,AG73,AH73,AL73)-1)*25,"") | AJ73: =IFERROR(J73*Weights!$B$4 + O73*Weights!$B$5 + S73*Weights!$B$6 + Y73*Weights!$B$7 + AD73*Weights!$B$8 + AI73*Weights!$B$9,"") | AK73: =IF(AJ73="","",IF(AJ73>=85,"✓✓✓",IF(AJ73>=70,"✓✓",IF(AJ73>=55,"✓",IF(AJ73>=40,"?","✗"))))) | AL73: 5
A74: UMC | B74: United Microelectronics Corporation | C74: 05 Fabs & Foundries | D74: 2026-10-11 | E74: 26.145576 | F74: 16.126 | G74: 3.2 | H74: 7.3774624 | I74: =IF(OR(E74="",R74="",R74<=0,E74<0),"",E74/R74) | J74: 63.1 | K74: 8.17 | L74: 30.6 | M74: 23.64 | N74: -0.76 | O74: 73.8 | P74: -5.19 | Q74: 17 | S74: =IFERROR(AVERAGE(IFERROR(IF(P74="","",IF(P74>=40,100,IF(P74>=30,90,IF(P74>=20,75,IF(P74>=15,60,IF(P74>=10,45,IF(P74>=5,30,15))))))),""),IFERROR(IF(Q74="","",IF(Q74>=40,100,IF(Q74>=30,90,IF(Q74>=20,75,IF(Q74>=10,60,IF(Q74>=5,45,IF(Q74>=0,30,15))))))),""),IFERROR(IF(R74="","",IF(R74>=40,100,IF(R74>=30,90,IF(R74>=20,75,IF(R74>=10,60,IF(R74>=0,45,IF(R74>=-10,30,15))))))),"")),"") | T74: 3 | U74: 3 | V74: 3 | W74: 3 | X74: 2 | Y74: =IFERROR((AVERAGE(T74,U74,V74,W74,X74)-1)*25,"") | Z74: 3 | AA74: 5 | AB74: 3 | AC74: 70 | AD74: =IFERROR(AVERAGE(IFERROR(IF(Z74="","",Z74*20),""),IFERROR(IF(AA74="","",AA74*20),""),IFERROR(IF(AB74="","",AB74*20),""),IFERROR(IF(AC74="","",IF(AC74>=85,100,IF(AC74>=70,90,IF(AC74>=55,75,IF(AC74>=40,60,IF(AC74>=25,40,20)))))),"")),"") | AE74: 4 | AF74: 2 | AG74: 4 | AH74: 4 | AI74: =IFERROR((AVERAGE(AE74,AF74,AG74,AH74,AL74)-1)*25,"") | AJ74: =IFERROR(J74*Weights!$B$4 + O74*Weights!$B$5 + S74*Weights!$B$6 + Y74*Weights!$B$7 + AD74*Weights!$B$8 + AI74*Weights!$B$9,"") | AK74: =IF(AJ74="","",IF(AJ74>=85,"✓✓✓",IF(AJ74>=70,"✓✓",IF(AJ74>=55,"✓",IF(AJ74>=40,"?","✗"))))) | AL74: 5
A75: AVGO | B75: Broadcom Inc. | C75: 06 AI Compute Silicon / Custom silicon / ASIC designers | D75: 2026-10-11 | E75: 18.642021 | F75: 35.07 | G75: 2.28 | H75: 19.369032 | I75: =IF(OR(E75="",R75="",R75<=0,E75<0),"",E75/R75) | J75: 57 | K75: 24.44 | L75: 75.52 | M75: 44.22 | N75: 0.68 | O75: 88.8 | P75: 24.38 | Q75: 85.5 | R75: 216.1 | S75: =IFERROR(AVERAGE(IFERROR(IF(P75="","",IF(P75>=40,100,IF(P75>=30,90,IF(P75>=20,75,IF(P75>=15,60,IF(P75>=10,45,IF(P75>=5,30,15))))))),""),IFERROR(IF(Q75="","",IF(Q75>=40,100,IF(Q75>=30,90,IF(Q75>=20,75,IF(Q75>=10,60,IF(Q75>=5,45,IF(Q75>=0,30,15))))))),""),IFERROR(IF(R75="","",IF(R75>=40,100,IF(R75>=30,90,IF(R75>=20,75,IF(R75>=10,60,IF(R75>=0,45,IF(R75>=-10,30,15))))))),"")),"") | T75: 5 | U75: 5 | V75: 4 | W75: 5 | X75: 5 | Y75: =IFERROR((AVERAGE(T75,U75,V75,W75,X75)-1)*25,"") | Z75: 4 | AA75: 1 | AB75: 4 | AC75: 36.7 | AD75: =IFERROR(AVERAGE(IFERROR(IF(Z75="","",Z75*20),""),IFERROR(IF(AA75="","",AA75*20),""),IFERROR(IF(AB75="","",AB75*20),""),IFERROR(IF(AC75="","",IF(AC75>=85,100,IF(AC75>=70,90,IF(AC75>=55,75,IF(AC75>=40,60,IF(AC75>=25,40,20)))))),"")),"") | AE75: 3 | AF75: 4 | AG75: 4 | AH75: 4 | AI75: =IFERROR((AVERAGE(AE75,AF75,AG75,AH75,AL75)-1)*25,"") | AJ75: =IFERROR(J75*Weights!$B$4 + O75*Weights!$B$5 + S75*Weights!$B$6 + Y75*Weights!$B$7 + AD75*Weights!$B$8 + AI75*Weights!$B$9,"") | AK75: =IF(AJ75="","",IF(AJ75>=85,"✓✓✓",IF(AJ75>=70,"✓✓",IF(AJ75>=55,"✓",IF(AJ75>=40,"?","✗"))))) | AL75: 5
A76: MRVL | B76: Marvell Technology, Inc. | C76: 06 AI Compute Silicon / Custom silicon / ASIC designers | D76: 2026-10-11 | E76: 39.198901 | F76: 88.057 | G76: 0.7 | H76: 26.178577 | I76: =IF(OR(E76="",R76="",R76<=0,E76<0),"",E76/R76) | J76: 23.5 | K76: 5.47 | L76: 52.22 | M76: 18.23 | N76: 0.47 | O76: 45.1 | P76: 11.45 | Q76: 36.5 | R76: 58.1 | S76: =IFERROR(AVERAGE(IFERROR(IF(P76="","",IF(P76>=40,100,IF(P76>=30,90,IF(P76>=20,75,IF(P76>=15,60,IF(P76>=10,45,IF(P76>=5,30,15))))))),""),IFERROR(IF(Q76="","",IF(Q76>=40,100,IF(Q76>=30,90,IF(Q76>=20,75,IF(Q76>=10,60,IF(Q76>=5,45,IF(Q76>=0,30,15))))))),""),IFERROR(IF(R76="","",IF(R76>=40,100,IF(R76>=30,90,IF(R76>=20,75,IF(R76>=10,60,IF(R76>=0,45,IF(R76>=-10,30,15))))))),"")),"") | T76: 4 | U76: 4 | V76: 4 | W76: 5 | X76: 5 | Y76: =IFERROR((AVERAGE(T76,U76,V76,W76,X76)-1)*25,"") | Z76: 4 | AA76: 5 | AB76: 5 | AC76: 72.5 | AD76: =IFERROR(AVERAGE(IFERROR(IF(Z76="","",Z76*20),""),IFERROR(IF(AA76="","",AA76*20),""),IFERROR(IF(AB76="","",AB76*20),""),IFERROR(IF(AC76="","",IF(AC76>=85,100,IF(AC76>=70,90,IF(AC76>=55,75,IF(AC76>=40,60,IF(AC76>=25,40,20)))))),"")),"") | AE76: 3 | AF76: 4 | AG76: 4 | AH76: 4 | AI76: =IFERROR((AVERAGE(AE76,AF76,AG76,AH76,AL76)-1)*25,"") | AJ76: =IFERROR(J76*Weights!$B$4 + O76*Weights!$B$5 + S76*Weights!$B$6 + Y76*Weights!$B$7 + AD76*Weights!$B$8 + AI76*Weights!$B$9,"") | AK76: =IF(AJ76="","",IF(AJ76>=85,"✓✓✓",IF(AJ76>=70,"✓✓",IF(AJ76>=55,"✓",IF(AJ76>=40,"?","✗"))))) | AL76: 5
A77: ALAB | B77: Astera Labs, Inc. | C77: 06 AI Compute Silicon / Custom silicon / ASIC designers | D77: 2026-10-11 | E77: 53.52484 | F77: 228.126 | G77: 0.47 | H77: 49.394627 | I77: =IF(OR(E77="",R77="",R77<=0,E77<0),"",E77/R77) | J77: 32.6 | K77: 15.47 | L77: 75.13 | M77: 23.02 | N77: -4.23 | O77: 78.6 | P77: 120.18 | Q77: 104.5 | R77: 198.9 | S77: =IFERROR(AVERAGE(IFERROR(IF(P77="","",IF(P77>=40,100,IF(P77>=30,90,IF(P77>=20,75,IF(P77>=15,60,IF(P77>=10,45,IF(P77>=5,30,15))))))),""),IFERROR(IF(Q77="","",IF(Q77>=40,100,IF(Q77>=30,90,IF(Q77>=20,75,IF(Q77>=10,60,IF(Q77>=5,45,IF(Q77>=0,30,15))))))),""),IFERROR(IF(R77="","",IF(R77>=40,100,IF(R77>=30,90,IF(R77>=20,75,IF(R77>=10,60,IF(R77>=0,45,IF(R77>=-10,30,15))))))),"")),"") | T77: 5 | U77: 4 | V77: 5 | W77: 5 | X77: 5 | Y77: =IFERROR((AVERAGE(T77,U77,V77,W77,X77)-1)*25,"") | Z77: 5 | AA77: 5 | AB77: 2 | AC77: 62.5 | AD77: =IFERROR(AVERAGE(IFERROR(IF(Z77="","",Z77*20),""),IFERROR(IF(AA77="","",AA77*20),""),IFERROR(IF(AB77="","",AB77*20),""),IFERROR(IF(AC77="","",IF(AC77>=85,100,IF(AC77>=70,90,IF(AC77>=55,75,IF(AC77>=40,60,IF(AC77>=25,40,20)))))),"")),"") | AE77: 2 | AF77: 5 | AG77: 5 | AH77: 4 | AI77: =IFERROR((AVERAGE(AE77,AF77,AG77,AH77,AL77)-1)*25,"") | AJ77: =IFERROR(J77*Weights!$B$4 + O77*Weights!$B$5 + S77*Weights!$B$6 + Y77*Weights!$B$7 + AD77*Weights!$B$8 + AI77*Weights!$B$9,"") | AK77: =IF(AJ77="","",IF(AJ77>=85,"✓✓✓",IF(AJ77>=70,"✓✓",IF(AJ77>=55,"✓",IF(AJ77>=40,"?","✗"))))) | AL77: 5
A78: SNDK | B78: Sandisk Corporation | C78: 06 AI Compute Silicon / Memory (HBM is the bottleneck) | D78: 2026-10-11 | E78: 6.5756685 | F78: 19.279 | G78: 5.03 | H78: 11.290823 | I78: =IF(OR(E78="",R78="",R78<=0,E78<0),"",E78/R78) | J78: 76.6 | K78: 64.7 | L78: 71.47 | M78: 56.77 | N78: -0.36 | O78: 80.1 | P78: 49.29 | Q78: 371.6 | R78: 272.8 | S78: =IFERROR(AVERAGE(IFERROR(IF(P78="","",IF(P78>=40,100,IF(P78>=30,90,IF(P78>=20,75,IF(P78>=15,60,IF(P78>=10,45,IF(P78>=5,30,15))))))),""),IFERROR(IF(Q78="","",IF(Q78>=40,100,IF(Q78>=30,90,IF(Q78>=20,75,IF(Q78>=10,60,IF(Q78>=5,45,IF(Q78>=0,30,15))))))),""),IFERROR(IF(R78="","",IF(R78>=40,100,IF(R78>=30,90,IF(R78>=20,75,IF(R78>=10,60,IF(R78>=0,45,IF(R78>=-10,30,15))))))),"")),"") | T78: 3 | U78: 3 | V78: 3 | W78: 4 | X78: 3 | Y78: =IFERROR((AVERAGE(T78,U78,V78,W78,X78)-1)*25,"") | Z78: 5 | AA78: 5 | AB78: 3 | AC78: 67.5 | AD78: =IFERROR(AVERAGE(IFERROR(IF(Z78="","",Z78*20),""),IFERROR(IF(AA78="","",AA78*20),""),IFERROR(IF(AB78="","",AB78*20),""),IFERROR(IF(AC78="","",IF(AC78>=85,100,IF(AC78>=70,90,IF(AC78>=55,75,IF(AC78>=40,60,IF(AC78>=25,40,20)))))),"")),"") | AE78: 4 | AF78: 4 | AG78: 5 | AH78: 4 | AI78: =IFERROR((AVERAGE(AE78,AF78,AG78,AH78,AL78)-1)*25,"") | AJ78: =IFERROR(J78*Weights!$B$4 + O78*Weights!$B$5 + S78*Weights!$B$6 + Y78*Weights!$B$7 + AD78*Weights!$B$8 + AI78*Weights!$B$9,"") | AK78: =IF(AJ78="","",IF(AJ78>=85,"✓✓✓",IF(AJ78>=70,"✓✓",IF(AJ78>=55,"✓",IF(AJ78>=40,"?","✗"))))) | AL78: 5
A79: COHR | B79: Coherent Corp. | C79: 07 Optical, Networking & Interconnect / Optical components & transceivers | D79: 2026-10-11 | E79: 26.601445 | F79: 47.361 | G79: -1.67 | H79: 8.648926 | I79: =IF(OR(E79="",R79="",R79<=0,E79<0),"",E79/R79) | J79: 37.7 | K79: 5.42 | L79: 37.5 | M79: -14.48 | N79: 1.1 | O79: 42.3 | P79: 11.32 | Q79: 33.7 | S79: =IFERROR(AVERAGE(IFERROR(IF(P79="","",IF(P79>=40,100,IF(P79>=30,90,IF(P79>=20,75,IF(P79>=15,60,IF(P79>=10,45,IF(P79>=5,30,15))))))),""),IFERROR(IF(Q79="","",IF(Q79>=40,100,IF(Q79>=30,90,IF(Q79>=20,75,IF(Q79>=10,60,IF(Q79>=5,45,IF(Q79>=0,30,15))))))),""),IFERROR(IF(R79="","",IF(R79>=40,100,IF(R79>=30,90,IF(R79>=20,75,IF(R79>=10,60,IF(R79>=0,45,IF(R79>=-10,30,15))))))),"")),"") | T79: 4 | U79: 4 | V79: 4 | W79: 5 | X79: 4 | Y79: =IFERROR((AVERAGE(T79,U79,V79,W79,X79)-1)*25,"") | Z79: 4 | AA79: 5 | AB79: 3 | AC79: 52.5 | AD79: =IFERROR(AVERAGE(IFERROR(IF(Z79="","",Z79*20),""),IFERROR(IF(AA79="","",AA79*20),""),IFERROR(IF(AB79="","",AB79*20),""),IFERROR(IF(AC79="","",IF(AC79>=85,100,IF(AC79>=70,90,IF(AC79>=55,75,IF(AC79>=40,60,IF(AC79>=25,40,20)))))),"")),"") | AE79: 4 | AF79: 4 | AG79: 3 | AH79: 4 | AI79: =IFERROR((AVERAGE(AE79,AF79,AG79,AH79,AL79)-1)*25,"") | AJ79: =IFERROR(J79*Weights!$B$4 + O79*Weights!$B$5 + S79*Weights!$B$6 + Y79*Weights!$B$7 + AD79*Weights!$B$8 + AI79*Weights!$B$9,"") | AK79: =IF(AJ79="","",IF(AJ79>=85,"✓✓✓",IF(AJ79>=70,"✓✓",IF(AJ79>=55,"✓",IF(AJ79>=40,"?","✗"))))) | AL79: 5
A80: LITE | B80: Lumentum Holdings Inc. | C80: 07 Optical, Networking & Interconnect / Optical components & transceivers | D80: 2026-10-11 | E80: 38.212578 | F80: 123.137 | G80: 0.3 | H80: 33.160267 | I80: =IF(OR(E80="",R80="",R80<=0,E80<0),"",E80/R80) | J80: 21.5 | K80: 8.78 | L80: 44.24 | M80: 9.96 | N80: -1.33 | O80: 54.8 | P80: 19.48 | Q80: 109.3 | S80: =IFERROR(AVERAGE(IFERROR(IF(P80="","",IF(P80>=40,100,IF(P80>=30,90,IF(P80>=20,75,IF(P80>=15,60,IF(P80>=10,45,IF(P80>=5,30,15))))))),""),IFERROR(IF(Q80="","",IF(Q80>=40,100,IF(Q80>=30,90,IF(Q80>=20,75,IF(Q80>=10,60,IF(Q80>=5,45,IF(Q80>=0,30,15))))))),""),IFERROR(IF(R80="","",IF(R80>=40,100,IF(R80>=30,90,IF(R80>=20,75,IF(R80>=10,60,IF(R80>=0,45,IF(R80>=-10,30,15))))))),"")),"") | T80: 5 | U80: 5 | V80: 4 | W80: 5 | X80: 5 | Y80: =IFERROR((AVERAGE(T80,U80,V80,W80,X80)-1)*25,"") | Z80: 5 | AA80: 5 | AB80: 3 | AC80: 66.7 | AD80: =IFERROR(AVERAGE(IFERROR(IF(Z80="","",Z80*20),""),IFERROR(IF(AA80="","",AA80*20),""),IFERROR(IF(AB80="","",AB80*20),""),IFERROR(IF(AC80="","",IF(AC80>=85,100,IF(AC80>=70,90,IF(AC80>=55,75,IF(AC80>=40,60,IF(AC80>=25,40,20)))))),"")),"") | AE80: 4 | AF80: 4 | AG80: 4 | AH80: 4 | AI80: =IFERROR((AVERAGE(AE80,AF80,AG80,AH80,AL80)-1)*25,"") | AJ80: =IFERROR(J80*Weights!$B$4 + O80*Weights!$B$5 + S80*Weights!$B$6 + Y80*Weights!$B$7 + AD80*Weights!$B$8 + AI80*Weights!$B$9,"") | AK80: =IF(AJ80="","",IF(AJ80>=85,"✓✓✓",IF(AJ80>=70,"✓✓",IF(AJ80>=55,"✓",IF(AJ80>=40,"?","✗"))))) | AL80: 5
A81: FN | B81: Fabrinet | C81: 07 Optical, Networking & Interconnect / Optical components & transceivers | D81: 2026-10-11 | E81: 24.257507 | F81: 31.983 | G81: 0.02 | H81: 3.7546675 | I81: =IF(OR(E81="",R81="",R81<=0,E81<0),"",E81/R81) | J81: 56.5 | K81: 15.73 | L81: 11.99 | M81: 0.07 | N81: -1.64 | O81: 53.1 | P81: 20.61 | Q81: 44.6 | R81: 59.7 | S81: =IFERROR(AVERAGE(IFERROR(IF(P81="","",IF(P81>=40,100,IF(P81>=30,90,IF(P81>=20,75,IF(P81>=15,60,IF(P81>=10,45,IF(P81>=5,30,15))))))),""),IFERROR(IF(Q81="","",IF(Q81>=40,100,IF(Q81>=30,90,IF(Q81>=20,75,IF(Q81>=10,60,IF(Q81>=5,45,IF(Q81>=0,30,15))))))),""),IFERROR(IF(R81="","",IF(R81>=40,100,IF(R81>=30,90,IF(R81>=20,75,IF(R81>=10,60,IF(R81>=0,45,IF(R81>=-10,30,15))))))),"")),"") | T81: 4 | U81: 4 | V81: 4 | W81: 5 | X81: 5 | Y81: =IFERROR((AVERAGE(T81,U81,V81,W81,X81)-1)*25,"") | Z81: 4 | AA81: 1 | AB81: 3 | AC81: 35.8 | AD81: =IFERROR(AVERAGE(IFERROR(IF(Z81="","",Z81*20),""),IFERROR(IF(AA81="","",AA81*20),""),IFERROR(IF(AB81="","",AB81*20),""),IFERROR(IF(AC81="","",IF(AC81>=85,100,IF(AC81>=70,90,IF(AC81>=55,75,IF(AC81>=40,60,IF(AC81>=25,40,20)))))),"")),"") | AE81: 3 | AF81: 4 | AG81: 4 | AH81: 4 | AI81: =IFERROR((AVERAGE(AE81,AF81,AG81,AH81,AL81)-1)*25,"") | AJ81: =IFERROR(J81*Weights!$B$4 + O81*Weights!$B$5 + S81*Weights!$B$6 + Y81*Weights!$B$7 + AD81*Weights!$B$8 + AI81*Weights!$B$9,"") | AK81: =IF(AJ81="","",IF(AJ81>=85,"✓✓✓",IF(AJ81>=70,"✓✓",IF(AJ81>=55,"✓",IF(AJ81>=40,"?","✗"))))) | AL81: 5
A82: AAOI | B82: Applied Optoelectronics, Inc. | C82: 07 Optical, Networking & Interconnect / Optical components & transceivers | D82: 2026-10-11 | E82: 23.824423 | F82: -316.561 | G82: -6.46 | H82: 15.620125 | I82: =IF(OR(E82="",R82="",R82<=0,E82<0),"",E82/R82) | J82: 49.4 | K82: -2.66 | L82: 28.92 | M82: -100.9 | O82: 12.5 | P82: 26.93 | Q82: 86.4 | S82: =IFERROR(AVERAGE(IFERROR(IF(P82="","",IF(P82>=40,100,IF(P82>=30,90,IF(P82>=20,75,IF(P82>=15,60,IF(P82>=10,45,IF(P82>=5,30,15))))))),""),IFERROR(IF(Q82="","",IF(Q82>=40,100,IF(Q82>=30,90,IF(Q82>=20,75,IF(Q82>=10,60,IF(Q82>=5,45,IF(Q82>=0,30,15))))))),""),IFERROR(IF(R82="","",IF(R82>=40,100,IF(R82>=30,90,IF(R82>=20,75,IF(R82>=10,60,IF(R82>=0,45,IF(R82>=-10,30,15))))))),"")),"") | T82: 3 | U82: 3 | V82: 2 | W82: 4 | X82: 3 | Y82: =IFERROR((AVERAGE(T82,U82,V82,W82,X82)-1)*25,"") | Z82: 4 | AA82: 5 | AB82: 3 | AC82: 40 | AD82: =IFERROR(AVERAGE(IFERROR(IF(Z82="","",Z82*20),""),IFERROR(IF(AA82="","",AA82*20),""),IFERROR(IF(AB82="","",AB82*20),""),IFERROR(IF(AC82="","",IF(AC82>=85,100,IF(AC82>=70,90,IF(AC82>=55,75,IF(AC82>=40,60,IF(AC82>=25,40,20)))))),"")),"") | AE82: 3 | AF82: 4 | AG82: 3 | AH82: 4 | AI82: =IFERROR((AVERAGE(AE82,AF82,AG82,AH82,AL82)-1)*25,"") | AJ82: =IFERROR(J82*Weights!$B$4 + O82*Weights!$B$5 + S82*Weights!$B$6 + Y82*Weights!$B$7 + AD82*Weights!$B$8 + AI82*Weights!$B$9,"") | AK82: =IF(AJ82="","",IF(AJ82>=85,"✓✓✓",IF(AJ82>=70,"✓✓",IF(AJ82>=55,"✓",IF(AJ82>=40,"?","✗"))))) | AL82: 5
A83: POET | B83: POET Technologies Inc. | C83: 07 Optical, Networking & Interconnect / Optical components & transceivers | D83: 2026-10-11 | E83: -41 | F83: -8.47 | G83: -3.6 | H83: 704.17395 | I83: =IF(OR(E83="",R83="",R83<=0,E83<0),"",E83/R83) | J83: 27.3 | K83: -4.28 | L83: 100 | M83: -2538.03 | O83: 34.7 | P83: 24.82 | Q83: 112.3 | S83: =IFERROR(AVERAGE(IFERROR(IF(P83="","",IF(P83>=40,100,IF(P83>=30,90,IF(P83>=20,75,IF(P83>=15,60,IF(P83>=10,45,IF(P83>=5,30,15))))))),""),IFERROR(IF(Q83="","",IF(Q83>=40,100,IF(Q83>=30,90,IF(Q83>=20,75,IF(Q83>=10,60,IF(Q83>=5,45,IF(Q83>=0,30,15))))))),""),IFERROR(IF(R83="","",IF(R83>=40,100,IF(R83>=30,90,IF(R83>=20,75,IF(R83>=10,60,IF(R83>=0,45,IF(R83>=-10,30,15))))))),"")),"") | T83: 2 | U83: 2 | V83: 2 | W83: 2 | X83: 2 | Y83: =IFERROR((AVERAGE(T83,U83,V83,W83,X83)-1)*25,"") | Z83: 1 | AA83: 3 | AB83: 2 | AC83: 39.2 | AD83: =IFERROR(AVERAGE(IFERROR(IF(Z83="","",Z83*20),""),IFERROR(IF(AA83="","",AA83*20),""),IFERROR(IF(AB83="","",AB83*20),""),IFERROR(IF(AC83="","",IF(AC83>=85,100,IF(AC83>=70,90,IF(AC83>=55,75,IF(AC83>=40,60,IF(AC83>=25,40,20)))))),"")),"") | AE83: 3 | AF83: 4 | AG83: 4 | AH83: 2 | AI83: =IFERROR((AVERAGE(AE83,AF83,AG83,AH83,AL83)-1)*25,"") | AJ83: =IFERROR(J83*Weights!$B$4 + O83*Weights!$B$5 + S83*Weights!$B$6 + Y83*Weights!$B$7 + AD83*Weights!$B$8 + AI83*Weights!$B$9,"") | AK83: =IF(AJ83="","",IF(AJ83>=85,"✓✓✓",IF(AJ83>=70,"✓✓",IF(AJ83>=55,"✓",IF(AJ83>=40,"?","✗"))))) | AL83: 5
A84: ANET | B84: Arista Networks, Inc. | C84: 07 Optical, Networking & Interconnect / Networking systems | D84: 2026-10-11 | E84: 41.546066 | F84: 55.795 | G84: 1.89 | H84: 25.933311 | I84: =IF(OR(E84="",R84="",R84<=0,E84<0),"",E84/R84) | J84: 48.8 | K84: 21.8 | L84: 63 | M84: 48.91 | N84: -2.88 | O84: 90.6 | P84: 27.15 | Q84: 37.7 | R84: 36.5 | S84: =IFERROR(AVERAGE(IFERROR(IF(P84="","",IF(P84>=40,100,IF(P84>=30,90,IF(P84>=20,75,IF(P84>=15,60,IF(P84>=10,45,IF(P84>=5,30,15))))))),""),IFERROR(IF(Q84="","",IF(Q84>=40,100,IF(Q84>=30,90,IF(Q84>=20,75,IF(Q84>=10,60,IF(Q84>=5,45,IF(Q84>=0,30,15))))))),""),IFERROR(IF(R84="","",IF(R84>=40,100,IF(R84>=30,90,IF(R84>=20,75,IF(R84>=10,60,IF(R84>=0,45,IF(R84>=-10,30,15))))))),"")),"") | T84: 4 | U84: 5 | V84: 5 | W84: 5 | X84: 5 | Y84: =IFERROR((AVERAGE(T84,U84,V84,W84,X84)-1)*25,"") | Z84: 5 | AA84: 3 | AB84: 3 | AC84: 89.2 | AD84: =IFERROR(AVERAGE(IFERROR(IF(Z84="","",Z84*20),""),IFERROR(IF(AA84="","",AA84*20),""),IFERROR(IF(AB84="","",AB84*20),""),IFERROR(IF(AC84="","",IF(AC84>=85,100,IF(AC84>=70,90,IF(AC84>=55,75,IF(AC84>=40,60,IF(AC84>=25,40,20)))))),"")),"") | AE84: 3 | AF84: 4 | AG84: 5 | AH84: 4 | AI84: =IFERROR((AVERAGE(AE84,AF84,AG84,AH84,AL84)-1)*25,"") | AJ84: =IFERROR(J84*Weights!$B$4 + O84*Weights!$B$5 + S84*Weights!$B$6 + Y84*Weights!$B$7 + AD84*Weights!$B$8 + AI84*Weights!$B$9,"") | AK84: =IF(AJ84="","",IF(AJ84>=85,"✓✓✓",IF(AJ84>=70,"✓✓",IF(AJ84>=55,"✓",IF(AJ84>=40,"?","✗"))))) | AL84: 5
A85: CSCO | B85: Cisco Systems, Inc. | C85: 07 Optical, Networking & Interconnect / Networking systems | D85: 2026-10-11 | E85: 22.117122 | F85: 25.646 | G85: 2.74 | H85: 7.3709097 | I85: =IF(OR(E85="",R85="",R85<=0,E85<0),"",E85/R85) | J85: 65.7 | K85: 15.11 | L85: 64.52 | M85: 20.16 | N85: 0.82 | O85: 79.8 | P85: 3.57 | Q85: 17.6 | R85: 51.3 | S85: =IFERROR(AVERAGE(IFERROR(IF(P85="","",IF(P85>=40,100,IF(P85>=30,90,IF(P85>=20,75,IF(P85>=15,60,IF(P85>=10,45,IF(P85>=5,30,15))))))),""),IFERROR(IF(Q85="","",IF(Q85>=40,100,IF(Q85>=30,90,IF(Q85>=20,75,IF(Q85>=10,60,IF(Q85>=5,45,IF(Q85>=0,30,15))))))),""),IFERROR(IF(R85="","",IF(R85>=40,100,IF(R85>=30,90,IF(R85>=20,75,IF(R85>=10,60,IF(R85>=0,45,IF(R85>=-10,30,15))))))),"")),"") | T85: 2 | U85: 3 | V85: 4 | W85: 3 | X85: 3 | Y85: =IFERROR((AVERAGE(T85,U85,V85,W85,X85)-1)*25,"") | Z85: 3 | AA85: 3 | AB85: 3 | AC85: 59.2 | AD85: =IFERROR(AVERAGE(IFERROR(IF(Z85="","",Z85*20),""),IFERROR(IF(AA85="","",AA85*20),""),IFERROR(IF(AB85="","",AB85*20),""),IFERROR(IF(AC85="","",IF(AC85>=85,100,IF(AC85>=70,90,IF(AC85>=55,75,IF(AC85>=40,60,IF(AC85>=25,40,20)))))),"")),"") | AE85: 5 | AF85: 4 | AG85: 4 | AH85: 4 | AI85: =IFERROR((AVERAGE(AE85,AF85,AG85,AH85,AL85)-1)*25,"") | AJ85: =IFERROR(J85*Weights!$B$4 + O85*Weights!$B$5 + S85*Weights!$B$6 + Y85*Weights!$B$7 + AD85*Weights!$B$8 + AI85*Weights!$B$9,"") | AK85: =IF(AJ85="","",IF(AJ85>=85,"✓✓✓",IF(AJ85>=70,"✓✓",IF(AJ85>=55,"✓",IF(AJ85>=40,"?","✗"))))) | AL85: 5
A86: CIEN | B86: Ciena Corporation | C86: 07 Optical, Networking & Interconnect / Networking systems | D86: 2026-10-11 | E86: 38.024807 | F86: 62.373 | G86: 1.28 | H86: 10.593313 | I86: =IF(OR(E86="",R86="",R86<=0,E86<0),"",E86/R86) | J86: 48.5 | K86: 11.6 | L86: 44.07 | M86: 13.53 | N86: 0.64 | O86: 63.1 | P86: 9.5 | Q86: 37 | R86: 429.6 | S86: =IFERROR(AVERAGE(IFERROR(IF(P86="","",IF(P86>=40,100,IF(P86>=30,90,IF(P86>=20,75,IF(P86>=15,60,IF(P86>=10,45,IF(P86>=5,30,15))))))),""),IFERROR(IF(Q86="","",IF(Q86>=40,100,IF(Q86>=30,90,IF(Q86>=20,75,IF(Q86>=10,60,IF(Q86>=5,45,IF(Q86>=0,30,15))))))),""),IFERROR(IF(R86="","",IF(R86>=40,100,IF(R86>=30,90,IF(R86>=20,75,IF(R86>=10,60,IF(R86>=0,45,IF(R86>=-10,30,15))))))),"")),"") | T86: 4 | U86: 4 | V86: 4 | W86: 5 | X86: 4 | Y86: =IFERROR((AVERAGE(T86,U86,V86,W86,X86)-1)*25,"") | Z86: 5 | AA86: 5 | AB86: 3 | AC86: 35 | AD86: =IFERROR(AVERAGE(IFERROR(IF(Z86="","",Z86*20),""),IFERROR(IF(AA86="","",AA86*20),""),IFERROR(IF(AB86="","",AB86*20),""),IFERROR(IF(AC86="","",IF(AC86>=85,100,IF(AC86>=70,90,IF(AC86>=55,75,IF(AC86>=40,60,IF(AC86>=25,40,20)))))),"")),"") | AE86: 4 | AF86: 4 | AG86: 4 | AH86: 4 | AI86: =IFERROR((AVERAGE(AE86,AF86,AG86,AH86,AL86)-1)*25,"") | AJ86: =IFERROR(J86*Weights!$B$4 + O86*Weights!$B$5 + S86*Weights!$B$6 + Y86*Weights!$B$7 + AD86*Weights!$B$8 + AI86*Weights!$B$9,"") | AK86: =IF(AJ86="","",IF(AJ86>=85,"✓✓✓",IF(AJ86>=70,"✓✓",IF(AJ86>=55,"✓",IF(AJ86>=40,"?","✗"))))) | AL86: 5
A87: APH | B87: Amphenol Corporation | C87: 07 Optical, Networking & Interconnect / Cabling & physical layer | D87: 2026-10-11 | E87: 26.194736 | F87: 24.242 | G87: 2.15 | H87: 7.4153423 | I87: =IF(OR(E87="",R87="",R87<=0,E87<0),"",E87/R87) | J87: 69.3 | K87: 14.81 | L87: 38.95 | M87: 15.96 | N87: 1.42 | O87: 61.5 | P87: 22.31 | Q87: 55 | R87: 62.1 | S87: =IFERROR(AVERAGE(IFERROR(IF(P87="","",IF(P87>=40,100,IF(P87>=30,90,IF(P87>=20,75,IF(P87>=15,60,IF(P87>=10,45,IF(P87>=5,30,15))))))),""),IFERROR(IF(Q87="","",IF(Q87>=40,100,IF(Q87>=30,90,IF(Q87>=20,75,IF(Q87>=10,60,IF(Q87>=5,45,IF(Q87>=0,30,15))))))),""),IFERROR(IF(R87="","",IF(R87>=40,100,IF(R87>=30,90,IF(R87>=20,75,IF(R87>=10,60,IF(R87>=0,45,IF(R87>=-10,30,15))))))),"")),"") | T87: 3 | U87: 3 | V87: 4 | W87: 4 | X87: 4 | Y87: =IFERROR((AVERAGE(T87,U87,V87,W87,X87)-1)*25,"") | Z87: 4 | AA87: 1 | AB87: 3 | AC87: 74.2 | AD87: =IFERROR(AVERAGE(IFERROR(IF(Z87="","",Z87*20),""),IFERROR(IF(AA87="","",AA87*20),""),IFERROR(IF(AB87="","",AB87*20),""),IFERROR(IF(AC87="","",IF(AC87>=85,100,IF(AC87>=70,90,IF(AC87>=55,75,IF(AC87>=40,60,IF(AC87>=25,40,20)))))),"")),"") | AE87: 5 | AF87: 4 | AG87: 4 | AH87: 4 | AI87: =IFERROR((AVERAGE(AE87,AF87,AG87,AH87,AL87)-1)*25,"") | AJ87: =IFERROR(J87*Weights!$B$4 + O87*Weights!$B$5 + S87*Weights!$B$6 + Y87*Weights!$B$7 + AD87*Weights!$B$8 + AI87*Weights!$B$9,"") | AK87: =IF(AJ87="","",IF(AJ87>=85,"✓✓✓",IF(AJ87>=70,"✓✓",IF(AJ87>=55,"✓",IF(AJ87>=40,"?","✗"))))) | AL87: 5
A88: TEL | B88: TE Connectivity plc | C88: 07 Optical, Networking & Interconnect / Cabling & physical layer | D88: 2026-10-11 | E88: 16.834116 | F88: 13.575 | G88: 5.24 | H88: 3.2756002 | I88: =IF(OR(E88="",R88="",R88<=0,E88<0),"",E88/R88) | J88: 78.2 | K88: 14.8 | L88: 36.12 | M88: 17.16 | N88: 0.92 | O88: 59 | P88: 1.97 | Q88: 13.8 | S88: =IFERROR(AVERAGE(IFERROR(IF(P88="","",IF(P88>=40,100,IF(P88>=30,90,IF(P88>=20,75,IF(P88>=15,60,IF(P88>=10,45,IF(P88>=5,30,15))))))),""),IFERROR(IF(Q88="","",IF(Q88>=40,100,IF(Q88>=30,90,IF(Q88>=20,75,IF(Q88>=10,60,IF(Q88>=5,45,IF(Q88>=0,30,15))))))),""),IFERROR(IF(R88="","",IF(R88>=40,100,IF(R88>=30,90,IF(R88>=20,75,IF(R88>=10,60,IF(R88>=0,45,IF(R88>=-10,30,15))))))),"")),"") | T88: 2 | U88: 3 | V88: 3 | W88: 3 | X88: 3 | Y88: =IFERROR((AVERAGE(T88,U88,V88,W88,X88)-1)*25,"") | Z88: 4 | AA88: 2 | AB88: 3 | AC88: 39.2 | AD88: =IFERROR(AVERAGE(IFERROR(IF(Z88="","",Z88*20),""),IFERROR(IF(AA88="","",AA88*20),""),IFERROR(IF(AB88="","",AB88*20),""),IFERROR(IF(AC88="","",IF(AC88>=85,100,IF(AC88>=70,90,IF(AC88>=55,75,IF(AC88>=40,60,IF(AC88>=25,40,20)))))),"")),"") | AE88: 5 | AF88: 4 | AG88: 4 | AH88: 4 | AI88: =IFERROR((AVERAGE(AE88,AF88,AG88,AH88,AL88)-1)*25,"") | AJ88: =IFERROR(J88*Weights!$B$4 + O88*Weights!$B$5 + S88*Weights!$B$6 + Y88*Weights!$B$7 + AD88*Weights!$B$8 + AI88*Weights!$B$9,"") | AK88: =IF(AJ88="","",IF(AJ88>=85,"✓✓✓",IF(AJ88>=70,"✓✓",IF(AJ88>=55,"✓",IF(AJ88>=40,"?","✗"))))) | AL88: 5
A89: GLW | B89: Corning Incorporated | C89: 07 Optical, Networking & Interconnect / Cabling & physical layer | D89: 2026-10-11 | E89: 35.840588 | F89: 36.246 | G89: 1.78 | H89: 7.9396396 | I89: =IF(OR(E89="",R89="",R89<=0,E89<0),"",E89/R89) | J89: 47.1 | K89: 8.31 | L89: 36.39 | M89: 14.12 | N89: 1.68 | O89: 41 | P89: 3.27 | Q89: 16.6 | R89: 19.2 | S89: =IFERROR(AVERAGE(IFERROR(IF(P89="","",IF(P89>=40,100,IF(P89>=30,90,IF(P89>=20,75,IF(P89>=15,60,IF(P89>=10,45,IF(P89>=5,30,15))))))),""),IFERROR(IF(Q89="","",IF(Q89>=40,100,IF(Q89>=30,90,IF(Q89>=20,75,IF(Q89>=10,60,IF(Q89>=5,45,IF(Q89>=0,30,15))))))),""),IFERROR(IF(R89="","",IF(R89>=40,100,IF(R89>=30,90,IF(R89>=20,75,IF(R89>=10,60,IF(R89>=0,45,IF(R89>=-10,30,15))))))),"")),"") | T89: 4 | U89: 5 | V89: 5 | W89: 5 | X89: 5 | Y89: =IFERROR((AVERAGE(T89,U89,V89,W89,X89)-1)*25,"") | Z89: 4 | AA89: 5 | AB89: 3 | AC89: 55.8 | AD89: =IFERROR(AVERAGE(IFERROR(IF(Z89="","",Z89*20),""),IFERROR(IF(AA89="","",AA89*20),""),IFERROR(IF(AB89="","",AB89*20),""),IFERROR(IF(AC89="","",IF(AC89>=85,100,IF(AC89>=70,90,IF(AC89>=55,75,IF(AC89>=40,60,IF(AC89>=25,40,20)))))),"")),"") | AE89: 5 | AF89: 4 | AG89: 4 | AH89: 4 | AI89: =IFERROR((AVERAGE(AE89,AF89,AG89,AH89,AL89)-1)*25,"") | AJ89: =IFERROR(J89*Weights!$B$4 + O89*Weights!$B$5 + S89*Weights!$B$6 + Y89*Weights!$B$7 + AD89*Weights!$B$8 + AI89*Weights!$B$9,"") | AK89: =IF(AJ89="","",IF(AJ89>=85,"✓✓✓",IF(AJ89>=70,"✓✓",IF(AJ89>=55,"✓",IF(AJ89>=40,"?","✗"))))) | AL89: 5
A90: SMCI | B90: Super Micro Computer, Inc. | C90: 08 Servers, Systems & Liquid Cooling | D90: 2026-10-11 | E90: 8.6551548 | F90: 12.558 | G90: -25.75 | H90: 0.6931065 | I90: =IF(OR(E90="",R90="",R90<=0,E90<0),"",E90/R90) | J90: 74.2 | K90: 9.73 | L90: 10.82 | M90: -17.85 | N90: 0.61 | O90: 18.4 | P90: 76.34 | Q90: 93.2 | R90: 503.7 | S90: =IFERROR(AVERAGE(IFERROR(IF(P90="","",IF(P90>=40,100,IF(P90>=30,90,IF(P90>=20,75,IF(P90>=15,60,IF(P90>=10,45,IF(P90>=5,30,15))))))),""),IFERROR(IF(Q90="","",IF(Q90>=40,100,IF(Q90>=30,90,IF(Q90>=20,75,IF(Q90>=10,60,IF(Q90>=5,45,IF(Q90>=0,30,15))))))),""),IFERROR(IF(R90="","",IF(R90>=40,100,IF(R90>=30,90,IF(R90>=20,75,IF(R90>=10,60,IF(R90>=0,45,IF(R90>=-10,30,15))))))),"")),"") | T90: 5 | U90: 3 | V90: 3 | W90: 5 | X90: 4 | Y90: =IFERROR((AVERAGE(T90,U90,V90,W90,X90)-1)*25,"") | Z90: 5 | AA90: 1 | AB90: 3 | AC90: 61.7 | AD90: =IFERROR(AVERAGE(IFERROR(IF(Z90="","",Z90*20),""),IFERROR(IF(AA90="","",AA90*20),""),IFERROR(IF(AB90="","",AB90*20),""),IFERROR(IF(AC90="","",IF(AC90>=85,100,IF(AC90>=70,90,IF(AC90>=55,75,IF(AC90>=40,60,IF(AC90>=25,40,20)))))),"")),"") | AE90: 3 | AF90: 2 | AG90: 2 | AH90: 1 | AI90: =IFERROR((AVERAGE(AE90,AF90,AG90,AH90,AL90)-1)*25,"") | AJ90: =IFERROR(J90*Weights!$B$4 + O90*Weights!$B$5 + S90*Weights!$B$6 + Y90*Weights!$B$7 + AD90*Weights!$B$8 + AI90*Weights!$B$9,"") | AK90: =IF(AJ90="","",IF(AJ90>=85,"✓✓✓",IF(AJ90>=70,"✓✓",IF(AJ90>=55,"✓",IF(AJ90>=40,"?","✗"))))) | AL90: 5
A91: DELL | B91: Dell Technologies Inc. | C91: 08 Servers, Systems & Liquid Cooling | D91: 2026-10-11 | E91: 20.12767 | F91: 22.104 | G91: 2.3 | H91: 2.4644961 | I91: =IF(OR(E91="",R91="",R91<=0,E91<0),"",E91/R91) | J91: 61.9 | K91: 27.41 | L91: 19.91 | M91: 5.66 | N91: 1.34 | O91: 51.6 | P91: 3.53 | Q91: 57.7 | R91: 255.1 | S91: =IFERROR(AVERAGE(IFERROR(IF(P91="","",IF(P91>=40,100,IF(P91>=30,90,IF(P91>=20,75,IF(P91>=15,60,IF(P91>=10,45,IF(P91>=5,30,15))))))),""),IFERROR(IF(Q91="","",IF(Q91>=40,100,IF(Q91>=30,90,IF(Q91>=20,75,IF(Q91>=10,60,IF(Q91>=5,45,IF(Q91>=0,30,15))))))),""),IFERROR(IF(R91="","",IF(R91>=40,100,IF(R91>=30,90,IF(R91>=20,75,IF(R91>=10,60,IF(R91>=0,45,IF(R91>=-10,30,15))))))),"")),"") | T91: 3 | U91: 3 | V91: 4 | W91: 4 | X91: 4 | Y91: =IFERROR((AVERAGE(T91,U91,V91,W91,X91)-1)*25,"") | Z91: 4 | AA91: 4 | AB91: 3 | AC91: 98.3 | AD91: =IFERROR(AVERAGE(IFERROR(IF(Z91="","",Z91*20),""),IFERROR(IF(AA91="","",AA91*20),""),IFERROR(IF(AB91="","",AB91*20),""),IFERROR(IF(AC91="","",IF(AC91>=85,100,IF(AC91>=70,90,IF(AC91>=55,75,IF(AC91>=40,60,IF(AC91>=25,40,20)))))),"")),"") | AE91: 4 | AF91: 4 | AG91: 4 | AH91: 4 | AI91: =IFERROR((AVERAGE(AE91,AF91,AG91,AH91,AL91)-1)*25,"") | AJ91: =IFERROR(J91*Weights!$B$4 + O91*Weights!$B$5 + S91*Weights!$B$6 + Y91*Weights!$B$7 + AD91*Weights!$B$8 + AI91*Weights!$B$9,"") | AK91: =IF(AJ91="","",IF(AJ91>=85,"✓✓✓",IF(AJ91>=70,"✓✓",IF(AJ91>=55,"✓",IF(AJ91>=40,"?","✗"))))) | AL91: 5
A92: HPE | B92: Hewlett Packard Enterprise Company | C92: 08 Servers, Systems & Liquid Cooling | D92: 2026-10-11 | E92: 15.600644 | F92: 15.945 | G92: 4.26 | H92: 2.3289526 | I92: =IF(OR(E92="",R92="",R92<=0,E92<0),"",E92/R92) | J92: 81.9 | K92: 6.18 | L92: 36.62 | M92: 9.93 | N92: 2.05 | O92: 38.4 | P92: 6.37 | Q92: 33.7 | R92: 404.9 | S92: =IFERROR(AVERAGE(IFERROR(IF(P92="","",IF(P92>=40,100,IF(P92>=30,90,IF(P92>=20,75,IF(P92>=15,60,IF(P92>=10,45,IF(P92>=5,30,15))))))),""),IFERROR(IF(Q92="","",IF(Q92>=40,100,IF(Q92>=30,90,IF(Q92>=20,75,IF(Q92>=10,60,IF(Q92>=5,45,IF(Q92>=0,30,15))))))),""),IFERROR(IF(R92="","",IF(R92>=40,100,IF(R92>=30,90,IF(R92>=20,75,IF(R92>=10,60,IF(R92>=0,45,IF(R92>=-10,30,15))))))),"")),"") | T92: 3 | U92: 3 | V92: 4 | W92: 3 | X92: 4 | Y92: =IFERROR((AVERAGE(T92,U92,V92,W92,X92)-1)*25,"") | Z92: 2 | AA92: 3 | AB92: 3 | AC92: 99.2 | AD92: =IFERROR(AVERAGE(IFERROR(IF(Z92="","",Z92*20),""),IFERROR(IF(AA92="","",AA92*20),""),IFERROR(IF(AB92="","",AB92*20),""),IFERROR(IF(AC92="","",IF(AC92>=85,100,IF(AC92>=70,90,IF(AC92>=55,75,IF(AC92>=40,60,IF(AC92>=25,40,20)))))),"")),"") | AE92: 4 | AF92: 4 | AG92: 3 | AH92: 4 | AI92: =IFERROR((AVERAGE(AE92,AF92,AG92,AH92,AL92)-1)*25,"") | AJ92: =IFERROR(J92*Weights!$B$4 + O92*Weights!$B$5 + S92*Weights!$B$6 + Y92*Weights!$B$7 + AD92*Weights!$B$8 + AI92*Weights!$B$9,"") | AK92: =IF(AJ92="","",IF(AJ92>=85,"✓✓✓",IF(AJ92>=70,"✓✓",IF(AJ92>=55,"✓",IF(AJ92>=40,"?","✗"))))) | AL92: 5
A93: MSFT | B93: Microsoft Corporation | C93: 09 Compute-as-a-Service / Hyperscalers (public-cloud AI revenue) | D93: 2026-10-11 | E93: 24.613303 | F93: 20.52 | G93: 1.69 | H93: 11.973236 | I93: =IF(OR(E93="",R93="",R93<=0,E93<0),"",E93/R93) | J93: 70 | K93: 21.22 | L93: 67.94 | M93: 20.19 | N93: 0.27 | O93: 90.6 | P93: 16.12 | Q93: 17.7 | R93: 31.3 | S93: =IFERROR(AVERAGE(IFERROR(IF(P93="","",IF(P93>=40,100,IF(P93>=30,90,IF(P93>=20,75,IF(P93>=15,60,IF(P93>=10,45,IF(P93>=5,30,15))))))),""),IFERROR(IF(Q93="","",IF(Q93>=40,100,IF(Q93>=30,90,IF(Q93>=20,75,IF(Q93>=10,60,IF(Q93>=5,45,IF(Q93>=0,30,15))))))),""),IFERROR(IF(R93="","",IF(R93>=40,100,IF(R93>=30,90,IF(R93>=20,75,IF(R93>=10,60,IF(R93>=0,45,IF(R93>=-10,30,15))))))),"")),"") | T93: 3 | U93: 5 | V93: 5 | W93: 5 | X93: 5 | Y93: =IFERROR((AVERAGE(T93,U93,V93,W93,X93)-1)*25,"") | Z93: 3 | AA93: 5 | AB93: 4 | AC93: 71.7 | AD93: =IFERROR(AVERAGE(IFERROR(IF(Z93="","",Z93*20),""),IFERROR(IF(AA93="","",AA93*20),""),IFERROR(IF(AB93="","",AB93*20),""),IFERROR(IF(AC93="","",IF(AC93>=85,100,IF(AC93>=70,90,IF(AC93>=55,75,IF(AC93>=40,60,IF(AC93>=25,40,20)))))),"")),"") | AE93: 5 | AF93: 5 | AG93: 5 | AH93: 3 | AI93: =IFERROR((AVERAGE(AE93,AF93,AG93,AH93,AL93)-1)*25,"") | AJ93: =IFERROR(J93*Weights!$B$4 + O93*Weights!$B$5 + S93*Weights!$B$6 + Y93*Weights!$B$7 + AD93*Weights!$B$8 + AI93*Weights!$B$9,"") | AK93: =IF(AJ93="","",IF(AJ93>=85,"✓✓✓",IF(AJ93>=70,"✓✓",IF(AJ93>=55,"✓",IF(AJ93>=40,"?","✗"))))) | AL93: 5
A94: GOOGL | B94: Alphabet Inc. | C94: 09 Compute-as-a-Service / Hyperscalers (public-cloud AI revenue) | D94: 2026-10-11 | E94: 23.115559 | F94: 24.156 | G94: 1.24 | H94: 9.645901 | I94: =IF(OR(E94="",R94="",R94<=0,E94<0),"",E94/R94) | J94: 54 | K94: 15.14 | L94: 60.9 | M94: 11.95 | N94: -0.7 | O94: 83.1 | P94: 12.51 | Q94: 24.2 | S94: =IFERROR(AVERAGE(IFERROR(IF(P94="","",IF(P94>=40,100,IF(P94>=30,90,IF(P94>=20,75,IF(P94>=15,60,IF(P94>=10,45,IF(P94>=5,30,15))))))),""),IFERROR(IF(Q94="","",IF(Q94>=40,100,IF(Q94>=30,90,IF(Q94>=20,75,IF(Q94>=10,60,IF(Q94>=5,45,IF(Q94>=0,30,15))))))),""),IFERROR(IF(R94="","",IF(R94>=40,100,IF(R94>=30,90,IF(R94>=20,75,IF(R94>=10,60,IF(R94>=0,45,IF(R94>=-10,30,15))))))),"")),"") | T94: 3 | U94: 4 | V94: 5 | W94: 5 | X94: 5 | Y94: =IFERROR((AVERAGE(T94,U94,V94,W94,X94)-1)*25,"") | Z94: 4 | AA94: 4 | AB94: 3 | AC94: 45 | AD94: =IFERROR(AVERAGE(IFERROR(IF(Z94="","",Z94*20),""),IFERROR(IF(AA94="","",AA94*20),""),IFERROR(IF(AB94="","",AB94*20),""),IFERROR(IF(AC94="","",IF(AC94>=85,100,IF(AC94>=70,90,IF(AC94>=55,75,IF(AC94>=40,60,IF(AC94>=25,40,20)))))),"")),"") | AE94: 5 | AF94: 5 | AG94: 4 | AH94: 2 | AI94: =IFERROR((AVERAGE(AE94,AF94,AG94,AH94,AL94)-1)*25,"") | AJ94: =IFERROR(J94*Weights!$B$4 + O94*Weights!$B$5 + S94*Weights!$B$6 + Y94*Weights!$B$7 + AD94*Weights!$B$8 + AI94*Weights!$B$9,"") | AK94: =IF(AJ94="","",IF(AJ94>=85,"✓✓✓",IF(AJ94>=70,"✓✓",IF(AJ94>=55,"✓",IF(AJ94>=40,"?","✗"))))) | AL94: 5
A95: AMZN | B95: Amazon.com, Inc. | C95: 09 Compute-as-a-Service / Hyperscalers (public-cloud AI revenue) | D95: 2026-10-11 | E95: 25.073498 | F95: 17.359 | G95: -0.09 | H95: 3.6492524 | I95: =IF(OR(E95="",R95="",R95<=0,E95<0),"",E95/R95) | J95: 73.8 | K95: 9.66 | L95: 50.77 | M95: -0.32 | N95: 0.76 | O95: 75.6 | P95: 11.73 | Q95: 19.6 | S95: =IFERROR(AVERAGE(IFERROR(IF(P95="","",IF(P95>=40,100,IF(P95>=30,90,IF(P95>=20,75,IF(P95>=15,60,IF(P95>=10,45,IF(P95>=5,30,15))))))),""),IFERROR(IF(Q95="","",IF(Q95>=40,100,IF(Q95>=30,90,IF(Q95>=20,75,IF(Q95>=10,60,IF(Q95>=5,45,IF(Q95>=0,30,15))))))),""),IFERROR(IF(R95="","",IF(R95>=40,100,IF(R95>=30,90,IF(R95>=20,75,IF(R95>=10,60,IF(R95>=0,45,IF(R95>=-10,30,15))))))),"")),"") | T95: 3 | U95: 5 | V95: 5 | W95: 5 | X95: 5 | Y95: =IFERROR((AVERAGE(T95,U95,V95,W95,X95)-1)*25,"") | Z95: 5 | AA95: 3 | AB95: 3 | AC95: 53.3 | AD95: =IFERROR(AVERAGE(IFERROR(IF(Z95="","",Z95*20),""),IFERROR(IF(AA95="","",AA95*20),""),IFERROR(IF(AB95="","",AB95*20),""),IFERROR(IF(AC95="","",IF(AC95>=85,100,IF(AC95>=70,90,IF(AC95>=55,75,IF(AC95>=40,60,IF(AC95>=25,40,20)))))),"")),"") | AE95: 5 | AF95: 4 | AG95: 3 | AH95: 2 | AI95: =IFERROR((AVERAGE(AE95,AF95,AG95,AH95,AL95)-1)*25,"") | AJ95: =IFERROR(J95*Weights!$B$4 + O95*Weights!$B$5 + S95*Weights!$B$6 + Y95*Weights!$B$7 + AD95*Weights!$B$8 + AI95*Weights!$B$9,"") | AK95: =IF(AJ95="","",IF(AJ95>=85,"✓✓✓",IF(AJ95>=70,"✓✓",IF(AJ95>=55,"✓",IF(AJ95>=40,"?","✗"))))) | AL95: 5
A96: META | B96: Meta Platforms, Inc. | C96: 09 Compute-as-a-Service / Hyperscalers (public-cloud AI revenue) | D96: 2026-10-11 | E96: 20.80368 | F96: 16.959 | G96: 2.24 | H96: 8.021206 | I96: =IF(OR(E96="",R96="",R96<=0,E96<0),"",E96/R96) | J96: 69 | K96: 17.18 | L96: 81.75 | M96: 17.95 | N96: 0.2 | O96: 91.9 | P96: 19.89 | Q96: 28 | R96: -13.6 | S96: =IFERROR(AVERAGE(IFERROR(IF(P96="","",IF(P96>=40,100,IF(P96>=30,90,IF(P96>=20,75,IF(P96>=15,60,IF(P96>=10,45,IF(P96>=5,30,15))))))),""),IFERROR(IF(Q96="","",IF(Q96>=40,100,IF(Q96>=30,90,IF(Q96>=20,75,IF(Q96>=10,60,IF(Q96>=5,45,IF(Q96>=0,30,15))))))),""),IFERROR(IF(R96="","",IF(R96>=40,100,IF(R96>=30,90,IF(R96>=20,75,IF(R96>=10,60,IF(R96>=0,45,IF(R96>=-10,30,15))))))),"")),"") | T96: 3 | U96: 4 | V96: 5 | W96: 5 | X96: 5 | Y96: =IFERROR((AVERAGE(T96,U96,V96,W96,X96)-1)*25,"") | Z96: 5 | AA96: 5 | AB96: 3 | AC96: 44.2 | AD96: =IFERROR(AVERAGE(IFERROR(IF(Z96="","",Z96*20),""),IFERROR(IF(AA96="","",AA96*20),""),IFERROR(IF(AB96="","",AB96*20),""),IFERROR(IF(AC96="","",IF(AC96>=85,100,IF(AC96>=70,90,IF(AC96>=55,75,IF(AC96>=40,60,IF(AC96>=25,40,20)))))),"")),"") | AE96: 4 | AF96: 3 | AG96: 3 | AH96: 2 | AI96: =IFERROR((AVERAGE(AE96,AF96,AG96,AH96,AL96)-1)*25,"") | AJ96: =IFERROR(J96*Weights!$B$4 + O96*Weights!$B$5 + S96*Weights!$B$6 + Y96*Weights!$B$7 + AD96*Weights!$B$8 + AI96*Weights!$B$9,"") | AK96: =IF(AJ96="","",IF(AJ96>=85,"✓✓✓",IF(AJ96>=70,"✓✓",IF(AJ96>=55,"✓",IF(AJ96>=40,"?","✗"))))) | AL96: 5
A97: ORCL | B97: Oracle Corporation | C97: 09 Compute-as-a-Service / Hyperscalers (public-cloud AI revenue) | D97: 2026-10-11 | E97: 14.403056 | F97: 16.598 | G97: -6.7 | H97: 5.9721107 | I97: =IF(OR(E97="",R97="",R97<=0,E97<0),"",E97/R97) | J97: 80 | K97: 8.36 | L97: 63.96 | M97: -40.01 | N97: 3.84 | O97: 64.4 | P97: 10.48 | Q97: 29.6 | R97: 62.6 | S97: =IFERROR(AVERAGE(IFERROR(IF(P97="","",IF(P97>=40,100,IF(P97>=30,90,IF(P97>=20,75,IF(P97>=15,60,IF(P97>=10,45,IF(P97>=5,30,15))))))),""),IFERROR(IF(Q97="","",IF(Q97>=40,100,IF(Q97>=30,90,IF(Q97>=20,75,IF(Q97>=10,60,IF(Q97>=5,45,IF(Q97>=0,30,15))))))),""),IFERROR(IF(R97="","",IF(R97>=40,100,IF(R97>=30,90,IF(R97>=20,75,IF(R97>=10,60,IF(R97>=0,45,IF(R97>=-10,30,15))))))),"")),"") | T97: 3 | U97: 4 | V97: 4 | W97: 5 | X97: 5 | Y97: =IFERROR((AVERAGE(T97,U97,V97,W97,X97)-1)*25,"") | Z97: 3 | AA97: 2 | AB97: 3 | AC97: 50.8 | AD97: =IFERROR(AVERAGE(IFERROR(IF(Z97="","",Z97*20),""),IFERROR(IF(AA97="","",AA97*20),""),IFERROR(IF(AB97="","",AB97*20),""),IFERROR(IF(AC97="","",IF(AC97>=85,100,IF(AC97>=70,90,IF(AC97>=55,75,IF(AC97>=40,60,IF(AC97>=25,40,20)))))),"")),"") | AE97: 4 | AF97: 4 | AG97: 2 | AH97: 4 | AI97: =IFERROR((AVERAGE(AE97,AF97,AG97,AH97,AL97)-1)*25,"") | AJ97: =IFERROR(J97*Weights!$B$4 + O97*Weights!$B$5 + S97*Weights!$B$6 + Y97*Weights!$B$7 + AD97*Weights!$B$8 + AI97*Weights!$B$9,"") | AK97: =IF(AJ97="","",IF(AJ97>=85,"✓✓✓",IF(AJ97>=70,"✓✓",IF(AJ97>=55,"✓",IF(AJ97>=40,"?","✗"))))) | AL97: 5
A98: NBIS | B98: Nebius Group N.V. | C98: 09 Compute-as-a-Service / Neoclouds (AI-native cloud providers) | D98: 2026-10-11 | E98: -62.133045 | F98: 19.2 | G98: -10.48 | H98: 41.42076 | I98: =IF(OR(E98="",R98="",R98<=0,E98<0),"",E98/R98) | J98: 27.5 | K98: -2.16 | L98: 74.26 | M98: -434.2 | N98: 8.35 | O98: 55.8 | P98: 239.83 | Q98: 454 | S98: =IFERROR(AVERAGE(IFERROR(IF(P98="","",IF(P98>=40,100,IF(P98>=30,90,IF(P98>=20,75,IF(P98>=15,60,IF(P98>=10,45,IF(P98>=5,30,15))))))),""),IFERROR(IF(Q98="","",IF(Q98>=40,100,IF(Q98>=30,90,IF(Q98>=20,75,IF(Q98>=10,60,IF(Q98>=5,45,IF(Q98>=0,30,15))))))),""),IFERROR(IF(R98="","",IF(R98>=40,100,IF(R98>=30,90,IF(R98>=20,75,IF(R98>=10,60,IF(R98>=0,45,IF(R98>=-10,30,15))))))),"")),"") | T98: 5 | U98: 4 | V98: 3 | W98: 5 | X98: 5 | Y98: =IFERROR((AVERAGE(T98,U98,V98,W98,X98)-1)*25,"") | Z98: 3 | AA98: 5 | AB98: 3 | AC98: 65.8 | AD98: =IFERROR(AVERAGE(IFERROR(IF(Z98="","",Z98*20),""),IFERROR(IF(AA98="","",AA98*20),""),IFERROR(IF(AB98="","",AB98*20),""),IFERROR(IF(AC98="","",IF(AC98>=85,100,IF(AC98>=70,90,IF(AC98>=55,75,IF(AC98>=40,60,IF(AC98>=25,40,20)))))),"")),"") | AE98: 3 | AF98: 4 | AG98: 3 | AH98: 3 | AI98: =IFERROR((AVERAGE(AE98,AF98,AG98,AH98,AL98)-1)*25,"") | AJ98: =IFERROR(J98*Weights!$B$4 + O98*Weights!$B$5 + S98*Weights!$B$6 + Y98*Weights!$B$7 + AD98*Weights!$B$8 + AI98*Weights!$B$9,"") | AK98: =IF(AJ98="","",IF(AJ98>=85,"✓✓✓",IF(AJ98>=70,"✓✓",IF(AJ98>=55,"✓",IF(AJ98>=40,"?","✗"))))) | AL98: 5
A99: APLD | B99: Applied Digital Corporation | C99: 09 Compute-as-a-Service / Neoclouds (AI-native cloud providers) | D99: 2026-10-11 | E99: -30.187141 | F99: 6.3 | G99: -38.77 | H99: 8.209241 | I99: =IF(OR(E99="",R99="",R99<=0,E99<0),"",E99/R99) | J99: 32.5 | K99: -1.82 | L99: 21.62 | M99: -318.27 | O99: 30.6 | P99: 122.64 | Q99: 432.4 | S99: =IFERROR(AVERAGE(IFERROR(IF(P99="","",IF(P99>=40,100,IF(P99>=30,90,IF(P99>=20,75,IF(P99>=15,60,IF(P99>=10,45,IF(P99>=5,30,15))))))),""),IFERROR(IF(Q99="","",IF(Q99>=40,100,IF(Q99>=30,90,IF(Q99>=20,75,IF(Q99>=10,60,IF(Q99>=5,45,IF(Q99>=0,30,15))))))),""),IFERROR(IF(R99="","",IF(R99>=40,100,IF(R99>=30,90,IF(R99>=20,75,IF(R99>=10,60,IF(R99>=0,45,IF(R99>=-10,30,15))))))),"")),"") | T99: 4 | U99: 3 | V99: 3 | W99: 4 | X99: 3 | Y99: =IFERROR((AVERAGE(T99,U99,V99,W99,X99)-1)*25,"") | Z99: 2 | AA99: 5 | AB99: 3 | AC99: 40.8 | AD99: =IFERROR(AVERAGE(IFERROR(IF(Z99="","",Z99*20),""),IFERROR(IF(AA99="","",AA99*20),""),IFERROR(IF(AB99="","",AB99*20),""),IFERROR(IF(AC99="","",IF(AC99>=85,100,IF(AC99>=70,90,IF(AC99>=55,75,IF(AC99>=40,60,IF(AC99>=25,40,20)))))),"")),"") | AE99: 1 | AF99: 4 | AG99: 2 | AH99: 3 | AI99: =IFERROR((AVERAGE(AE99,AF99,AG99,AH99,AL99)-1)*25,"") | AJ99: =IFERROR(J99*Weights!$B$4 + O99*Weights!$B$5 + S99*Weights!$B$6 + Y99*Weights!$B$7 + AD99*Weights!$B$8 + AI99*Weights!$B$9,"") | AK99: =IF(AJ99="","",IF(AJ99>=85,"✓✓✓",IF(AJ99>=70,"✓✓",IF(AJ99>=55,"✓",IF(AJ99>=40,"?","✗"))))) | AL99: 5
A100: CORZ | B100: Core Scientific, Inc. | C100: 09 Compute-as-a-Service / Bitcoin miners pivoting to AI hosting | D100: 2026-10-11 | E100: 94.679276 | F100: 4.1 | G100: -19.34 | H100: 11.246269 | I100: =IF(OR(E100="",R100="",R100<=0,E100<0),"",E100/R100) | J100: 45 | K100: -6.46 | L100: 32.14 | M100: -217.53 | O100: 40.8 | P100: -20.72 | Q100: 108.8 | S100: =IFERROR(AVERAGE(IFERROR(IF(P100="","",IF(P100>=40,100,IF(P100>=30,90,IF(P100>=20,75,IF(P100>=15,60,IF(P100>=10,45,IF(P100>=5,30,15))))))),""),IFERROR(IF(Q100="","",IF(Q100>=40,100,IF(Q100>=30,90,IF(Q100>=20,75,IF(Q100>=10,60,IF(Q100>=5,45,IF(Q100>=0,30,15))))))),""),IFERROR(IF(R100="","",IF(R100>=40,100,IF(R100>=30,90,IF(R100>=20,75,IF(R100>=10,60,IF(R100>=0,45,IF(R100>=-10,30,15))))))),"")),"") | T100: 4 | U100: 3 | V100: 3 | W100: 5 | X100: 3 | Y100: =IFERROR((AVERAGE(T100,U100,V100,W100,X100)-1)*25,"") | Z100: 3 | AA100: 3 | AB100: 3 | AC100: 40.8 | AD100: =IFERROR(AVERAGE(IFERROR(IF(Z100="","",Z100*20),""),IFERROR(IF(AA100="","",AA100*20),""),IFERROR(IF(AB100="","",AB100*20),""),IFERROR(IF(AC100="","",IF(AC100>=85,100,IF(AC100>=70,90,IF(AC100>=55,75,IF(AC100>=40,60,IF(AC100>=25,40,20)))))),"")),"") | AE100: 1 | AF100: 4 | AG100: 3 | AH100: 3 | AI100: =IFERROR((AVERAGE(AE100,AF100,AG100,AH100,AL100)-1)*25,"") | AJ100: =IFERROR(J100*Weights!$B$4 + O100*Weights!$B$5 + S100*Weights!$B$6 + Y100*Weights!$B$7 + AD100*Weights!$B$8 + AI100*Weights!$B$9,"") | AK100: =IF(AJ100="","",IF(AJ100>=85,"✓✓✓",IF(AJ100>=70,"✓✓",IF(AJ100>=55,"✓",IF(AJ100>=40,"?","✗"))))) | AL100: 5
...

Sheet Rating Audit
A1: Date | B1: Ticker | C1: Dimension | D1: Rating | E1: Rationale | F1: Source | G1: Confidence | H1: Type
A2: 2026-05-17 | B2: CEG | C2: D1 | D2: 2 | E2: Current realized AI revenue ~5-10% of $30B TTM; MSFT TMI 20yr PPA is forward (restart 2028), not yet earnings. D4 carries the buildout side per D1/D4 split. | F2: yfinance info.totalRevenue; MSFT TMI press release 2024-09-20; CEG FY2025 10-K MD&A (to verify segment) | G2: Medium | H2: Initial
A3: 2026-05-17 | B3: CEG | C3: D2 | D3: 5 | E3: Operating nuclear baseload is structurally bottlenecked — ~94 US reactors total, CEG owns 22 GW (largest fleet); restart candidates limited; hyperscaler PPAs at premium vs merchant clearing prices demonstrate pricing power. | F3: Industry data; CEG FY2024 10-K Items 1-2; MSFT TMI PPA reportedly $100+/MWh vs PJM RT ~$30-50 | G3: High | H3: Initial
A4: 2026-05-17 | B4: CEG | C4: D3 | D4: 4 | E4: Multi-source moat: NRC operating licenses (regulatory), scale advantage on fixed O&M across 22 GW, long-dated PPA switching costs. Not 5 because gas portion (Calpine, post-2025) is unmoated commodity. Halo-check passed. | F4: 10-K Item 1 fleet description; rubric anchors (ASML/TSMC = true 5) | G4: High | H4: Initial
A5: 2026-05-17 | B5: CEG | C5: D4 | D5: 5 | E5: TMI restart capex funded and active; multiple nuclear uprates in progress; Calpine integration completed Jan 2025. Customer commitments (MSFT PPA) backing the spend. Negative FCF reflects buildout pace. | F5: TMI deal disclosures; CEG capex guidance in 2025 earnings releases; Calpine close announcement 2025-01 | G5: High | H5: Initial
A6: 2026-05-17 | B6: CEG | C6: D5 | D6: 4 | E6: MSFT anchor customer for TMI on 20yr PPA; public reporting indicates additional hyperscaler discussions. Realized hyperscaler revenue today modest (~5-15%); contracted forward exposure substantial. | F6: TMI deal disclosures; CEG FY2024 10-K (no explicit hyperscaler segment break — verify in FY2025) | G6: Medium | H6: Initial
A7: 2026-05-17 | B7: CEG | C7: M1 | D7: 3 | E7: Mixed revisions: near-term Q EPS estimate cut ~9% over 90d ($2.84→$2.585); FY estimates stable to slightly up; 7-day count 1 up vs 3 down. Net = neutral. | F7: yfinance Ticker.eps_trend, eps_revisions (pulled 2026-05-17) | G7: High | H7: Initial
A8: 2026-05-17 | B8: CEG | C8: M2 | D8: 2 | E8: Sector underperformance: −20.3pp vs XLU over 6mo (CEG −20.9%, XLU −0.6%); −33.6% drawdown from 52w high $402.32 (2025-10-15) to $267.20 (2026-05-15); −13.1pp lag vs XLU over 2yr. | F8: yfinance auto-adjusted close prices CEG vs XLU (pulled 2026-05-17) | G8: High | H8: Initial
A9: 2026-05-17 | B9: CEG | C9: M3 | D9: 2 | E9: 34 Form 4 filings past 12mo, pattern consistent with 10b5-1 + RSU withholding (quarterly clusters, multi-filer dates). ZERO open-market discretionary buys through 33.6% drawdown. Rubric: absence of buying during major drawdown is the diagnostic signal. | F9: SEC EDGAR Form 4 filings for CIK 0001868275, 2025-05 through 2026-04 (filings saved to per-stock/CEG/filings/; parser script has known bug for HTML-wrapped XML, pattern verified manually) | G9: Medium | H9: Initial
A10: 2026-05-17 | B10: CEG | C10: R1 | D10: 4 | E10: No customer >15% of revenue today — IPP sells predominantly into wholesale markets and via PPAs. MSFT becomes ~5% when TMI online 2028 — trajectory item; rating may shift toward 3 in future quarters. | F10: CEG FY2024 10-K customer disclosures; TMI deal economics | G10: Medium | H10: Initial
A11: 2026-05-17 | B11: CEG | C11: R2 | D11: 5 | E11: 100% US operations, no China revenue, no export-controlled technology, no BIS exposure. | F11: 10-K Item 1 geographic segment disclosure | G11: High | H11: Initial
A12: 2026-05-17 | B12: CEG | C12: R3 | D12: 3 | E12: ND/EBITDA 2.71x (info.totalDebt-based, includes operating leases); 0.67x using balance_sheet Total Debt. FCF −$4.5B (capex-driven, not distress). Quick ratio 0.48 (tight short-term). IG-rated. Holistic = sector-average. | F12: yfinance info + balance_sheet (pulled 2026-05-17); Moody's/S&P public ratings | G12: High | H12: Initial
A13: 2026-05-17 | B13: CEG | C13: R4 | D13: 4 | E13: No material company-specific litigation disclosed. NRC oversight is structural, not 'pending matters' per rubric. FERC co-location overhang (Nov-2024 AWS/Talen ISA rejection) is industry-policy thesis risk, captured in thesis.md §9, not R4. | F13: 10-K Item 3 Legal Proceedings; FERC Docket No. ER24-2172 ruling | G13: Medium | H13: Initial
... A1402: 2026-05-18 | B1402: CRM | C1402: D1 | D1402: 2 | E1402: [3 → 2] D1 correction. Agentforce ARR $800M / FY26 $41.5B = 1.9% AI mix strict. Adding Data 360 ARR = $2.9B / $41.5B = 7%. Original D1=3 mixed forward-looking narrative with current %. By strict rubric reading, 7% combined puts D1=2 (5-15% band). Methodology cleanup per Dom 2026-05-18. | F1402: D1 calibration pass 2026-05-18: strict rubric reading (% AI revenue of total) applied to Layer 10. Methodology cleanup, not thesis change. | G1402: High | H1402: Update
A1403: 2026-05-24 | B1403: SMR | C1403: D1. AI Rev % | D1403: 4 | E1403: 3 | F1403: Revenue $565K/qtr — essentially zero realized AI revenue. Downgrade from potential 25-50% to 10-25%. | G1403: Q1 2026 10-Q | H1403: High | I1403: Update
A1404: 2026-05-24 | B1404: SMR | C1404: D4. Capacity | D1404: 4 | E1404: 2 | F1404: ENTRA1 deal WAS the expansion story. ENTRA1 is 3-employee WeWork company with zero nuclear experience. TVA MOU non-binding. | G1404: Iceberg Research Nov 2025, Guggenheim | H1404: High | I1404: Update
A1405: 2026-05-24 | B1405: SMR | C1405: D5. Hyperscaler | D1405: 4 | E1405: 2 | F1405: No hyperscaler contracts. TVA/ENTRA1 path is indirect at best. | G1405: Company disclosures | H1405: High | I1405: Update
A1406: 2026-05-24 | B1406: SMR | C1406: M1. EPS Rev | D1406: 3 | E1406: 1 | F1406: Citi cut PT twice to $7 (Sell). Revenue forecast cut $76.2M→$59.9M. Multiple downgrades. | G1406: TipRanks, analyst actions | H1406: High | I1406: Update
A1407: 2026-05-24 | B1407: SMR | C1407: M3. Insider | D1407: 3 | E1407: 1 | F1407: Fluor fully exited — sold all 27M shares ($322M) in April. COO sold 49K shares. Zero buying. | G1407: SEC Form 4, April 2026 | H1407: High | I1407: Update
A1408: 2026-05-24 | B1408: SMR | C1408: R3. BS Risk | D1408: 3 | E1408: 2 | F1408: ~$1.0-1.2B liquidity but $346M+ still owed to ENTRA1 (total potential >$3B). ATM dilution ongoing. | G1408: Q1 2026 10-Q, ENTRA1 agreement | H1408: Medium | I1408: Update
A1409: 2026-05-24 | B1409: SMR | C1409: R4. Reg Risk | D1409: 4 | E1409: 1 | F1409: Active securities class action (Truedson v. NuScale). ENTRA1 governance flags (shared office, 3 employees, $495M for non-binding MOU). | G1409: Court filings, Iceberg Research | H1409: High | I1409: Update
A1410: 2026-05-24 | B1410: POET | C1410: D4. Capacity | D1410: 3 | E1410: 2 | F1410: Lost Marvell/Celestial AI for cause (confidentiality breach). Flagship customer gone; only $5M replacement order. | G1410: Marvell cancellation notice Apr 23 | H1410: High | I1410: Update
A1411: 2026-05-24 | B1411: POET | C1411: M2. Rel Str | D1411: 5 | E1411: 3 | F1411: Stock crashed 47% on Marvell cancellation, recovered somewhat. Extreme volatility. Roughly in-line with sector net of crash and recovery. | G1411: Yahoo Finance | H1411: Medium | I1411: Update
A1412: 2026-05-24 | B1412: POET | C1412: M3. Insider | D1412: 3 | E1412: 2 | F1412: Net selling ~$400K, zero buying during 133% run. CFO retiring with timing coinciding with PFIC controversy. | G1412: SEC Form 4, company PR | H1412: Medium | I1412: Update
A1413: 2026-05-24 | B1413: POET | C1413: R3. BS Risk | D1413: 2 | E1413: 4 | F1413: UPGRADE. Post-$400M offering: ~$430M+ cash, no debt, ~$9M/qtr burn = 12+ year runway. | G1413: Q1 2026 10-Q + offering terms | H1413: High | I1413: Update
A1414: 2026-05-24 | B1414: POET | C1414: R4. Reg Risk | D1414: 4 | E1414: 2 | F1414: Active class action (PFIC misrepresentation). Wolfpack short report. PFIC fixable via redomiciliation but legal overhang real. | G1414: Court filings, Wolfpack Research | H1414: Medium | I1414: Update
... A1420: 2026-05-24 | B1420: NEE | C1420: R4. Reg Risk | D1420: 4 | E1420: 2 | F1420: Same regulatory gauntlet as D. Virginia SCC highest risk. $1.778B customer credit package designed to buy approval. | G1420: E&E News, Clean Virginia | H1420: High | I1420: Update
A1421: 2026-05-25 | B1421: CRDO | C1421: D1 AI Rev % | D1421: 5 | E1421: ~100% revenue from AI infrastructure connectivity (AECs for GPU clusters) | F1421: Q3 FY2026 earnings call | G1421: High | H1421: Initial
A1422: 2026-05-25 | B1422: CRDO | C1422: D2 Position | D1422: 4 | E1422: Upstream with 2-4 competitors, validated IP via patent cross-licenses | F1422: Patent settlements 2025-2026 | G1422: Medium | H1422: Initial
A1423: 2026-05-25 | B1423: CRDO | C1423: D3 Moat | D1423: 4 | E1423: Proprietary SerDes IP, competitors chose to license. Share held at 5 hyperscalers | F1423: Cross-license settlements, customer wins | G1423: Medium | H1423: Initial
A1424: 2026-05-25 | B1424: CRDO | C1424: D4 Capacity | D1424: 4 | E1424: Fabless; DustPhotonics $750M+ acquisition expands into SiPho for CPO/NPO | F1424: DustPhotonics 8-K Apr 2026 | G1424: High | H1424: Initial
A1425: 2026-05-25 | B1425: CRDO | C1425: D5 Hyperscaler | D1425: 5 | E1425: Five hyperscaler customers, three >10% revenue. Combined >60% | F1425: Q1 FY2026 earnings call | G1425: High | H1425: Initial
A1426: 2026-05-25 | B1426: CRDO | C1426: M1 EPS Rev | D1426: 5 | E1426: Consistent massive beats all year. 16 Buy, 1 Hold, 0 Sell | F1426: MarketBeat analyst consensus | G1426: High | H1426: Initial
A1427: 2026-05-25 | B1427: CRDO | C1427: M2 Rel Str | D1427: 5 | E1427: Stock tripled in past year. >100% outperformance vs SOXX | F1427: Price data vs SOXX | G1427: High | H1427: Initial
A1428: 2026-05-25 | B1428: CRDO | C1428: M3 Insider | D1428: 3 | E1428: CTO sold ~$10M but retains >6M shares (<0.5% sold). Routine | F1428: Form 4 filings | G1428: Medium | H1428: Initial
A1429: 2026-05-25 | B1429: CRDO | C1429: R1 Cust Conc | D1429: 2 | E1429: Three customers each >10% revenue. Combined likely >50% | F1429: Q1 FY2026 earnings call | G1429: High | H1429: Initial
A1430: 2026-05-25 | B1430: CRDO | C1430: R2 Geo Risk | D1430: 4 | E1430: AECs not export-controlled. US hyperscaler customers. Cayman incorporation minor | F1430: Product classification | G1430: Medium | H1430: Initial
A1431: 2026-05-25 | B1431: CRDO | C1431: R3 BS Risk | D1431: 5 | E1431: Net cash. ND/EBITDA=-3.67. Fabless, low capital intensity | F1431: Q3 FY2026 balance sheet | G1431: High | H1431: Initial
A1432: 2026-05-25 | B1432: CRDO | C1432: R4 Reg Risk | D1432: 5 | E1432: All patent disputes settled. No regulatory overhangs | F1432: Settlement filings 2025-2026 | G1432: High | H1432: Initial
... A1741: 2026-06-05 | B1741: TEM | C1741: R4 | D1741: 2 | E1741: Spruce Point short report (accounting allegations) + dual-class governance + Lefkofsky promoter history + health-data privacy = material overhang. | F1741: Spruce Point May 2025; context briefing | G1741: Med | H1741: Initial
A1742: 2026-06-09 | B1742: ALL | C1742: Methodology | D1742: — | E1742: Added 4th Momentum metric: % of last 120 trading days with close > 50-day SMA (objective, from yfinance price history). Bands: ≥85→100, ≥70→90, ≥55→75, ≥40→60, ≥25→40, <25→20. Momentum Score now averages the 3 subjective ratings (×20) with the banded 50DMA score. Rationale: objectifies trend consistency; separates durable uptrends from one-gap bounces. Origin: external feedback reviewed 2026-06-09; 5 sibling suggestions declined (P/B, op margin, volume, inst. ownership, analyst PTs) — see session notes. Approved by Dom. | F1742: scripts/momentum_50dma.py; Methodology tab row 36 | G1742: High | H1742: Methodology change
A1743: 2026-06-10 | B1743: EQT | C1743: D1 | D1743: 1 | E1743: (was 5) Q1 2026 revenue 100% commodity (no 'data center' in 10-Q); two datacenter-linked supply deals are index-plus priced to power developers and don't flow until Shippingport fall-2026/Homer City 2028. ~0% current AI revenue. | F1743: EQT 10-Q Q1 2026 (2026-04-22); S&P Global 2025-07-21 | G1743: High | H1743: Update
A1744: 2026-06-10 | B1744: EQT | C1744: D2 | D1744: 2 | E1744: (was 5) Price-taker: index-plus/TETCO M-2 pricing, Q2 2026 strategic curtailments into weak prices; AI mechanism is in-basin basis (2nd-derivative). Scale+midstream are cost advantages, not pricing power. | F1744: EQT 10-Q Q1 2026; S&P Global 2025-07-21 | G1744: High | H1744: Update
A1745: 2026-06-10 | B1745: EQT | C1745: D5 | D1745: 2 | E1745: (was 5) No hyperscaler counterparty; deals are with power developers (Homer City Redevelopment, Frontier Group). Chain hyperscaler->unnamed tenant->developer->EQT gas = indirect. | F1745: Businesswire 2025-07-15; NGI | G1745: High | H1745: Update
A1746: 2026-06-10 | B1746: RRC | C1746: D1 | D1746: 1 | E1746: (was 4) ~0% current AI revenue; only signed power-linked deal is 75 MMcf/d to an unnamed Midwest power plant starting late 2027 (~5% of volumes when live), datacenter linkage unconfirmed. Q1 release: zero 'data center' mentions. | F1746: RRC 8-K 2026-04-21 & 2026-02-24 | G1746: High | H1746: Update
A1747: 2026-06-10 | B1747: RRC | C1747: D2 | D1747: 2 | E1747: (was 4) Structural price-taker, sells below Henry Hub (FY26 guide NYMEX -$0.35/-0.45); Q1 +$0.18 premium was seasonal. One unstarted premium contract on ~5% of volumes. | F1747: RRC 8-K 2026-04-21 | G1747: High | H1747: Update
A1748: 2026-06-10 | B1748: RRC | C1748: D5 | D1748: 1 | E1748: (was 4) Zero signed hyperscaler/developer deals; Fort Cherry alliance partners are frac-services + real-estate (no tenant named); NextEra South Mon 'potential participation' only. | F1748: Liberty Energy Apr 2025; RRC Q1 2026 call | G1748: High | H1748: Update
A1749: 2026-06-10 | B1749: AR | C1749: D1 | D1749: 1 | E1749: (was 4) ~0% current AI; Q1 2026 revenue 67% gas (LNG-corridor)/26% NGL (export)/2% oil, no datacenter mention in 10-Q. Only AI engagement is >5 Bcf/d of RFP participation, no wins. | F1749: AR 10-Q Q1 2026 (2026-04-29); Q1 call | G1749: High | H1749: Update
A1750: 2026-06-10 | B1750: AR | C1750: D2 | D1750: 2 | E1750: (was 4) Price-taker with superior logistics; premiums (90% Tier-1 points) derive from firm-transport + LNG/LPG export benchmarks, not negotiated with AI buyers. | F1750: AR 10-Q Q1 2026; investor materials | G1750: High | H1750: Update
A1751: 2026-06-10 | B1751: AR | C1751: D5 | D1751: 1 | E1751: (was 4) Zero signed hyperscaler/developer deals; closest is unnamed-counterparty RFPs + HG dry-gas 'optionality' + geographic-proximity narrative. | F1751: AR Q1 2026 call; 10-Q | G1751: High | H1751: Update
A1752: 2026-06-10 | B1752: EXE | C1752: D1 | D1752: 1 | E1752: (was 4) 0% direct AI; generous indirect ~1-3% via gas-demand share runs through Henry Hub (excluded by directness lens). 10-Q mentions 'data center' once, as a price driver not a customer. | F1752: EXE 10-Q Q1 2026 (2026-04-28) | G1752: High | H1752: Update
A1753: 2026-06-10 | B1753: EXE | C1753: D2 | D1753: 2 | E1753: (was 4) Price-taker, demonstrated: Q1 avg sales $4.92/Mcf vs NYMEX $5.04 (discount), hedges >65% of volumes, Delfin LNG SPA priced at Henry Hub. Scale = cost advantage not pricing power. | F1753: EXE 10-Q Q1 2026 | G1753: High | H1753: Update
A1754: 2026-06-10 | B1754: EXE | C1754: D5 | D1754: 1 | E1754: (was 4) Narrative-stage; no signed deal with a named hyperscaler/developer; negotiating with PJM power-provider intermediaries, unsigned. Peers (DTE, Energy Transfer) have signed deals EXE lacks. | F1754: EXE Q1 2026 call (2026-04-29) | G1754: High | H1754: Update
... A1811: 2026-06-10 | B1811: NNE | C1811: D5 | D1811: 2 | E1811: (was 4) AI-datacenter exposure is 100% narrative/MOU (Supermicro/EHC/DS Dansuk, all non-binding); a binding deal would file 8-K Item 1.01 -- none has. Named MOUs keep it above pure vapor. | F1811: NNE Q2 PR 2026-05-14; Supermicro MOU 2026-05-06 | G1811: High | H1811: Update
A1812: 2026-06-10 | B1812: CTRA | C1812: — | D1812: — | E1812: Removed from Watchlist: Coterra merged into Devon Energy (DVN) at 0.70 DVN/sh, consummated 2026-05-07, delisted NYSE same day. Pre-merger ratings retired (not re-scored — entity gone). Successor DVN is a separate new-name decision. | F1812: Globe and Mail / StockTitan 8-K 2026-05-07 | G1812: High | H1812: Removed
A1813: 2026-06-10 | B1813: GEV | C1813: D1 | D1813: 2 | E1813: (was 3) AI exposure is ORDERS/backlog not current revenue: $2.4B DC equipment orders ~=13% of Q1 orders, but disclosed current DC revenue is <10% of a broad grid+gas+wind co. Distinguish backlog from revenue. | F1813: GEV Q1 2026 8-K 2026-04-22 | G1813: Med | H1813: Update
A1814: 2026-06-10 | B1814: TER | C1814: D1 | D1814: 4 | E1814: (was 5) Genuine AI majority but trimmed for precision: ~70% of rev AI-related, SemiTest 87%, compute ~75% of SoC test -- but 'AI-related' is mgmt framing incl. non-AI HPC, and Robotics is non-AI. 25-50% band. | F1814: TER Q1 2026 8-K/call 2026-04-29 | G1814: High | H1814: Update
A1815: 2026-06-10 | B1815: TER | C1815: D5 | D1815: 3 | E1815: (was 4) Sells test to OSATs/IDMs/fabless, NOT hyperscalers; indirect pull from hyperscaler custom-silicon ASICs being tested keeps it at 3 (was 4, overstated a direct relationship). | F1815: TER Q1 2026 call | G1815: High | H1815: Update
A1816: 2026-06-10 | B1816: LRCX | C1816: D1 | D1816: 3 | E1816: (was 4) AI is a demand tailwind, not a disclosed revenue majority -- sells etch/dep into all WFE; AI-specific (adv packaging/HBM) is a modest slice of a broad cyclical base incl. NAND recovery. | F1816: LRCX Q3 FY2026 2026-04-22 | G1816: High | H1816: Update
A1817: 2026-06-10 | B1817: LRCX | C1817: D5 | D1817: 2 | E1817: (was 4) Sells to FABS (TSMC/Samsung/SK Hynix/Micron/Intel), zero direct hyperscaler relationship; 4 was narrative inflation. | F1817: LRCX Q3 FY2026 | G1817: High | H1817: Update
A1818: 2026-06-10 | B1818: ARM | C1818: D1 | D1818: 4 | E1818: (was 5) IP not equipment, but AI-infrastructure is still a minority: data-center royalty doubled YoY yet smartphone/IoT/auto remain the largest base; CSS to ~50% of royalties is FUTURE. | F1818: ARM FY2026 6-K 2026-05 | G1818: Med | H1818: Update
A1819: 2026-06-10 | B1819: ARM | C1819: D5 | D1819: 4 | E1819: (was 5) Most direct hyperscaler link in semicap (AWS Graviton/Google Axion/MSFT Cobalt pay per-chip royalties) but it's licensing not co-design, and hyperscalers are part of a minority data-center segment; 4 not 5. | F1819: ARM FY2026 6-K | G1819: High | H1819: Update
A1820: 2026-06-10 | B1820: ASML | C1820: D1 | D1820: 3 | E1820: (was 4) AI drives the demand/guidance but ASML sells litho into all advanced logic+DRAM; no disclosed AI line; EUV ~65% of sales is leading-edge broadly, only partly AI-specific. | F1820: ASML Q1 2026 2026-04-15 | G1820: High | H1820: Update
A1821: 2026-06-10 | B1821: ASML | C1821: D5 | D1821: 2 | E1821: (was 4) Sells exclusively to FABS (TSMC/Samsung/Intel/SK Hynix); no hyperscaler relationship; 4 was pure narrative inflation. D2=5 EUV monopoly intact. | F1821: ASML Q1 2026 | G1821: High | H1821: Update
A1822: 2026-06-10 | B1822: AMAT | C1822: D1 | D1822: 3 | E1822: (was 4) Same as LRCX: leading-edge/HBM/adv-packaging are the fastest-growing WFE but not a disclosed majority of a base that still includes large ICAPS/trailing-edge + China (non-AI). | F1822: AMAT Q2 FY2026 8-K 2026-05-14 | G1822: High | H1822: Update
A1823: 2026-06-10 | B1823: AMAT | C1823: D5 | D1823: 2 | E1823: (was 4) Sells to FABS not hyperscalers; no direct hyperscaler relationship; 4 inflated. | F1823: AMAT Q2 FY2026 8-K | G1823: High | H1823: Update
A1824: 2026-06-10 | B1824: TSM | C1824: D1 | D1824: 5 | E1824: (was 4) UPGRADE. HPC platform = 61% of Q1 2026 revenue (up from 55% prior qtr), overwhelmingly AI accelerator/datacenter wafers (NVDA/AMD/AVGO/custom-ASIC). Cleared >50%; old 4 was a stale sub-majority model. | F1824: TSMC Q1 2026 slides 2026-04-16 | G1824: High | H1824: Update
... A1939: 2026-06-12 | B1939: SHAZ | C1939: R4 | D1939: 2 | E1939: (SALP-13F batch add, Opus subagent research + orchestrator review) Bleecker Street short report (retracted NVIDIA-shareholder claim), CEO litigation history, de-SPAC supervoting (~65% votes/~1% economics). | F1939: SHAZ context briefing | G1939: Med | H1939: Proposal
A1940: 2026-06-12 | B1940: SHAZ | C1940: M1/M2/M3 | E1940: LEFT UNRATED — no sell-side coverage, 32 days of price history, squeeze-driven +~4,000% YTD; any momentum rating would be noise. Revisit after 2 full quarters. | F1940: SHAZ context briefing | G1940: High | H1940: Proposal
A1941: 2026-06-12 | B1941: HIVE | C1941: D1 | D1941: 2 | E1941: (SALP-13F batch add; subagent briefing + orchestrator completion — subagent stalled post-briefing) HPC $19.5M of $297.8M FY2026 revenue = 6.5% (5-10% band); mining ~93%. | F1941: HIVE FY2026 results PR 2026-06-02 | G1941: High | H1941: Proposal
A1942: 2026-06-12 | B1942: HIVE | C1942: D2 | D1942: 2 | E1942: (SALP-13F batch add; subagent briefing + orchestrator completion — subagent stalled post-briefing) BTC-mining-derived capacity is commodity; B200 GPU rental undifferentiated; edge is cheap Itaipu hydro + speed. | F1942: briefing s3/s6 | G1942: Med | H1942: Proposal
A1943: 2026-06-12 | B1943: HIVE | C1943: D3 | D1943: 2 | E1943: (SALP-13F batch add; subagent briefing + orchestrator completion — subagent stalled post-briefing) Moat = stranded-hydro cost position only; no defensible IP or switching costs. | F1943: briefing s6 | G1943: Med | H1943: Proposal
A1944: 2026-06-12 | B1944: HIVE | C1944: D4 | D1944: 4 | E1944: (SALP-13F batch add; subagent briefing + orchestrator completion — subagent stalled post-briefing) 400 MW Paraguay buildout + $115M 0% converts funded; held below 5 because the $3.5B GTA Gigafactory (the 2028 ARR bet) financing is NOT in place. DEBATABLE vs 5. | F1944: FY2026 PR; DCD Yguazu | G1944: Med | H1944: Proposal
A1945: 2026-06-12 | B1945: HIVE | C1945: D5 | D1945: 2 | E1945: (SALP-13F batch add; subagent briefing + orchestrator completion — subagent stalled post-briefing) Real but sub-scale AI-infra commitment (<$1B/yr capex tier); 5,500 GPUs, $35M contracted ARR. | F1945: FY2026 PR | G1945: Med | H1945: Proposal
A1946: 2026-06-12 | B1946: HIVE | C1946: M1 | D1946: 3 | E1946: (SALP-13F batch add; subagent briefing + orchestrator completion — subagent stalled post-briefing) PT raises post-print (B.Riley $8, Cantor $7 2x, KBW $5, Rosenblatt $5.50) but Q4 adj-EBITDA MISS (-$9.0M) and EPS deep loss; revisions are ARR-narrative, not EPS. DEBATABLE vs 4. | F1946: investing.com 2026-06 | G1946: Med | H1946: Proposal
A1947: 2026-06-12 | B1947: HIVE | C1947: M2 | D1947: 3 | E1947: (SALP-13F batch add; subagent briefing + orchestrator completion — subagent stalled post-briefing) +69.5% 3mo but +14.4% 6mo; 50DMA% 41.7 objective carries trend. Timeframe-sensitive. DEBATABLE vs 4. | F1947: yfinance; momentum_50dma | G1947: Med | H1947: Proposal
A1948: 2026-06-12 | B1948: HIVE | C1948: M3 | D1948: 2 | E1948: (SALP-13F batch add; subagent briefing + orchestrator completion — subagent stalled post-briefing) Pure selling, zero buys: Exec Chair Holmes sold 575K sh to ZERO (Mar-30), COO Rossy 215K to ZERO (Jun-8), Dir McGee 16.7K (Jun-3). Chairman+COO-to-zero exceeds routine diversification even under asymmetric weighting (BE 2026-05-17 principle). | F1948: gurufocus Form-4 coverage | G1948: High | H1948: Proposal
A1949: 2026-06-12 | B1949: HIVE | C1949: R1 | D1949: 3 | E1949: (SALP-13F batch add; subagent briefing + orchestrator completion — subagent stalled post-briefing) HPC ARR concentrated in few contracts (Bell Canada marquee); mining customer = BTC network (diffuse). Mixed. | F1949: briefing s6 | G1949: Med | H1949: Proposal
A1950: 2026-06-12 | B1950: HIVE | C1950: R2 | D1950: 3 | E1950: (SALP-13F batch add; subagent briefing + orchestrator completion — subagent stalled post-briefing) Asset leg: Paraguay = material EM sovereign/grid/currency exposure (300-400 MW campus); demand/policy legs clean. One-leg = 3 per R2 risk-leg tiering. | F1950: briefing s6; R2 rubric 2026-06-12 | G1950: Med | H1950: Proposal
A1951: 2026-06-12 | B1951: HIVE | C1951: R3 | D1951: 2 | E1951: (SALP-13F batch add; subagent briefing + orchestrator completion — subagent stalled post-briefing) GAAP net loss -$148M FY26, statement FCF -$116M, BTC-price-dependent cash engine (Q4 adj-EBITDA negative at $76K BTC); funds via dilution + 0% converts (Apr-26 $115M, exchange $2.57). ND/EBITDA -0.21 at FYE is PRE-notes — pro-forma debt ~$130-185M. | F1951: FY2026 PR balance sheet + notes | G1951: High | H1951: Proposal
A1952: 2026-06-12 | B1952: HIVE | C1952: R4 | D1952: 4 | E1952: (SALP-13F batch add; subagent briefing + orchestrator completion — subagent stalled post-briefing) No major disclosed overhang; crypto-regulatory backdrop sector-systemic. | F1952: briefing s6 | G1952: Med | H1952: Proposal
A1953: 2026-06-12 | B1953: SEI/TE/PSIX/PUMP/BW/WYFI/SHAZ/HIVE | C1953: ALL | E1953: Dom ACCEPTED all 94 batch proposals as rated, including flagged debatable calls (SEI D1/D5/M3, BW D1/R3, PUMP D4/D5/R1, PSIX D1/D5/R1, HIVE D4/M1/M2, WYFI EV/MW 70-MW basis, SHAZ all + momentum-unrated). Open verification items carried forward, not blockers: SEI M3 and BW M3 Form-4 confirmations. | F1953: Session 2026-06-12 | G1953: High | H1953: Accept
A1954: 2026-06-12 | B1954: GEV | C1954: D5 | D1954: 5 | E1954: (was 4; Dom accepted 2026-06-12 refresh proposal) Quantified multi-hyperscaler DC demand: $2.4B Q1 DC equipment orders (> all FY2025), ~20 GW of 100 GW gas backlog DC-tied, 56 GW slot reservations carrying $5.3B down payments. | F1954: per-stock/GEV/context-2026-06-12.md; 8-K 2026-05-22 | G1954: High | H1954: Update
A1955: 2026-06-12 | B1955: GEV | C1955: eps_yoy | E1955: INPUT BLANKED (was +1,768%) per new one-time-item rule (rule 15): dominated by ~$4.5B non-operating Prolec divestiture gain — scoring 100 on a divestiture is a garbage input. Growth now averages rev metrics only. NOTE: drops GEV 70.3 ✓✓ -> ~67.6 ✓ — data-honesty correction, not a rating change. | F1955: per-stock/GEV/context-2026-06-12.md; 10-Q | G1955: High | H1955: Update
A1956: 2026-06-12 | B1956: MPWR | C1956: D2 | D1956: 3 | E1956: (was 4; Dom accepted) 800V HVDC is a ~15-vendor contested field with Infineon leading and TI shipping complete architectures with NVIDIA; MPWR lost GB200 to Infineon — position is contested, not privileged. | F1956: per-stock/MPWR/context-2026-06-12.md; CNESA; TI PR 2026-03-16 | G1956: High | H1956: Update
A1957: 2026-06-12 | B1957: MPWR | C1957: M1 | D1957: 4 | E1957: (was 5; Dom accepted) Rosenblatt downgrade to Neutral on valuation/product-momentum reset; sentiment split. Guide still re-accelerating, hence 4 not 3. | F1957: TipRanks; Q1 2026 transcript | G1957: Med | H1957: Update
A1958: 2026-06-12 | B1958: MPWR | C1958: M3 | D1958: 2 | E1958: (was 3; Dom accepted) One-directional insider selling CONCURRENT with a restatement/material-weakness window mgmt did not address on the Q1 call — the case where selling carries signal (asymmetric-weighting principle still applied; this is not routine diversification). | F1958: per-stock/MPWR/context-2026-06-12.md; Form 4s | G1958: Med | H1958: Update
A1959: 2026-06-12 | B1959: MPWR | C1959: R4 | D1959: 3 | E1959: (was 4; Dom accepted) FY2024 + 4xFY2025 restatement and OPEN material weakness in deferred-tax controls (8-K 2026-02-26). Non-cash/tax-only but unresolved — not clean. | F1959: 8-K 2026-02-26; GuruFocus | G1959: High | H1959: Update
A1960: 2026-06-15 | B1960: QCOM | C1960: EPS YoY | D1960: BLANK | E1960: Rule 15: Q2 FY2026 GAAP EPS +173% dominated by ~$5.7B one-time deferred-tax valuation-allowance release (~$5.33/sh); non-GAAP EPS ~-7%. Mirror item: FY25 GAAP collapse on $7.1B allowance establishment. Non-operating-dominated → blanked; Growth averages revenue metrics. | F1960: per-stock/QCOM/context-2026-06-15.md; Q2 FY26 8-K | G1960: High | H1960: Initial
A1961: 2026-06-15 | B1961: NXPI | C1961: EPS YoY | D1961: BLANK | E1961: Rule 15: Q1 2026 GAAP EPS +130.7% dominated by $627M MEMS Sensors divestiture gain (sold for $878M cash); non-GAAP EPS +16% is operating reality. Non-operating-dominated → blanked. | F1961: per-stock/NXPI/context-2026-06-15.md; 10-Q + 8-K 2026-04-28 | G1961: High | H1961: Initial
A1962: 2026-06-15 | B1962: MCHP | C1962: EPS YoY | D1962: BLANK | E1962: Rule 15: Q4 FY2026 GAAP EPS $0.21 vs $(0.29) prior — sign-flip dominated by purchase accounting, restructuring, preferred dividends. Non-operating-dominated → blanked; Growth averages revenue metrics. | F1962: per-stock/MCHP/context-2026-06-15.md; 8-K EX-99.1 | G1962: High | H1962: Initial
A1963: 2026-06-15 | B1963: ON | C1963: EPS YoY | D1963: BLANK | E1963: Rule 15: Q1 2026 GAAP EPS -$0.08 vs -$1.15 — both periods GAAP losses dominated by restructuring/impairment ($539.3M opex Q1’25; $329.3M opex Q1’26). Non-GAAP +16% ($0.64 vs $0.55) is clean read. Non-operating-dominated → blanked. | F1963: per-stock/ON/context-2026-06-15.md; 10-Q ended 2026-04-03 | G1963: High | H1963: Initial
A1964: 2026-06-15 | B1964: TXN | C1964: EPS YoY | D1964: KEEP 31.3% | E1964: Rule 15 check: +31.3% ($1.68 vs $1.28) is operating-driven; ~$0.05 discrete tax benefit immaterial (~3%). Populated, not blanked. | F1964: per-stock/TXN/context-2026-06-15.md; Q1’26 call 2026-04-22 | G1964: High | H1964: Initial
A1965: 2026-06-15 | B1965: ADI | C1965: EPS YoY | D1965: KEEP 110.5% | E1965: Rule 15 check: +110.5% GAAP ($2.40 vs $1.14) operational; no divestiture/FV/tax one-off in last 4 qtrs (Empower is a cash use, not a gain). Populated, not blanked. | F1965: per-stock/ADI/context-2026-06-15.md; XBRL companyconcept | G1965: High | H1965: Initial
A1966: 2026-06-15 | B1966: STM | C1966: EPS YoY | D1966: KEEP -33.3% | E1966: Rule 15 check: -33.3% ($0.04 vs $0.06) operationally real (margin/restructuring/PPA) off a small base; not one-time-dominated. Populated, not blanked. | F1966: per-stock/STM/context-2026-06-15.md; ST Q1’26 6-K | G1966: Medium | H1966: Initial
A1967: 2026-06-15 | B1967: SWKS | C1967: EPS YoY | D1967: KEEP -44.2% | E1967: Rule 15 check: -44.2% GAAP ($0.24 vs $0.43) is operational (lower revenue + recurring amortization/restructuring), not one-time-dominated. Populated, not blanked. | F1967: per-stock/SWKS/context-2026-06-15.md; Q2 FY26 8-K | G1967: High | H1967: Initial
A1968: 2026-06-15 | B1968: TXN | C1968: D1 | D1968: 2 | E1968: ~6-7% datacenter (power/signal chain) +~90% YoY; core industrial/auto/PE | F1968: per-stock/TXN/context-2026-06-15.md | G1968: Med | H1968: Initial
A1969: 2026-06-15 | B1969: TXN | C1969: D2 | D1969: 4 | E1969: Analog scale/cost leader (300mm), broad sticky catalog, pricing firming | F1969: per-stock/TXN/context-2026-06-15.md | G1969: High | H1969: Initial
A1970: 2026-06-15 | B1970: TXN | C1970: D3 | D1970: 4 | E1970: Durable scale+breadth moat, design-in switching costs | F1970: per-stock/TXN/context-2026-06-15.md | G1970: High | H1970: Initial
A1971: 2026-06-15 | B1971: TXN | C1971: D4 | D1971: 5 | E1971: Funded multi-year megafab buildout (~26% capex/rev), customer-backed | F1971: per-stock/TXN/context-2026-06-15.md | G1971: High | H1971: Initial
...
